Workbook

Sheet Léeme
A1: Seguimiento a Oportunidades de Mejora (OM) de la Revisión por la Dirección — consolidado
A2: Universidad de Cundinamarca · Sistemas Integrados de Gestión · generado el 14/10/2026 desde el dataset de la web (generado el 2026-10-14).
A4: Hojas
A5: Por sistema | B5: Estado vigente de cada sistema y total global (= «Todos los sistemas» en la web).
A6: Por vigencia | B6: Estado vigente por sistema y vigencia (= gráfica «Avance promedio por vigencia»).
A7: Por corte | B7: Evolución por seguimiento: solo las OM evaluadas en cada corte (= gráficas de evolución).
A8: OM | B8: Una fila por oportunidad de mejora (162). Estado, avance, cumplida, atención y vencida con fórmulas.
A9: Seguimientos | B9: Una fila por seguimiento (1012), con la observación completa (la web la recorta a 400 caracteres).
A10: Escala | B10: Escala institucional 0 · 0,5 · 1 · 1,5 · 2 con su estado y avance.
A12: Cómo se calcula cada cifra (igual que los íconos «!» de la web)
A13: Avance de una OM | B13: Última calificación ÷ 2. Escala: 0 → 0 %, 0,5 → 25 %, 1 → 50 %, 1,5 → 75 %, 2 → 100 %. Una OM nunca calificada cuenta como 0 %.
A14: Avance promedio vigente | B14: Promedio del avance de cada OM. Cada OM pesa lo mismo; por eso el total global no es el promedio de los cinco sistemas.
A15: Tasa de cierre vigente | B15: OM cumplidas (última calificación = 2) ÷ total de OM. El avance parcial no suma.
A16: Sin cerrar / Atención | B16: Sin cerrar = OM − cumplidas. Atención = las sin cerrar con última calificación 0.
A17: Vencida | B17: Fecha de entrega anterior al último corte de seguimiento de su sistema y OM no cumplida. Una entrega registrada como texto («Inmediato») no se evalúa.
A18: Evolución por corte | B18: En cada corte, promedio y tasa de cierre de solo las OM evaluadas ese día. Si un libro repite la fecha de un corte, cuenta la última columna.
A19: Estado vigente vs. por corte | B19: «Vigente» describe cómo está hoy cada OM (todas). «Por corte» describe cómo salió un seguimiento (solo las evaluadas). Por eso pueden diferir: p. ej. SGSI 89,3 % vigente vs. 87,5 % en el corte del 30-sep-2026 (4 OM).
A21: Notas sobre los datos
A22: Fuente | B22: Libros de data/ (uno por sistema) más la actualización data/13-10-2026/SISTEMAS INTEGRADOS DE GESTION.xlsx, que aporta el corte del 30-sep-2026.
A23: SGSI 2025 | B23: Se descartaron dos cortes rotulados «30 DE DICIEMBRE 2026» (fecha futura, fuera de orden). Indicación del 13-10-2026.
A24: SG-SST 2025 | B24: La última columna de la hoja SST del libro 13-10-2026 decía «30 ABRIL 2026» y es el corte del 30-sep-2026. Reemplaza la segunda columna «30 ABRIL 2026» del libro de junio; por eso la PM 7 (ausente en el libro nuevo) queda en 0.
A25: SGC 2025 en el Excel original | B25: La fila de promedios de la hoja «SGC 2025» usa SUM(G2:G12)/COUNT(G2:G12) y deja fuera las PM 12 y 13. Este consolidado y la web promedian las 13 OM.
A26: Fechas de entrega | B26: Las escritas como texto («Inmediato», «IPA 2025») quedan sin fecha y no se evalúan para vencimiento. «31/06/2026» (SGC 2025, PM 3) no es una fecha válida: queda sin fecha.
A27: Recalcular | B27: Todas las cifras de Por sistema, Por vigencia, Por corte y las columnas calculadas de OM y Seguimientos son fórmulas: si se corrige una calificación en Seguimientos, todo se recalcula.

Sheet Por sistema
A1: Estado vigente de cada sistema
A2: Última calificación de cada OM. Mismas cifras que la tabla y los KPI de «Todos los sistemas» en la web.
A4: Sigla | B4: Sistema de gestión | C4: Vigencias | D4: Último corte | E4: OM | F4: Cumplidas | G4: Sin cerrar | H4: Atención | I4: Avance promedio vigente | J4: Tasa de cierre vigente | K4: Vencidas
A5: SGC | B5: Sistema de Gestión de Calidad | C5: 2022–2025 | D5: =SUMPRODUCT(MAX((Seguimientos!$C$2:$C$1013=A5)*Seguimientos!$F$2:$F$1013)) | E5: =COUNTIF(OM!$B$2:$B$163,A5) | F5: =COUNTIFS(OM!$B$2:$B$163,A5,OM!$R$2:$R$163,"Sí") | G5: =E5-F5 | H5: =COUNTIFS(OM!$B$2:$B$163,A5,OM!$S$2:$S$163,"Sí") | I5: =AVERAGEIF(OM!$B$2:$B$163,A5,OM!$P$2:$P$163) | J5: =IF(E5=0,"",F5/E5) | K5: =COUNTIFS(OM!$B$2:$B$163,A5,OM!$T$2:$T$163,"Sí")
A6: SGA | B6: Sistema de Gestión Ambiental | C6: 2022–2025 | D6: =SUMPRODUCT(MAX((Seguimientos!$C$2:$C$1013=A6)*Seguimientos!$F$2:$F$1013)) | E6: =COUNTIF(OM!$B$2:$B$163,A6) | F6: =COUNTIFS(OM!$B$2:$B$163,A6,OM!$R$2:$R$163,"Sí") | G6: =E6-F6 | H6: =COUNTIFS(OM!$B$2:$B$163,A6,OM!$S$2:$S$163,"Sí") | I6: =AVERAGEIF(OM!$B$2:$B$163,A6,OM!$P$2:$P$163) | J6: =IF(E6=0,"",F6/E6) | K6: =COUNTIFS(OM!$B$2:$B$163,A6,OM!$T$2:$T$163,"Sí")
A7: SG-SST | B7: Seguridad y Salud en el Trabajo | C7: 2023–2025 | D7: =SUMPRODUCT(MAX((Seguimientos!$C$2:$C$1013=A7)*Seguimientos!$F$2:$F$1013)) | E7: =COUNTIF(OM!$B$2:$B$163,A7) | F7: =COUNTIFS(OM!$B$2:$B$163,A7,OM!$R$2:$R$163,"Sí") | G7: =E7-F7 | H7: =COUNTIFS(OM!$B$2:$B$163,A7,OM!$S$2:$S$163,"Sí") | I7: =AVERAGEIF(OM!$B$2:$B$163,A7,OM!$P$2:$P$163) | J7: =IF(E7=0,"",F7/E7) | K7: =COUNTIFS(OM!$B$2:$B$163,A7,OM!$T$2:$T$163,"Sí")
A8: SGSI | B8: Seguridad de la Información | C8: 2023–2025 | D8: =SUMPRODUCT(MAX((Seguimientos!$C$2:$C$1013=A8)*Seguimientos!$F$2:$F$1013)) | E8: =COUNTIF(OM!$B$2:$B$163,A8) | F8: =COUNTIFS(OM!$B$2:$B$163,A8,OM!$R$2:$R$163,"Sí") | G8: =E8-F8 | H8: =COUNTIFS(OM!$B$2:$B$163,A8,OM!$S$2:$S$163,"Sí") | I8: =AVERAGEIF(OM!$B$2:$B$163,A8,OM!$P$2:$P$163) | J8: =IF(E8=0,"",F8/E8) | K8: =COUNTIFS(OM!$B$2:$B$163,A8,OM!$T$2:$T$163,"Sí")
A9: SGAS | B9: Sistema de Gestión Antisoborno | C9: 2024–2025 | D9: =SUMPRODUCT(MAX((Seguimientos!$C$2:$C$1013=A9)*Seguimientos!$F$2:$F$1013)) | E9: =COUNTIF(OM!$B$2:$B$163,A9) | F9: =COUNTIFS(OM!$B$2:$B$163,A9,OM!$R$2:$R$163,"Sí") | G9: =E9-F9 | H9: =COUNTIFS(OM!$B$2:$B$163,A9,OM!$S$2:$S$163,"Sí") | I9: =AVERAGEIF(OM!$B$2:$B$163,A9,OM!$P$2:$P$163) | J9: =IF(E9=0,"",F9/E9) | K9: =COUNTIFS(OM!$B$2:$B$163,A9,OM!$T$2:$T$163,"Sí")
A10: Total | B10: Todos los sistemas | D10: =MAX(D5:D9) | E10: =SUM(E5:E9) | F10: =SUM(F5:F9) | G10: =SUM(G5:G9) | H10: =SUM(H5:H9) | I10: =AVERAGE(OM!$P$2:$P$163) | J10: =IF(E10=0,"",F10/E10) | K10: =SUM(K5:K9)
A12: Avance promedio vigente: promedio de (última calificación ÷ 2) de cada OM; una nunca calificada cuenta como 0 %.
A13: Total: promedia todas las OM juntas (cada OM pesa lo mismo), igual que el KPI «Avance promedio global vigente».
A14: Tasa de cierre vigente: OM cumplidas (última calificación = 2) ÷ total de OM.
A15: Atención: OM sin cerrar con última calificación 0. Sin cerrar = OM − cumplidas.
A16: Vencidas: fecha de entrega anterior al último corte del sistema y OM no cumplida.

Sheet Por vigencia
A1: Estado vigente por sistema y vigencia
A2: Mismas cifras que la gráfica «Avance promedio por vigencia de la RXD» de cada tablero.
A4: Sistema | B4: Vigencia | C4: OM | D4: Cumplidas | E4: Sin cerrar | F4: Avance promedio vigente | G4: Tasa de cierre vigente
A5: SGC | B5: 2022 | C5: =COUNTIFS(OM!$B$2:$B$163,A5,OM!$D$2:$D$163,B5) | D5: =COUNTIFS(OM!$B$2:$B$163,A5,OM!$D$2:$D$163,B5,OM!$R$2:$R$163,"Sí") | E5: =C5-D5 | F5: =AVERAGEIFS(OM!$P$2:$P$163,OM!$B$2:$B$163,A5,OM!$D$2:$D$163,B5) | G5: =IF(C5=0,"",D5/C5)
A6: SGC | B6: 2023 | C6: =COUNTIFS(OM!$B$2:$B$163,A6,OM!$D$2:$D$163,B6) | D6: =COUNTIFS(OM!$B$2:$B$163,A6,OM!$D$2:$D$163,B6,OM!$R$2:$R$163,"Sí") | E6: =C6-D6 | F6: =AVERAGEIFS(OM!$P$2:$P$163,OM!$B$2:$B$163,A6,OM!$D$2:$D$163,B6) | G6: =IF(C6=0,"",D6/C6)
A7: SGC | B7: 2024 | C7: =COUNTIFS(OM!$B$2:$B$163,A7,OM!$D$2:$D$163,B7) | D7: =COUNTIFS(OM!$B$2:$B$163,A7,OM!$D$2:$D$163,B7,OM!$R$2:$R$163,"Sí") | E7: =C7-D7 | F7: =AVERAGEIFS(OM!$P$2:$P$163,OM!$B$2:$B$163,A7,OM!$D$2:$D$163,B7) | G7: =IF(C7=0,"",D7/C7)
A8: SGC | B8: 2025 | C8: =COUNTIFS(OM!$B$2:$B$163,A8,OM!$D$2:$D$163,B8) | D8: =COUNTIFS(OM!$B$2:$B$163,A8,OM!$D$2:$D$163,B8,OM!$R$2:$R$163,"Sí") | E8: =C8-D8 | F8: =AVERAGEIFS(OM!$P$2:$P$163,OM!$B$2:$B$163,A8,OM!$D$2:$D$163,B8) | G8: =IF(C8=0,"",D8/C8)
A9: SGA | B9: 2022 | C9: =COUNTIFS(OM!$B$2:$B$163,A9,OM!$D$2:$D$163,B9) | D9: =COUNTIFS(OM!$B$2:$B$163,A9,OM!$D$2:$D$163,B9,OM!$R$2:$R$163,"Sí") | E9: =C9-D9 | F9: =AVERAGEIFS(OM!$P$2:$P$163,OM!$B$2:$B$163,A9,OM!$D$2:$D$163,B9) | G9: =IF(C9=0,"",D9/C9)
A10: SGA | B10: 2023 | C10: =COUNTIFS(OM!$B$2:$B$163,A10,OM!$D$2:$D$163,B10) | D10: =COUNTIFS(OM!$B$2:$B$163,A10,OM!$D$2:$D$163,B10,OM!$R$2:$R$163,"Sí") | E10: =C10-D10 | F10: =AVERAGEIFS(OM!$P$2:$P$163,OM!$B$2:$B$163,A10,OM!$D$2:$D$163,B10) | G10: =IF(C10=0,"",D10/C10)
A11: SGA | B11: 2024 | C11: =COUNTIFS(OM!$B$2:$B$163,A11,OM!$D$2:$D$163,B11) | D11: =COUNTIFS(OM!$B$2:$B$163,A11,OM!$D$2:$D$163,B11,OM!$R$2:$R$163,"Sí") | E11: =C11-D11 | F11: =AVERAGEIFS(OM!$P$2:$P$163,OM!$B$2:$B$163,A11,OM!$D$2:$D$163,B11) | G11: =IF(C11=0,"",D11/C11)
A12: SGA | B12: 2025 | C12: =COUNTIFS(OM!$B$2:$B$163,A12,OM!$D$2:$D$163,B12) | D12: =COUNTIFS(OM!$B$2:$B$163,A12,OM!$D$2:$D$163,B12,OM!$R$2:$R$163,"Sí") | E12: =C12-D12 | F12: =AVERAGEIFS(OM!$P$2:$P$163,OM!$B$2:$B$163,A12,OM!$D$2:$D$163,B12) | G12: =IF(C12=0,"",D12/C12)
A13: SG-SST | B13: 2023 | C13: =COUNTIFS(OM!$B$2:$B$163,A13,OM!$D$2:$D$163,B13) | D13: =COUNTIFS(OM!$B$2:$B$163,A13,OM!$D$2:$D$163,B13,OM!$R$2:$R$163,"Sí") | E13: =C13-D13 | F13: =AVERAGEIFS(OM!$P$2:$P$163,OM!$B$2:$B$163,A13,OM!$D$2:$D$163,B13) | G13: =IF(C13=0,"",D13/C13)
A14: SG-SST | B14: 2024 | C14: =COUNTIFS(OM!$B$2:$B$163,A14,OM!$D$2:$D$163,B14) | D14: =COUNTIFS(OM!$B$2:$B$163,A14,OM!$D$2:$D$163,B14,OM!$R$2:$R$163,"Sí") | E14: =C14-D14 | F14: =AVERAGEIFS(OM!$P$2:$P$163,OM!$B$2:$B$163,A14,OM!$D$2:$D$163,B14) | G14: =IF(C14=0,"",D14/C14)
A15: SG-SST | B15: 2025 | C15: =COUNTIFS(OM!$B$2:$B$163,A15,OM!$D$2:$D$163,B15) | D15: =COUNTIFS(OM!$B$2:$B$163,A15,OM!$D$2:$D$163,B15,OM!$R$2:$R$163,"Sí") | E15: =C15-D15 | F15: =AVERAGEIFS(OM!$P$2:$P$163,OM!$B$2:$B$163,A15,OM!$D$2:$D$163,B15) | G15: =IF(C15=0,"",D15/C15)
A16: SGSI | B16: 2023 | C16: =COUNTIFS(OM!$B$2:$B$163,A16,OM!$D$2:$D$163,B16) | D16: =COUNTIFS(OM!$B$2:$B$163,A16,OM!$D$2:$D$163,B16,OM!$R$2:$R$163,"Sí") | E16: =C16-D16 | F16: =AVERAGEIFS(OM!$P$2:$P$163,OM!$B$2:$B$163,A16,OM!$D$2:$D$163,B16) | G16: =IF(C16=0,"",D16/C16)
... A20: SGAS | B20: 2025 | C20: =COUNTIFS(OM!$B$2:$B$163,A20,OM!$D$2:$D$163,B20) | D20: =COUNTIFS(OM!$B$2:$B$163,A20,OM!$D$2:$D$163,B20,OM!$R$2:$R$163,"Sí") | E20: =C20-D20 | F20: =AVERAGEIFS(OM!$P$2:$P$163,OM!$B$2:$B$163,A20,OM!$D$2:$D$163,B20) | G20: =IF(C20=0,"",D20/C20)

Sheet Por corte
A1: Evolución por seguimiento
A2: En cada corte cuentan solo las OM evaluadas ese día. Mismas cifras que las gráficas de evolución (una línea por vigencia) y que la fila de promedios de cada hoja del libro de seguimiento.
A4: Sistema | B4: Vigencia | C4: Fecha de corte | D4: OM evaluadas | E4: Cumplidas | F4: Avance promedio | G4: Tasa de cierre
A5: SGC | B5: 2022 | C5: 45133 | D5: =COUNTIFS(Seguimientos!$C$2:$C$1013,A5,Seguimientos!$D$2:$D$1013,B5,Seguimientos!$F$2:$F$1013,C5,Seguimientos!$J$2:$J$1013,1) | E5: =COUNTIFS(Seguimientos!$C$2:$C$1013,A5,Seguimientos!$D$2:$D$1013,B5,Seguimientos!$F$2:$F$1013,C5,Seguimientos!$J$2:$J$1013,1,Seguimientos!$H$2:$H$1013,2) | F5: =IF(D5=0,"",AVERAGEIFS(Seguimientos!$I$2:$I$1013,Seguimientos!$C$2:$C$1013,A5,Seguimientos!$D$2:$D$1013,B5,Seguimientos!$F$2:$F$1013,C5,Seguimientos!$J$2:$J$1013,1)) | G5: =IF(D5=0,"",E5/D5)
A6: SGC | B6: 2022 | C6: 45245 | D6: =COUNTIFS(Seguimientos!$C$2:$C$1013,A6,Seguimientos!$D$2:$D$1013,B6,Seguimientos!$F$2:$F$1013,C6,Seguimientos!$J$2:$J$1013,1) | E6: =COUNTIFS(Seguimientos!$C$2:$C$1013,A6,Seguimientos!$D$2:$D$1013,B6,Seguimientos!$F$2:$F$1013,C6,Seguimientos!$J$2:$J$1013,1,Seguimientos!$H$2:$H$1013,2) | F6: =IF(D6=0,"",AVERAGEIFS(Seguimientos!$I$2:$I$1013,Seguimientos!$C$2:$C$1013,A6,Seguimientos!$D$2:$D$1013,B6,Seguimientos!$F$2:$F$1013,C6,Seguimientos!$J$2:$J$1013,1)) | G6: =IF(D6=0,"",E6/D6)
A7: SGC | B7: 2022 | C7: 45405 | D7: =COUNTIFS(Seguimientos!$C$2:$C$1013,A7,Seguimientos!$D$2:$D$1013,B7,Seguimientos!$F$2:$F$1013,C7,Seguimientos!$J$2:$J$1013,1) | E7: =COUNTIFS(Seguimientos!$C$2:$C$1013,A7,Seguimientos!$D$2:$D$1013,B7,Seguimientos!$F$2:$F$1013,C7,Seguimientos!$J$2:$J$1013,1,Seguimientos!$H$2:$H$1013,2) | F7: =IF(D7=0,"",AVERAGEIFS(Seguimientos!$I$2:$I$1013,Seguimientos!$C$2:$C$1013,A7,Seguimientos!$D$2:$D$1013,B7,Seguimientos!$F$2:$F$1013,C7,Seguimientos!$J$2:$J$1013,1)) | G7: =IF(D7=0,"",E7/D7)
A8: SGC | B8: 2022 | C8: 45497 | D8: =COUNTIFS(Seguimientos!$C$2:$C$1013,A8,Seguimientos!$D$2:$D$1013,B8,Seguimientos!$F$2:$F$1013,C8,Seguimientos!$J$2:$J$1013,1) | E8: =COUNTIFS(Seguimientos!$C$2:$C$1013,A8,Seguimientos!$D$2:$D$1013,B8,Seguimientos!$F$2:$F$1013,C8,Seguimientos!$J$2:$J$1013,1,Seguimientos!$H$2:$H$1013,2) | F8: =IF(D8=0,"",AVERAGEIFS(Seguimientos!$I$2:$I$1013,Seguimientos!$C$2:$C$1013,A8,Seguimientos!$D$2:$D$1013,B8,Seguimientos!$F$2:$F$1013,C8,Seguimientos!$J$2:$J$1013,1)) | G8: =IF(D8=0,"",E8/D8)
A9: SGC | B9: 2022 | C9: 45583 | D9: =COUNTIFS(Seguimientos!$C$2:$C$1013,A9,Seguimientos!$D$2:$D$1013,B9,Seguimientos!$F$2:$F$1013,C9,Seguimientos!$J$2:$J$1013,1) | E9: =COUNTIFS(Seguimientos!$C$2:$C$1013,A9,Seguimientos!$D$2:$D$1013,B9,Seguimientos!$F$2:$F$1013,C9,Seguimientos!$J$2:$J$1013,1,Seguimientos!$H$2:$H$1013,2) | F9: =IF(D9=0,"",AVERAGEIFS(Seguimientos!$I$2:$I$1013,Seguimientos!$C$2:$C$1013,A9,Seguimientos!$D$2:$D$1013,B9,Seguimientos!$F$2:$F$1013,C9,Seguimientos!$J$2:$J$1013,1)) | G9: =IF(D9=0,"",E9/D9)
A10: SGC | B10: 2022 | C10: 45777 | D10: =COUNTIFS(Seguimientos!$C$2:$C$1013,A10,Seguimientos!$D$2:$D$1013,B10,Seguimientos!$F$2:$F$1013,C10,Seguimientos!$J$2:$J$1013,1) | E10: =COUNTIFS(Seguimientos!$C$2:$C$1013,A10,Seguimientos!$D$2:$D$1013,B10,Seguimientos!$F$2:$F$1013,C10,Seguimientos!$J$2:$J$1013,1,Seguimientos!$H$2:$H$1013,2) | F10: =IF(D10=0,"",AVERAGEIFS(Seguimientos!$I$2:$I$1013,Seguimientos!$C$2:$C$1013,A10,Seguimientos!$D$2:$D$1013,B10,Seguimientos!$F$2:$F$1013,C10,Seguimientos!$J$2:$J$1013,1)) | G10: =IF(D10=0,"",E10/D10)
A11: SGC | B11: 2022 | C11: 45838 | D11: =COUNTIFS(Seguimientos!$C$2:$C$1013,A11,Seguimientos!$D$2:$D$1013,B11,Seguimientos!$F$2:$F$1013,C11,Seguimientos!$J$2:$J$1013,1) | E11: =COUNTIFS(Seguimientos!$C$2:$C$1013,A11,Seguimientos!$D$2:$D$1013,B11,Seguimientos!$F$2:$F$1013,C11,Seguimientos!$J$2:$J$1013,1,Seguimientos!$H$2:$H$1013,2) | F11: =IF(D11=0,"",AVERAGEIFS(Seguimientos!$I$2:$I$1013,Seguimientos!$C$2:$C$1013,A11,Seguimientos!$D$2:$D$1013,B11,Seguimientos!$F$2:$F$1013,C11,Seguimientos!$J$2:$J$1013,1)) | G11: =IF(D11=0,"",E11/D11)
A12: SGC | B12: 2022 | C12: 45930 | D12: =COUNTIFS(Seguimientos!$C$2:$C$1013,A12,Seguimientos!$D$2:$D$1013,B12,Seguimientos!$F$2:$F$1013,C12,Seguimientos!$J$2:$J$1013,1) | E12: =COUNTIFS(Seguimientos!$C$2:$C$1013,A12,Seguimientos!$D$2:$D$1013,B12,Seguimientos!$F$2:$F$1013,C12,Seguimientos!$J$2:$J$1013,1,Seguimientos!$H$2:$H$1013,2) | F12: =IF(D12=0,"",AVERAGEIFS(Seguimientos!$I$2:$I$1013,Seguimientos!$C$2:$C$1013,A12,Seguimientos!$D$2:$D$1013,B12,Seguimientos!$F$2:$F$1013,C12,Seguimientos!$J$2:$J$1013,1)) | G12: =IF(D12=0,"",E12/D12)
A13: SGC | B13: 2023 | C13: 45405 | D13: =COUNTIFS(Seguimientos!$C$2:$C$1013,A13,Seguimientos!$D$2:$D$1013,B13,Seguimientos!$F$2:$F$1013,C13,Seguimientos!$J$2:$J$1013,1) | E13: =COUNTIFS(Seguimientos!$C$2:$C$1013,A13,Seguimientos!$D$2:$D$1013,B13,Seguimientos!$F$2:$F$1013,C13,Seguimientos!$J$2:$J$1013,1,Seguimientos!$H$2:$H$1013,2) | F13: =IF(D13=0,"",AVERAGEIFS(Seguimientos!$I$2:$I$1013,Seguimientos!$C$2:$C$1013,A13,Seguimientos!$D$2:$D$1013,B13,Seguimientos!$F$2:$F$1013,C13,Seguimientos!$J$2:$J$1013,1)) | G13: =IF(D13=0,"",E13/D13)
A14: SGC | B14: 2023 | C14: 45497 | D14: =COUNTIFS(Seguimientos!$C$2:$C$1013,A14,Seguimientos!$D$2:$D$1013,B14,Seguimientos!$F$2:$F$1013,C14,Seguimientos!$J$2:$J$1013,1) | E14: =COUNTIFS(Seguimientos!$C$2:$C$1013,A14,Seguimientos!$D$2:$D$1013,B14,Seguimientos!$F$2:$F$1013,C14,Seguimientos!$J$2:$J$1013,1,Seguimientos!$H$2:$H$1013,2) | F14: =IF(D14=0,"",AVERAGEIFS(Seguimientos!$I$2:$I$1013,Seguimientos!$C$2:$C$1013,A14,Seguimientos!$D$2:$D$1013,B14,Seguimientos!$F$2:$F$1013,C14,Seguimientos!$J$2:$J$1013,1)) | G14: =IF(D14=0,"",E14/D14)
A15: SGC | B15: 2023 | C15: 45583 | D15: =COUNTIFS(Seguimientos!$C$2:$C$1013,A15,Seguimientos!$D$2:$D$1013,B15,Seguimientos!$F$2:$F$1013,C15,Seguimientos!$J$2:$J$1013,1) | E15: =COUNTIFS(Seguimientos!$C$2:$C$1013,A15,Seguimientos!$D$2:$D$1013,B15,Seguimientos!$F$2:$F$1013,C15,Seguimientos!$J$2:$J$1013,1,Seguimientos!$H$2:$H$1013,2) | F15: =IF(D15=0,"",AVERAGEIFS(Seguimientos!$I$2:$I$1013,Seguimientos!$C$2:$C$1013,A15,Seguimientos!$D$2:$D$1013,B15,Seguimientos!$F$2:$F$1013,C15,Seguimientos!$J$2:$J$1013,1)) | G15: =IF(D15=0,"",E15/D15)
A16: SGC | B16: 2023 | C16: 45777 | D16: =COUNTIFS(Seguimientos!$C$2:$C$1013,A16,Seguimientos!$D$2:$D$1013,B16,Seguimientos!$F$2:$F$1013,C16,Seguimientos!$J$2:$J$1013,1) | E16: =COUNTIFS(Seguimientos!$C$2:$C$1013,A16,Seguimientos!$D$2:$D$1013,B16,Seguimientos!$F$2:$F$1013,C16,Seguimientos!$J$2:$J$1013,1,Seguimientos!$H$2:$H$1013,2) | F16: =IF(D16=0,"",AVERAGEIFS(Seguimientos!$I$2:$I$1013,Seguimientos!$C$2:$C$1013,A16,Seguimientos!$D$2:$D$1013,B16,Seguimientos!$F$2:$F$1013,C16,Seguimientos!$J$2:$J$1013,1)) | G16: =IF(D16=0,"",E16/D16)
... A90: SGAS | B90: 2025 | C90: 46295 | D90: =COUNTIFS(Seguimientos!$C$2:$C$1013,A90,Seguimientos!$D$2:$D$1013,B90,Seguimientos!$F$2:$F$1013,C90,Seguimientos!$J$2:$J$1013,1) | E90: =COUNTIFS(Seguimientos!$C$2:$C$1013,A90,Seguimientos!$D$2:$D$1013,B90,Seguimientos!$F$2:$F$1013,C90,Seguimientos!$J$2:$J$1013,1,Seguimientos!$H$2:$H$1013,2) | F90: =IF(D90=0,"",AVERAGEIFS(Seguimientos!$I$2:$I$1013,Seguimientos!$C$2:$C$1013,A90,Seguimientos!$D$2:$D$1013,B90,Seguimientos!$F$2:$F$1013,C90,Seguimientos!$J$2:$J$1013,1)) | G90: =IF(D90=0,"",E90/D90)

Sheet OM
A1: ID OM | B1: Sistema | C1: Nombre del sistema | D1: Vigencia | E1: PM N° | F1: Oportunidad de mejora | G1: Responsable | H1: Áreas | I1: Entregable | J1: Entrega comprometida (texto) | K1: Fecha de entrega | L1: Seguimientos | M1: N.º último calificado | N1: Fecha último corte calificado | O1: Última calificación | P1: Avance vigente | Q1: Estado vigente | R1: Cumplida | S1: Atención (sin avance) | T1: Vencida
A2: sgc-2022-1 | B2: SGC | C2: Sistema de Gestión de Calidad | D2: 2022 | E2: 1 | F2: Se evidencia un comportamiento estable de las salidas no conformes entre 2021-2022; sin embargo, en los seguimientos no se cuenta con el aseguramiento de cubrir a la totalidad de las partes interesadas. | G2: Oficina de calidad – procesos a los que aplica SNC | H2: Calidad | I2: Actualizar los procedimientos e instructivos de salidas no conformes de los procesos, para incluir actividades de verificación de conformidad posterior a su tratamiento. | J2: 45078 | K2: 45078 | L2: =COUNTIF(Seguimientos!$A$2:$A$1013,A2) | M2: =SUMPRODUCT(MAX((Seguimientos!$A$2:$A$1013=A2)*(Seguimientos!$H$2:$H$1013<>"")*Seguimientos!$B$2:$B$1013)) | N2: =IF(M2=0,"",INDEX(Seguimientos!$F$2:$F$1013,MATCH(A2&"|"&M2,Seguimientos!$K$2:$K$1013,0))) | O2: =IF(M2=0,0,INDEX(Seguimientos!$H$2:$H$1013,MATCH(A2&"|"&M2,Seguimientos!$K$2:$K$1013,0))) | P2: =O2/2 | Q2: =INDEX(Escala!$B$2:$B$6,MATCH(O2,Escala!$A$2:$A$6,0)) | R2: =IF(O2=2,"Sí","No") | S2: =IF(O2=0,"Sí","No") | T2: =IF(AND(ISNUMBER(K2),O2<2),IF(K2<INDEX('Por sistema'!$D$5:$D$9,MATCH(B2,'Por sistema'!$A$5:$A$9,0)),"Sí","No"),"No")
A3: sgc-2022-2 | B3: SGC | C3: Sistema de Gestión de Calidad | D3: 2022 | E3: 2 | F3: Generar contrato de auditoria integrada de SIG en una sola auditoria. (Interna y tercera parte) | G3: Coordinación de Calidad | H3: Calidad | I3: Generar el contrato de auditorías Integrales en el primer semestre para los sistemas de gestión. | J3: 45078 | K3: 45078 | L3: =COUNTIF(Seguimientos!$A$2:$A$1013,A3) | M3: =SUMPRODUCT(MAX((Seguimientos!$A$2:$A$1013=A3)*(Seguimientos!$H$2:$H$1013<>"")*Seguimientos!$B$2:$B$1013)) | N3: =IF(M3=0,"",INDEX(Seguimientos!$F$2:$F$1013,MATCH(A3&"|"&M3,Seguimientos!$K$2:$K$1013,0))) | O3: =IF(M3=0,0,INDEX(Seguimientos!$H$2:$H$1013,MATCH(A3&"|"&M3,Seguimientos!$K$2:$K$1013,0))) | P3: =O3/2 | Q3: =INDEX(Escala!$B$2:$B$6,MATCH(O3,Escala!$A$2:$A$6,0)) | R3: =IF(O3=2,"Sí","No") | S3: =IF(O3=0,"Sí","No") | T3: =IF(AND(ISNUMBER(K3),O3<2),IF(K3<INDEX('Por sistema'!$D$5:$D$9,MATCH(B3,'Por sistema'!$A$5:$A$9,0)),"Sí","No"),"No")
A4: sgc-2022-3 | B4: SGC | C4: Sistema de Gestión de Calidad | D4: 2022 | E4: 3 | F4: La sistematización de la reevaluación al proveedor de bienes y servicios en la plataforma Integradoc. | G4: Dirección de Bienes y Servicios - Oficina de Calidad | H4: Calidad, Bienes, Servicios y Compras | I4: Sistematizar del formato de reevaluación de proveedores. | J4: 45078 | K4: 45078 | L4: =COUNTIF(Seguimientos!$A$2:$A$1013,A4) | M4: =SUMPRODUCT(MAX((Seguimientos!$A$2:$A$1013=A4)*(Seguimientos!$H$2:$H$1013<>"")*Seguimientos!$B$2:$B$1013)) | N4: =IF(M4=0,"",INDEX(Seguimientos!$F$2:$F$1013,MATCH(A4&"|"&M4,Seguimientos!$K$2:$K$1013,0))) | O4: =IF(M4=0,0,INDEX(Seguimientos!$H$2:$H$1013,MATCH(A4&"|"&M4,Seguimientos!$K$2:$K$1013,0))) | P4: =O4/2 | Q4: =INDEX(Escala!$B$2:$B$6,MATCH(O4,Escala!$A$2:$A$6,0)) | R4: =IF(O4=2,"Sí","No") | S4: =IF(O4=0,"Sí","No") | T4: =IF(AND(ISNUMBER(K4),O4<2),IF(K4<INDEX('Por sistema'!$D$5:$D$9,MATCH(B4,'Por sistema'!$A$5:$A$9,0)),"Sí","No"),"No")
A5: sgc-2022-4 | B5: SGC | C5: Sistema de Gestión de Calidad | D5: 2022 | E5: 4 | F5: La Universidad en aras de garantizar procesos pre-contractuales, contractuales y post-contractuales con selección objetiva y transparencia, crea el procedimiento ABSP18 para supervisores e interventores, donde se establecen actividades y responsables dentro del mismo, junto con requisitos y condiciones generales para el desarrollo del procedimiento. | G5: Dirección de Bienes y Servicios (Oficina de Compras) - Oficina de Calidad | H5: Calidad, Bienes, Servicios y Compras | I5: Realizar un diagnostico de los procedimientos de contratación y supervisión para generar los ajustes necesarios que conlleven a optimizar el proceso. | J5: 45261 | K5: 45261 | L5: =COUNTIF(Seguimientos!$A$2:$A$1013,A5) | M5: =SUMPRODUCT(MAX((Seguimientos!$A$2:$A$1013=A5)*(Seguimientos!$H$2:$H$1013<>"")*Seguimientos!$B$2:$B$1013)) | N5: =IF(M5=0,"",INDEX(Seguimientos!$F$2:$F$1013,MATCH(A5&"|"&M5,Seguimientos!$K$2:$K$1013,0))) | O5: =IF(M5=0,0,INDEX(Seguimientos!$H$2:$H$1013,MATCH(A5&"|"&M5,Seguimientos!$K$2:$K$1013,0))) | P5: =O5/2 | Q5: =INDEX(Escala!$B$2:$B$6,MATCH(O5,Escala!$A$2:$A$6,0)) | R5: =IF(O5=2,"Sí","No") | S5: =IF(O5=0,"Sí","No") | T5: =IF(AND(ISNUMBER(K5),O5<2),IF(K5<INDEX('Por sistema'!$D$5:$D$9,MATCH(B5,'Por sistema'!$A$5:$A$9,0)),"Sí","No"),"No")
A6: sgc-2022-4-sn1u5ppt | B6: SGC | C6: Sistema de Gestión de Calidad | D6: 2022 | E6: 4 | F6: Mejora continua en la documentación del proceso de compras | G6: Dirección de Bienes y Servicios (Oficina de Compras) - Oficina de Calidad | H6: Calidad, Bienes, Servicios y Compras | J6: 45261 | K6: 45261 | L6: =COUNTIF(Seguimientos!$A$2:$A$1013,A6) | M6: =SUMPRODUCT(MAX((Seguimientos!$A$2:$A$1013=A6)*(Seguimientos!$H$2:$H$1013<>"")*Seguimientos!$B$2:$B$1013)) | N6: =IF(M6=0,"",INDEX(Seguimientos!$F$2:$F$1013,MATCH(A6&"|"&M6,Seguimientos!$K$2:$K$1013,0))) | O6: =IF(M6=0,0,INDEX(Seguimientos!$H$2:$H$1013,MATCH(A6&"|"&M6,Seguimientos!$K$2:$K$1013,0))) | P6: =O6/2 | Q6: =INDEX(Escala!$B$2:$B$6,MATCH(O6,Escala!$A$2:$A$6,0)) | R6: =IF(O6=2,"Sí","No") | S6: =IF(O6=0,"Sí","No") | T6: =IF(AND(ISNUMBER(K6),O6<2),IF(K6<INDEX('Por sistema'!$D$5:$D$9,MATCH(B6,'Por sistema'!$A$5:$A$9,0)),"Sí","No"),"No")
A7: sgc-2022-5 | B7: SGC | C7: Sistema de Gestión de Calidad | D7: 2022 | E7: 5 | F7: Cambiar metodología de riesgos y oportunidades | G7: Coordinación de calidad y dirección de Control Interno | H7: Control Interno, Calidad | I7: Ajustar la metodología de gestión de los riesgos y las oportunidades, con el fin de incrementar la rigurosidad de las calificaciones y el seguimiento. | J7: 45261 | K7: 45261 | L7: =COUNTIF(Seguimientos!$A$2:$A$1013,A7) | M7: =SUMPRODUCT(MAX((Seguimientos!$A$2:$A$1013=A7)*(Seguimientos!$H$2:$H$1013<>"")*Seguimientos!$B$2:$B$1013)) | N7: =IF(M7=0,"",INDEX(Seguimientos!$F$2:$F$1013,MATCH(A7&"|"&M7,Seguimientos!$K$2:$K$1013,0))) | O7: =IF(M7=0,0,INDEX(Seguimientos!$H$2:$H$1013,MATCH(A7&"|"&M7,Seguimientos!$K$2:$K$1013,0))) | P7: =O7/2 | Q7: =INDEX(Escala!$B$2:$B$6,MATCH(O7,Escala!$A$2:$A$6,0)) | R7: =IF(O7=2,"Sí","No") | S7: =IF(O7=0,"Sí","No") | T7: =IF(AND(ISNUMBER(K7),O7<2),IF(K7<INDEX('Por sistema'!$D$5:$D$9,MATCH(B7,'Por sistema'!$A$5:$A$9,0)),"Sí","No"),"No")
A8: sgc-2022-6 | B8: SGC | C8: Sistema de Gestión de Calidad | D8: 2022 | E8: 6 | F8: De la vigencia 2019 a la vigencia 2022 se presentan en total 26 planes de mejoramiento con categoría oportunidades de mejora propias de las cuales 18 se encuentran cerradas, 7 en ejecución y una en estado agregado. En relación con el impacto se concluye que las oportunidades de mejora propias han ayudado en un 35% mejorar métodos para estructurar roles, responsabilidades y tareas, seguida de un 27% en mejoras tecnológicas que permitan reducir tiempos de operación seguido de un 23% en la mejora de controles internos que aseguren resultados alineados a la estrategia y finalmente mejoras en los métodos de trabajo con un 15%. | G8: Coordinación de calidad y Control interno | H8: Control Interno, Calidad | I8: Determinar la ruta crítica de procedimientos que tengan el mayor porcentaje de no conformidades reiterativas para generar revisión y ajuste a sus controles con enfoque preventivo desde la metodología de riesgos y oportunidades. | J8: 45261 | K8: 45261 | L8: =COUNTIF(Seguimientos!$A$2:$A$1013,A8) | M8: =SUMPRODUCT(MAX((Seguimientos!$A$2:$A$1013=A8)*(Seguimientos!$H$2:$H$1013<>"")*Seguimientos!$B$2:$B$1013)) | N8: =IF(M8=0,"",INDEX(Seguimientos!$F$2:$F$1013,MATCH(A8&"|"&M8,Seguimientos!$K$2:$K$1013,0))) | O8: =IF(M8=0,0,INDEX(Seguimientos!$H$2:$H$1013,MATCH(A8&"|"&M8,Seguimientos!$K$2:$K$1013,0))) | P8: =O8/2 | Q8: =INDEX(Escala!$B$2:$B$6,MATCH(O8,Escala!$A$2:$A$6,0)) | R8: =IF(O8=2,"Sí","No") | S8: =IF(O8=0,"Sí","No") | T8: =IF(AND(ISNUMBER(K8),O8<2),IF(K8<INDEX('Por sistema'!$D$5:$D$9,MATCH(B8,'Por sistema'!$A$5:$A$9,0)),"Sí","No"),"No")
A9: sgc-2022-7 | B9: SGC | C9: Sistema de Gestión de Calidad | D9: 2022 | E9: 7 | F9: El incumplimiento en los métodos de trabajo es la mayor causa en no conformidades; sin embargo, es la solución de mejora que más se da en todas las oportunidades de mejora revisadas, se propone generar una ruta crítica de procedimientos que tengan el mayor porcentaje de no conformidades reiterativas para generar revisión a sus controles. | G9: Coordinación de Calidad Dirección de Control Interno | H9: Control Interno, Calidad | I9: Generar una ruta crítica de procedimientos y/o procesos que tengan el mayor porcentaje de no conformidades reiterativas y generar ajustes a los controles operacionales. | J9: 45261 | K9: 45261 | L9: =COUNTIF(Seguimientos!$A$2:$A$1013,A9) | M9: =SUMPRODUCT(MAX((Seguimientos!$A$2:$A$1013=A9)*(Seguimientos!$H$2:$H$1013<>"")*Seguimientos!$B$2:$B$1013)) | N9: =IF(M9=0,"",INDEX(Seguimientos!$F$2:$F$1013,MATCH(A9&"|"&M9,Seguimientos!$K$2:$K$1013,0))) | O9: =IF(M9=0,0,INDEX(Seguimientos!$H$2:$H$1013,MATCH(A9&"|"&M9,Seguimientos!$K$2:$K$1013,0))) | P9: =O9/2 | Q9: =INDEX(Escala!$B$2:$B$6,MATCH(O9,Escala!$A$2:$A$6,0)) | R9: =IF(O9=2,"Sí","No") | S9: =IF(O9=0,"Sí","No") | T9: =IF(AND(ISNUMBER(K9),O9<2),IF(K9<INDEX('Por sistema'!$D$5:$D$9,MATCH(B9,'Por sistema'!$A$5:$A$9,0)),"Sí","No"),"No")
A10: sgc-2023-1 | B10: SGC | C10: Sistema de Gestión de Calidad | D10: 2023 | E10: 1 | F10: Hacer un segundo seguimiento a las decisiones pendientes de años anteriores por parte de Control Interno antes de que llegue la auditoría de certificación. | G10: Control Interno | H10: Control Interno | I10: Informe o matriz de seguimiento a las decisiones pendientes de vigencias anteriores. | J10: Inmediato | L10: =COUNTIF(Seguimientos!$A$2:$A$1013,A10) | M10: =SUMPRODUCT(MAX((Seguimientos!$A$2:$A$1013=A10)*(Seguimientos!$H$2:$H$1013<>"")*Seguimientos!$B$2:$B$1013)) | N10: =IF(M10=0,"",INDEX(Seguimientos!$F$2:$F$1013,MATCH(A10&"|"&M10,Seguimientos!$K$2:$K$1013,0))) | O10: =IF(M10=0,0,INDEX(Seguimientos!$H$2:$H$1013,MATCH(A10&"|"&M10,Seguimientos!$K$2:$K$1013,0))) | P10: =O10/2 | Q10: =INDEX(Escala!$B$2:$B$6,MATCH(O10,Escala!$A$2:$A$6,0)) | R10: =IF(O10=2,"Sí","No") | S10: =IF(O10=0,"Sí","No") | T10: =IF(AND(ISNUMBER(K10),O10<2),IF(K10<INDEX('Por sistema'!$D$5:$D$9,MATCH(B10,'Por sistema'!$A$5:$A$9,0)),"Sí","No"),"No")
A11: sgc-2023-2 | B11: SGC | C11: Sistema de Gestión de Calidad | D11: 2023 | E11: 2 | F11: Coordinar una mesa de trabajo desde la Dirección de Planeación junto con la Dirección de Sistemas, la Dirección de Bienes y Servicios, y la Jefatura de Recursos Físicos, a más tardar el día 10 de noviembre para atender lo antes posible lo relacionado con el Data Center. | G11: Dirección de Planeación | H11: Planeación Institucional | I11: Registro de asistencia de la sesión de trabajo o grabación de la reunión. | J11: 45240 | K11: 45240 | L11: =COUNTIF(Seguimientos!$A$2:$A$1013,A11) | M11: =SUMPRODUCT(MAX((Seguimientos!$A$2:$A$1013=A11)*(Seguimientos!$H$2:$H$1013<>"")*Seguimientos!$B$2:$B$1013)) | N11: =IF(M11=0,"",INDEX(Seguimientos!$F$2:$F$1013,MATCH(A11&"|"&M11,Seguimientos!$K$2:$K$1013,0))) | O11: =IF(M11=0,0,INDEX(Seguimientos!$H$2:$H$1013,MATCH(A11&"|"&M11,Seguimientos!$K$2:$K$1013,0))) | P11: =O11/2 | Q11: =INDEX(Escala!$B$2:$B$6,MATCH(O11,Escala!$A$2:$A$6,0)) | R11: =IF(O11=2,"Sí","No") | S11: =IF(O11=0,"Sí","No") | T11: =IF(AND(ISNUMBER(K11),O11<2),IF(K11<INDEX('Por sistema'!$D$5:$D$9,MATCH(B11,'Por sistema'!$A$5:$A$9,0)),"Sí","No"),"No")
A12: sgc-2023-3 | B12: SGC | C12: Sistema de Gestión de Calidad | D12: 2023 | E12: 3 | F12: Dar continuidad a las mesas de trabajo, capacitaciones virtuales y jornadas de sensibilización, dirigidas a las áreas solicitantes. | G12: Jefatura de Compras | H12: Bienes, Servicios y Compras | I12: Registro de asistencia de la sesión de trabajo o grabación de la reunión. | J12: Una capacitación antes del 17-11-2023, una en febrero de 2024 y otra en julio de 2024. | L12: =COUNTIF(Seguimientos!$A$2:$A$1013,A12) | M12: =SUMPRODUCT(MAX((Seguimientos!$A$2:$A$1013=A12)*(Seguimientos!$H$2:$H$1013<>"")*Seguimientos!$B$2:$B$1013)) | N12: =IF(M12=0,"",INDEX(Seguimientos!$F$2:$F$1013,MATCH(A12&"|"&M12,Seguimientos!$K$2:$K$1013,0))) | O12: =IF(M12=0,0,INDEX(Seguimientos!$H$2:$H$1013,MATCH(A12&"|"&M12,Seguimientos!$K$2:$K$1013,0))) | P12: =O12/2 | Q12: =INDEX(Escala!$B$2:$B$6,MATCH(O12,Escala!$A$2:$A$6,0)) | R12: =IF(O12=2,"Sí","No") | S12: =IF(O12=0,"Sí","No") | T12: =IF(AND(ISNUMBER(K12),O12<2),IF(K12<INDEX('Por sistema'!$D$5:$D$9,MATCH(B12,'Por sistema'!$A$5:$A$9,0)),"Sí","No"),"No")
A13: sgc-2023-4 | B13: SGC | C13: Sistema de Gestión de Calidad | D13: 2023 | E13: 4 | F13: Socializar a las áreas con el respaldo de las vicerrectorías y la Secretaría General, las demostraciones correspondientes a los sistemas de información académico, financiero y administrativo. | G13: Dirección de Sistemas y Tecnología | H13: Sistemas y Tecnología | I13: Registro de asistencia de las sesiones de trabajo y socializaciones a las diferentes áreas. | J13: 45275 | K13: 45275 | L13: =COUNTIF(Seguimientos!$A$2:$A$1013,A13) | M13: =SUMPRODUCT(MAX((Seguimientos!$A$2:$A$1013=A13)*(Seguimientos!$H$2:$H$1013<>"")*Seguimientos!$B$2:$B$1013)) | N13: =IF(M13=0,"",INDEX(Seguimientos!$F$2:$F$1013,MATCH(A13&"|"&M13,Seguimientos!$K$2:$K$1013,0))) | O13: =IF(M13=0,0,INDEX(Seguimientos!$H$2:$H$1013,MATCH(A13&"|"&M13,Seguimientos!$K$2:$K$1013,0))) | P13: =O13/2 | Q13: =INDEX(Escala!$B$2:$B$6,MATCH(O13,Escala!$A$2:$A$6,0)) | R13: =IF(O13=2,"Sí","No") | S13: =IF(O13=0,"Sí","No") | T13: =IF(AND(ISNUMBER(K13),O13<2),IF(K13<INDEX('Por sistema'!$D$5:$D$9,MATCH(B13,'Por sistema'!$A$5:$A$9,0)),"Sí","No"),"No")
A14: sgc-2023-5 | B14: SGC | C14: Sistema de Gestión de Calidad | D14: 2023 | E14: 5 | F14: Solicitar a los procesos que están presentando indicadores con incumplimiento y que actualmente no cuentan con planes de mejoramiento, generar para cada uno de estos, un plan de mejoramiento con el fin de fortalecer los resultados y dar un cierre eficaz a corte de diciembre 2023. En caso de que cuenten con plan de mejoramiento, este se debe revisar y ajustar según corresponda. | G14: Oficina de Calidad - Líderes de los procesos | H14: Calidad | I14: Planes de mejoramiento generados y cargados en el aplicativo correspondiente por los procesos para el fortalecimiento de los resultados de indicadores de gestión. | J14: 45291 | K14: 45291 | L14: =COUNTIF(Seguimientos!$A$2:$A$1013,A14) | M14: =SUMPRODUCT(MAX((Seguimientos!$A$2:$A$1013=A14)*(Seguimientos!$H$2:$H$1013<>"")*Seguimientos!$B$2:$B$1013)) | N14: =IF(M14=0,"",INDEX(Seguimientos!$F$2:$F$1013,MATCH(A14&"|"&M14,Seguimientos!$K$2:$K$1013,0))) | O14: =IF(M14=0,0,INDEX(Seguimientos!$H$2:$H$1013,MATCH(A14&"|"&M14,Seguimientos!$K$2:$K$1013,0))) | P14: =O14/2 | Q14: =INDEX(Escala!$B$2:$B$6,MATCH(O14,Escala!$A$2:$A$6,0)) | R14: =IF(O14=2,"Sí","No") | S14: =IF(O14=0,"Sí","No") | T14: =IF(AND(ISNUMBER(K14),O14<2),IF(K14<INDEX('Por sistema'!$D$5:$D$9,MATCH(B14,'Por sistema'!$A$5:$A$9,0)),"Sí","No"),"No")
A15: sgc-2023-6 | B15: SGC | C15: Sistema de Gestión de Calidad | D15: 2023 | E15: 6 | F15: Actualizar el Plan Estratégico de Seguridad Vial y sus anexos. | G15: Oficina de Recursos Físicos | H15: Recursos Físicos | I15: Plan Estratégico de Seguridad Vial y sus anexos actualizados. | J15: diciembre 2023 | L15: =COUNTIF(Seguimientos!$A$2:$A$1013,A15) | M15: =SUMPRODUCT(MAX((Seguimientos!$A$2:$A$1013=A15)*(Seguimientos!$H$2:$H$1013<>"")*Seguimientos!$B$2:$B$1013)) | N15: =IF(M15=0,"",INDEX(Seguimientos!$F$2:$F$1013,MATCH(A15&"|"&M15,Seguimientos!$K$2:$K$1013,0))) | O15: =IF(M15=0,0,INDEX(Seguimientos!$H$2:$H$1013,MATCH(A15&"|"&M15,Seguimientos!$K$2:$K$1013,0))) | P15: =O15/2 | Q15: =INDEX(Escala!$B$2:$B$6,MATCH(O15,Escala!$A$2:$A$6,0)) | R15: =IF(O15=2,"Sí","No") | S15: =IF(O15=0,"Sí","No") | T15: =IF(AND(ISNUMBER(K15),O15<2),IF(K15<INDEX('Por sistema'!$D$5:$D$9,MATCH(B15,'Por sistema'!$A$5:$A$9,0)),"Sí","No"),"No")
A16: sgc-2023-7 | B16: SGC | C16: Sistema de Gestión de Calidad | D16: 2023 | E16: 7 | F16: Como parte de las acciones de los resultados de la encuesta de satisfacción, se debe establecer un plan de trabajo con aquellos procesos que no alcanzaron un nivel de satisfacción de conformidad con el indicador propuesto, con el fin de evidenciar mejora con la segunda encuesta que se está aplicando en este momento. Responsable. | G16: Dirección de Planeación | H16: Planeación Institucional | I16: Cronograma del plan de trabajo con los procesos que no hayan alcanzado el nivel propuesto por el indicador. | J16: diciembre 2023 | L16: =COUNTIF(Seguimientos!$A$2:$A$1013,A16) | M16: =SUMPRODUCT(MAX((Seguimientos!$A$2:$A$1013=A16)*(Seguimientos!$H$2:$H$1013<>"")*Seguimientos!$B$2:$B$1013)) | N16: =IF(M16=0,"",INDEX(Seguimientos!$F$2:$F$1013,MATCH(A16&"|"&M16,Seguimientos!$K$2:$K$1013,0))) | O16: =IF(M16=0,0,INDEX(Seguimientos!$H$2:$H$1013,MATCH(A16&"|"&M16,Seguimientos!$K$2:$K$1013,0))) | P16: =O16/2 | Q16: =INDEX(Escala!$B$2:$B$6,MATCH(O16,Escala!$A$2:$A$6,0)) | R16: =IF(O16=2,"Sí","No") | S16: =IF(O16=0,"Sí","No") | T16: =IF(AND(ISNUMBER(K16),O16<2),IF(K16<INDEX('Por sistema'!$D$5:$D$9,MATCH(B16,'Por sistema'!$A$5:$A$9,0)),"Sí","No"),"No")
A17: sgc-2023-8 | B17: SGC | C17: Sistema de Gestión de Calidad | D17: 2023 | E17: 8 | F17: Realizar el cierre de los objetivos establecidos en la Resolución 096 de 2021, con corte a diciembre 2023 y llevar el análisis de los resultados al comité SAC para la toma de decisiones que sea pertinente. | G17: Oficina de Calidad | H17: Calidad | I17: Informe de cierre de los objetivos establecidos en la Resolución 096 de 2021, con corte a diciembre 2023 y acta de la sesión de comité SAC con el punto del informe socializado. | J17: 45351 | K17: 45351 | L17: =COUNTIF(Seguimientos!$A$2:$A$1013,A17) | M17: =SUMPRODUCT(MAX((Seguimientos!$A$2:$A$1013=A17)*(Seguimientos!$H$2:$H$1013<>"")*Seguimientos!$B$2:$B$1013)) | N17: =IF(M17=0,"",INDEX(Seguimientos!$F$2:$F$1013,MATCH(A17&"|"&M17,Seguimientos!$K$2:$K$1013,0))) | O17: =IF(M17=0,0,INDEX(Seguimientos!$H$2:$H$1013,MATCH(A17&"|"&M17,Seguimientos!$K$2:$K$1013,0))) | P17: =O17/2 | Q17: =INDEX(Escala!$B$2:$B$6,MATCH(O17,Escala!$A$2:$A$6,0)) | R17: =IF(O17=2,"Sí","No") | S17: =IF(O17=0,"Sí","No") | T17: =IF(AND(ISNUMBER(K17),O17<2),IF(K17<INDEX('Por sistema'!$D$5:$D$9,MATCH(B17,'Por sistema'!$A$5:$A$9,0)),"Sí","No"),"No")
A18: sgc-2023-9 | B18: SGC | C18: Sistema de Gestión de Calidad | D18: 2023 | E18: 9 | F18: Documentar los lineamientos de control de acceso universitario a partir de la consolidación de un procedimiento de ingreso a planta física que actualice los lineamientos establecidos en la Resolución 307 de 2008. | G18: Oficina de Recursos Físicos | H18: Recursos Físicos | I18: Procedimiento actualizado de acuerdo a la resolución 307/2008 y cargado en el MOD. | J18: febrero 2024 | L18: =COUNTIF(Seguimientos!$A$2:$A$1013,A18) | M18: =SUMPRODUCT(MAX((Seguimientos!$A$2:$A$1013=A18)*(Seguimientos!$H$2:$H$1013<>"")*Seguimientos!$B$2:$B$1013)) | N18: =IF(M18=0,"",INDEX(Seguimientos!$F$2:$F$1013,MATCH(A18&"|"&M18,Seguimientos!$K$2:$K$1013,0))) | O18: =IF(M18=0,0,INDEX(Seguimientos!$H$2:$H$1013,MATCH(A18&"|"&M18,Seguimientos!$K$2:$K$1013,0))) | P18: =O18/2 | Q18: =INDEX(Escala!$B$2:$B$6,MATCH(O18,Escala!$A$2:$A$6,0)) | R18: =IF(O18=2,"Sí","No") | S18: =IF(O18=0,"Sí","No") | T18: =IF(AND(ISNUMBER(K18),O18<2),IF(K18<INDEX('Por sistema'!$D$5:$D$9,MATCH(B18,'Por sistema'!$A$5:$A$9,0)),"Sí","No"),"No")
A19: sgc-2023-10 | B19: SGC | C19: Sistema de Gestión de Calidad | D19: 2023 | E19: 10 | F19: Establecer las condiciones técnicas de los teléfonos para determinar si están o no en uso. Responsable. | G19: Dirección de Sistemas y Tecnología | H19: Sistemas y Tecnología | I19: Informe de condiciones técnicas de los teléfonos. | J19: febrero 2024 | L19: =COUNTIF(Seguimientos!$A$2:$A$1013,A19) | M19: =SUMPRODUCT(MAX((Seguimientos!$A$2:$A$1013=A19)*(Seguimientos!$H$2:$H$1013<>"")*Seguimientos!$B$2:$B$1013)) | N19: =IF(M19=0,"",INDEX(Seguimientos!$F$2:$F$1013,MATCH(A19&"|"&M19,Seguimientos!$K$2:$K$1013,0))) | O19: =IF(M19=0,0,INDEX(Seguimientos!$H$2:$H$1013,MATCH(A19&"|"&M19,Seguimientos!$K$2:$K$1013,0))) | P19: =O19/2 | Q19: =INDEX(Escala!$B$2:$B$6,MATCH(O19,Escala!$A$2:$A$6,0)) | R19: =IF(O19=2,"Sí","No") | S19: =IF(O19=0,"Sí","No") | T19: =IF(AND(ISNUMBER(K19),O19<2),IF(K19<INDEX('Por sistema'!$D$5:$D$9,MATCH(B19,'Por sistema'!$A$5:$A$9,0)),"Sí","No"),"No")
A20: sgc-2023-11 | B20: SGC | C20: Sistema de Gestión de Calidad | D20: 2023 | E20: 11 | F20: Implementar una metodología de planificación de prácticas académicas y/o experiencias formativas, con el fin de reducir los impactos administrativos / académicos que implican la reprogramación o cancelación de las mismas. | G20: Comité de prácticas académicas | H20: Apoyo y Desarrollo Académico | I20: Documento con la metodología a aplicar o procedimiento e instructivo actualizado. | J20: 45381 | K20: 45381 | L20: =COUNTIF(Seguimientos!$A$2:$A$1013,A20) | M20: =SUMPRODUCT(MAX((Seguimientos!$A$2:$A$1013=A20)*(Seguimientos!$H$2:$H$1013<>"")*Seguimientos!$B$2:$B$1013)) | N20: =IF(M20=0,"",INDEX(Seguimientos!$F$2:$F$1013,MATCH(A20&"|"&M20,Seguimientos!$K$2:$K$1013,0))) | O20: =IF(M20=0,0,INDEX(Seguimientos!$H$2:$H$1013,MATCH(A20&"|"&M20,Seguimientos!$K$2:$K$1013,0))) | P20: =O20/2 | Q20: =INDEX(Escala!$B$2:$B$6,MATCH(O20,Escala!$A$2:$A$6,0)) | R20: =IF(O20=2,"Sí","No") | S20: =IF(O20=0,"Sí","No") | T20: =IF(AND(ISNUMBER(K20),O20<2),IF(K20<INDEX('Por sistema'!$D$5:$D$9,MATCH(B20,'Por sistema'!$A$5:$A$9,0)),"Sí","No"),"No")
A21: sgc-2023-12 | B21: SGC | C21: Sistema de Gestión de Calidad | D21: 2023 | E21: 12 | F21: Implementar una metodología de diagnóstico y priorización de necesidades de elementos educativos, con el fin de atender las necesidades que históricamente ha requerido la academia. | G21: Unidad de Apoyo Académico | H21: Apoyo y Desarrollo Académico | I21: Metodología implementada por medio de instructivo o procedimiento. Herramienta tecnológica o digitalización de la metodología en mención, si aplica. | J21: 45381 | K21: 45381 | L21: =COUNTIF(Seguimientos!$A$2:$A$1013,A21) | M21: =SUMPRODUCT(MAX((Seguimientos!$A$2:$A$1013=A21)*(Seguimientos!$H$2:$H$1013<>"")*Seguimientos!$B$2:$B$1013)) | N21: =IF(M21=0,"",INDEX(Seguimientos!$F$2:$F$1013,MATCH(A21&"|"&M21,Seguimientos!$K$2:$K$1013,0))) | O21: =IF(M21=0,0,INDEX(Seguimientos!$H$2:$H$1013,MATCH(A21&"|"&M21,Seguimientos!$K$2:$K$1013,0))) | P21: =O21/2 | Q21: =INDEX(Escala!$B$2:$B$6,MATCH(O21,Escala!$A$2:$A$6,0)) | R21: =IF(O21=2,"Sí","No") | S21: =IF(O21=0,"Sí","No") | T21: =IF(AND(ISNUMBER(K21),O21<2),IF(K21<INDEX('Por sistema'!$D$5:$D$9,MATCH(B21,'Por sistema'!$A$5:$A$9,0)),"Sí","No"),"No")
A22: sgc-2023-13 | B22: SGC | C22: Sistema de Gestión de Calidad | D22: 2023 | E22: 13 | F22: Incluir en el inventario de necesidades para priorización la mejora del aplicativo de SNC, en cuanto al paso posterior de seguimiento al cumplimiento de la recuperación de sesiones de formación. | G22: Oficina de Calidad - Sistemas y Tecnología | H22: Sistemas y Tecnología, Calidad | I22: Cronograma de priorización de la Dirección de Sistemas y Tecnología, donde se evidencia la inclusión de la mejora del aplicativo SNC. | J22: 45381 | K22: 45381 | L22: =COUNTIF(Seguimientos!$A$2:$A$1013,A22) | M22: =SUMPRODUCT(MAX((Seguimientos!$A$2:$A$1013=A22)*(Seguimientos!$H$2:$H$1013<>"")*Seguimientos!$B$2:$B$1013)) | N22: =IF(M22=0,"",INDEX(Seguimientos!$F$2:$F$1013,MATCH(A22&"|"&M22,Seguimientos!$K$2:$K$1013,0))) | O22: =IF(M22=0,0,INDEX(Seguimientos!$H$2:$H$1013,MATCH(A22&"|"&M22,Seguimientos!$K$2:$K$1013,0))) | P22: =O22/2 | Q22: =INDEX(Escala!$B$2:$B$6,MATCH(O22,Escala!$A$2:$A$6,0)) | R22: =IF(O22=2,"Sí","No") | S22: =IF(O22=0,"Sí","No") | T22: =IF(AND(ISNUMBER(K22),O22<2),IF(K22<INDEX('Por sistema'!$D$5:$D$9,MATCH(B22,'Por sistema'!$A$5:$A$9,0)),"Sí","No"),"No")
A23: sgc-2023-14 | B23: SGC | C23: Sistema de Gestión de Calidad | D23: 2023 | E23: 14 | F23: Generar estrategias para el fortalecimiento de las competencias relacionadas con la transparencia y la orientación al usuario y al ciudadano, así como fortalecer las metodologías de carácter digital y tecnológico para generar programas de formación y capacitación del personal. | G23: Dirección de Talento Humano | H23: Talento Humano | I23: Socialización de las estrategias a implementar para los dos casos y actualización documental si aplica. | J23: marzo 2024 | L23: =COUNTIF(Seguimientos!$A$2:$A$1013,A23) | M23: =SUMPRODUCT(MAX((Seguimientos!$A$2:$A$1013=A23)*(Seguimientos!$H$2:$H$1013<>"")*Seguimientos!$B$2:$B$1013)) | N23: =IF(M23=0,"",INDEX(Seguimientos!$F$2:$F$1013,MATCH(A23&"|"&M23,Seguimientos!$K$2:$K$1013,0))) | O23: =IF(M23=0,0,INDEX(Seguimientos!$H$2:$H$1013,MATCH(A23&"|"&M23,Seguimientos!$K$2:$K$1013,0))) | P23: =O23/2 | Q23: =INDEX(Escala!$B$2:$B$6,MATCH(O23,Escala!$A$2:$A$6,0)) | R23: =IF(O23=2,"Sí","No") | S23: =IF(O23=0,"Sí","No") | T23: =IF(AND(ISNUMBER(K23),O23<2),IF(K23<INDEX('Por sistema'!$D$5:$D$9,MATCH(B23,'Por sistema'!$A$5:$A$9,0)),"Sí","No"),"No")
A24: sgc-2023-15 | B24: SGC | C24: Sistema de Gestión de Calidad | D24: 2023 | E24: 15 | F24: Consolidar el plan estratégico de tecnologías de la información (redes, servicios, servidores, plataformas, etc.) para atender de manera adecuada la oferta académica virtual que la Universidad está proyectando. | G24: Dirección de Sistemas y Tecnología | H24: Sistemas y Tecnología | I24: Plan estratégico de tecnologías de la información (redes, servicios, servidores, plataformas, etc.) enfocado en la oferta académica virtual. | J24: marzo 2024 | L24: =COUNTIF(Seguimientos!$A$2:$A$1013,A24) | M24: =SUMPRODUCT(MAX((Seguimientos!$A$2:$A$1013=A24)*(Seguimientos!$H$2:$H$1013<>"")*Seguimientos!$B$2:$B$1013)) | N24: =IF(M24=0,"",INDEX(Seguimientos!$F$2:$F$1013,MATCH(A24&"|"&M24,Seguimientos!$K$2:$K$1013,0))) | O24: =IF(M24=0,0,INDEX(Seguimientos!$H$2:$H$1013,MATCH(A24&"|"&M24,Seguimientos!$K$2:$K$1013,0))) | P24: =O24/2 | Q24: =INDEX(Escala!$B$2:$B$6,MATCH(O24,Escala!$A$2:$A$6,0)) | R24: =IF(O24=2,"Sí","No") | S24: =IF(O24=0,"Sí","No") | T24: =IF(AND(ISNUMBER(K24),O24<2),IF(K24<INDEX('Por sistema'!$D$5:$D$9,MATCH(B24,'Por sistema'!$A$5:$A$9,0)),"Sí","No"),"No")
A25: sgc-2023-16 | B25: SGC | C25: Sistema de Gestión de Calidad | D25: 2023 | E25: 16 | F25: Reasignación de espacio físico para el archivo de talento humano. | G25: Planeación Institucional - Archivo y Correspondencia - Talento Humano | H25: Planeación Institucional, Talento Humano, Archivo y Correspondencia | I25: Documento o acto administrativo con la reasignación de espacio físico para el archivo de talento humano. | J25: Trimestre I 2024 | L25: =COUNTIF(Seguimientos!$A$2:$A$1013,A25) | M25: =SUMPRODUCT(MAX((Seguimientos!$A$2:$A$1013=A25)*(Seguimientos!$H$2:$H$1013<>"")*Seguimientos!$B$2:$B$1013)) | N25: =IF(M25=0,"",INDEX(Seguimientos!$F$2:$F$1013,MATCH(A25&"|"&M25,Seguimientos!$K$2:$K$1013,0))) | O25: =IF(M25=0,0,INDEX(Seguimientos!$H$2:$H$1013,MATCH(A25&"|"&M25,Seguimientos!$K$2:$K$1013,0))) | P25: =O25/2 | Q25: =INDEX(Escala!$B$2:$B$6,MATCH(O25,Escala!$A$2:$A$6,0)) | R25: =IF(O25=2,"Sí","No") | S25: =IF(O25=0,"Sí","No") | T25: =IF(AND(ISNUMBER(K25),O25<2),IF(K25<INDEX('Por sistema'!$D$5:$D$9,MATCH(B25,'Por sistema'!$A$5:$A$9,0)),"Sí","No"),"No")
A26: sgc-2023-17 | B26: SGC | C26: Sistema de Gestión de Calidad | D26: 2023 | E26: 17 | F26: Hacer un estudio de tiempos y movimientos con la Oficina de Calidad de los trámites internos para el proceso de investigación, articulado con el área administrativa. | G26: Dirección de Investigación - Oficina de Calidad | H26: Calidad, Investigación Universitaria | I26: Informe de estudio de tiempos y movimientos de los trámites internos para el proceso de investigación, articulado con el área administrativa. | J26: IPA 2024 | L26: =COUNTIF(Seguimientos!$A$2:$A$1013,A26) | M26: =SUMPRODUCT(MAX((Seguimientos!$A$2:$A$1013=A26)*(Seguimientos!$H$2:$H$1013<>"")*Seguimientos!$B$2:$B$1013)) | N26: =IF(M26=0,"",INDEX(Seguimientos!$F$2:$F$1013,MATCH(A26&"|"&M26,Seguimientos!$K$2:$K$1013,0))) | O26: =IF(M26=0,0,INDEX(Seguimientos!$H$2:$H$1013,MATCH(A26&"|"&M26,Seguimientos!$K$2:$K$1013,0))) | P26: =O26/2 | Q26: =INDEX(Escala!$B$2:$B$6,MATCH(O26,Escala!$A$2:$A$6,0)) | R26: =IF(O26=2,"Sí","No") | S26: =IF(O26=0,"Sí","No") | T26: =IF(AND(ISNUMBER(K26),O26<2),IF(K26<INDEX('Por sistema'!$D$5:$D$9,MATCH(B26,'Por sistema'!$A$5:$A$9,0)),"Sí","No"),"No")
A27: sgc-2023-18 | B27: SGC | C27: Sistema de Gestión de Calidad | D27: 2023 | E27: 18 | F27: Revisar la gestión del proceso de internacionalización dado que no solamente por los resultados estadísticos de los planes de mejoramiento, sino por otros temas revisados desde la Comisión de Control Interno, denota deficiencias en la gestión de la mejora. | G27: Vicerrectoría Académica | H27: Vicerrectoría Académica | I27: Informe de seguimiento a la gestión de mejora en las actividades del proceso de internacionalización. | J27: IPA 2024 | L27: =COUNTIF(Seguimientos!$A$2:$A$1013,A27) | M27: =SUMPRODUCT(MAX((Seguimientos!$A$2:$A$1013=A27)*(Seguimientos!$H$2:$H$1013<>"")*Seguimientos!$B$2:$B$1013)) | N27: =IF(M27=0,"",INDEX(Seguimientos!$F$2:$F$1013,MATCH(A27&"|"&M27,Seguimientos!$K$2:$K$1013,0))) | O27: =IF(M27=0,0,INDEX(Seguimientos!$H$2:$H$1013,MATCH(A27&"|"&M27,Seguimientos!$K$2:$K$1013,0))) | P27: =O27/2 | Q27: =INDEX(Escala!$B$2:$B$6,MATCH(O27,Escala!$A$2:$A$6,0)) | R27: =IF(O27=2,"Sí","No") | S27: =IF(O27=0,"Sí","No") | T27: =IF(AND(ISNUMBER(K27),O27<2),IF(K27<INDEX('Por sistema'!$D$5:$D$9,MATCH(B27,'Por sistema'!$A$5:$A$9,0)),"Sí","No"),"No")
A28: sgc-2023-19 | B28: SGC | C28: Sistema de Gestión de Calidad | D28: 2023 | E28: 19 | F28: Adelantar mesas de trabajo entre la Dirección Planeación, la Dirección de Bienes y Servicios, la Oficina de Equidad y Diversidad y la Oficina de Seguridad y Salud en el Trabajo, con el fin de validar la necesidad de realizar estudios de factibilidad para el acceso a la planta física de la UDEC en el marco de la inclusión. | G28: Oficina de Recursos Físicos | H28: Recursos Físicos | I28: Registros de asistencia o grabación de las mesas de trabajo de validación de estudios de factibilidad para el acceso a la planta física de la UDEC en el marco de la inclusión. | J28: IPA 2024 | L28: =COUNTIF(Seguimientos!$A$2:$A$1013,A28) | M28: =SUMPRODUCT(MAX((Seguimientos!$A$2:$A$1013=A28)*(Seguimientos!$H$2:$H$1013<>"")*Seguimientos!$B$2:$B$1013)) | N28: =IF(M28=0,"",INDEX(Seguimientos!$F$2:$F$1013,MATCH(A28&"|"&M28,Seguimientos!$K$2:$K$1013,0))) | O28: =IF(M28=0,0,INDEX(Seguimientos!$H$2:$H$1013,MATCH(A28&"|"&M28,Seguimientos!$K$2:$K$1013,0))) | P28: =O28/2 | Q28: =INDEX(Escala!$B$2:$B$6,MATCH(O28,Escala!$A$2:$A$6,0)) | R28: =IF(O28=2,"Sí","No") | S28: =IF(O28=0,"Sí","No") | T28: =IF(AND(ISNUMBER(K28),O28<2),IF(K28<INDEX('Por sistema'!$D$5:$D$9,MATCH(B28,'Por sistema'!$A$5:$A$9,0)),"Sí","No"),"No")
A29: sgc-2023-20 | B29: SGC | C29: Sistema de Gestión de Calidad | D29: 2023 | E29: 20 | F29: Generar contenido de un curso virtual, en el cual se profundice sobre las líneas de defensa dando mayor relevancia a los temas de autocontrol, teniendo en cuenta que por las estadísticas se tiende a ser reactivo a la espera de la auditoria para mejorar. | G29: Control Interno | H29: Control Interno | I29: Curso virtual activo y en funcionamiento en aulas virtuales, MOOCs. | J29: IPA 2024 | L29: =COUNTIF(Seguimientos!$A$2:$A$1013,A29) | M29: =SUMPRODUCT(MAX((Seguimientos!$A$2:$A$1013=A29)*(Seguimientos!$H$2:$H$1013<>"")*Seguimientos!$B$2:$B$1013)) | N29: =IF(M29=0,"",INDEX(Seguimientos!$F$2:$F$1013,MATCH(A29&"|"&M29,Seguimientos!$K$2:$K$1013,0))) | O29: =IF(M29=0,0,INDEX(Seguimientos!$H$2:$H$1013,MATCH(A29&"|"&M29,Seguimientos!$K$2:$K$1013,0))) | P29: =O29/2 | Q29: =INDEX(Escala!$B$2:$B$6,MATCH(O29,Escala!$A$2:$A$6,0)) | R29: =IF(O29=2,"Sí","No") | S29: =IF(O29=0,"Sí","No") | T29: =IF(AND(ISNUMBER(K29),O29<2),IF(K29<INDEX('Por sistema'!$D$5:$D$9,MATCH(B29,'Por sistema'!$A$5:$A$9,0)),"Sí","No"),"No")
A30: sgc-2023-21 | B30: SGC | C30: Sistema de Gestión de Calidad | D30: 2023 | E30: 21 | F30: Para los temas reiterativos de No conformidad incluir estas unidades auditables para el 2024 previo estudio de nivel de riesgos. | G30: Dirección de Control Interno | H30: Control Interno | I30: Plan de auditorias con la inclusión de temas relacionados con no conformidades reiterativas. Informe de estudio de nivel de riesgos 2024. | J30: IPA 2024 | L30: =COUNTIF(Seguimientos!$A$2:$A$1013,A30) | M30: =SUMPRODUCT(MAX((Seguimientos!$A$2:$A$1013=A30)*(Seguimientos!$H$2:$H$1013<>"")*Seguimientos!$B$2:$B$1013)) | N30: =IF(M30=0,"",INDEX(Seguimientos!$F$2:$F$1013,MATCH(A30&"|"&M30,Seguimientos!$K$2:$K$1013,0))) | O30: =IF(M30=0,0,INDEX(Seguimientos!$H$2:$H$1013,MATCH(A30&"|"&M30,Seguimientos!$K$2:$K$1013,0))) | P30: =O30/2 | Q30: =INDEX(Escala!$B$2:$B$6,MATCH(O30,Escala!$A$2:$A$6,0)) | R30: =IF(O30=2,"Sí","No") | S30: =IF(O30=0,"Sí","No") | T30: =IF(AND(ISNUMBER(K30),O30<2),IF(K30<INDEX('Por sistema'!$D$5:$D$9,MATCH(B30,'Por sistema'!$A$5:$A$9,0)),"Sí","No"),"No")
A31: sgc-2023-22 | B31: SGC | C31: Sistema de Gestión de Calidad | D31: 2023 | E31: 22 | F31: Adelantar la gestión del cambio de la Resolución 088: 2023, con el fin de desagregar las funciones del PHVA de los Sistemas de Gestión. | G31: Dirección de Control Interno | H31: Control Interno | I31: Matriz de gestión del cambio y articulación de las actividades de desagregación del ciclo PHVA de los sistemas de Gestión. | J31: IPA 2024 | L31: =COUNTIF(Seguimientos!$A$2:$A$1013,A31) | M31: =SUMPRODUCT(MAX((Seguimientos!$A$2:$A$1013=A31)*(Seguimientos!$H$2:$H$1013<>"")*Seguimientos!$B$2:$B$1013)) | N31: =IF(M31=0,"",INDEX(Seguimientos!$F$2:$F$1013,MATCH(A31&"|"&M31,Seguimientos!$K$2:$K$1013,0))) | O31: =IF(M31=0,0,INDEX(Seguimientos!$H$2:$H$1013,MATCH(A31&"|"&M31,Seguimientos!$K$2:$K$1013,0))) | P31: =O31/2 | Q31: =INDEX(Escala!$B$2:$B$6,MATCH(O31,Escala!$A$2:$A$6,0)) | R31: =IF(O31=2,"Sí","No") | S31: =IF(O31=0,"Sí","No") | T31: =IF(AND(ISNUMBER(K31),O31<2),IF(K31<INDEX('Por sistema'!$D$5:$D$9,MATCH(B31,'Por sistema'!$A$5:$A$9,0)),"Sí","No"),"No")
A32: sgc-2023-23 | B32: SGC | C32: Sistema de Gestión de Calidad | D32: 2023 | E32: 23 | F32: Incluir dentro de los acuerdos de gestión de los directivos y jefes el cierre de los planes de mejoramiento como actividad de tipo institucional, o en su defecto considerarla dentro del plan de acción de la siguiente vigencia como estrategia de mejora. | G32: Dirección de Talento Humano | H32: Talento Humano | I32: Acuerdos de Gestión con la articulación de actividades de cierre de planes de mejoramiento. | J32: IPA 2024 | L32: =COUNTIF(Seguimientos!$A$2:$A$1013,A32) | M32: =SUMPRODUCT(MAX((Seguimientos!$A$2:$A$1013=A32)*(Seguimientos!$H$2:$H$1013<>"")*Seguimientos!$B$2:$B$1013)) | N32: =IF(M32=0,"",INDEX(Seguimientos!$F$2:$F$1013,MATCH(A32&"|"&M32,Seguimientos!$K$2:$K$1013,0))) | O32: =IF(M32=0,0,INDEX(Seguimientos!$H$2:$H$1013,MATCH(A32&"|"&M32,Seguimientos!$K$2:$K$1013,0))) | P32: =O32/2 | Q32: =INDEX(Escala!$B$2:$B$6,MATCH(O32,Escala!$A$2:$A$6,0)) | R32: =IF(O32=2,"Sí","No") | S32: =IF(O32=0,"Sí","No") | T32: =IF(AND(ISNUMBER(K32),O32<2),IF(K32<INDEX('Por sistema'!$D$5:$D$9,MATCH(B32,'Por sistema'!$A$5:$A$9,0)),"Sí","No"),"No")
A33: sgc-2023-24 | B33: SGC | C33: Sistema de Gestión de Calidad | D33: 2023 | E33: 24 | F33: Hacer una capacitación para dar a conocer el uso adecuado de los teléfonos. | G33: Oficina de Atención al Ciudadano | H33: Atención al Ciudadano | I33: Registros de asistencia o grabaciones de las sesiones de capacitación. | J33: abril 2024 | L33: =COUNTIF(Seguimientos!$A$2:$A$1013,A33) | M33: =SUMPRODUCT(MAX((Seguimientos!$A$2:$A$1013=A33)*(Seguimientos!$H$2:$H$1013<>"")*Seguimientos!$B$2:$B$1013)) | N33: =IF(M33=0,"",INDEX(Seguimientos!$F$2:$F$1013,MATCH(A33&"|"&M33,Seguimientos!$K$2:$K$1013,0))) | O33: =IF(M33=0,0,INDEX(Seguimientos!$H$2:$H$1013,MATCH(A33&"|"&M33,Seguimientos!$K$2:$K$1013,0))) | P33: =O33/2 | Q33: =INDEX(Escala!$B$2:$B$6,MATCH(O33,Escala!$A$2:$A$6,0)) | R33: =IF(O33=2,"Sí","No") | S33: =IF(O33=0,"Sí","No") | T33: =IF(AND(ISNUMBER(K33),O33<2),IF(K33<INDEX('Por sistema'!$D$5:$D$9,MATCH(B33,'Por sistema'!$A$5:$A$9,0)),"Sí","No"),"No")
A34: sgc-2023-25 | B34: SGC | C34: Sistema de Gestión de Calidad | D34: 2023 | E34: 25 | F34: Realizar un análisis de causas del incremento de salidas no conformes relacionadas con la inasistencia de profesores, para determinar estrategias que permitan controlar esta tendencia. | G34: Desarrollo Académico | H34: Apoyo y Desarrollo Académico | I34: Informe de Análisis causa en el incremento de salidas no conformes relacionadas con la inasistencia de profesores, con el planteamiento de las estrategias para el control de tendencias crecientes. | J34: 45442 | K34: 45442 | L34: =COUNTIF(Seguimientos!$A$2:$A$1013,A34) | M34: =SUMPRODUCT(MAX((Seguimientos!$A$2:$A$1013=A34)*(Seguimientos!$H$2:$H$1013<>"")*Seguimientos!$B$2:$B$1013)) | N34: =IF(M34=0,"",INDEX(Seguimientos!$F$2:$F$1013,MATCH(A34&"|"&M34,Seguimientos!$K$2:$K$1013,0))) | O34: =IF(M34=0,0,INDEX(Seguimientos!$H$2:$H$1013,MATCH(A34&"|"&M34,Seguimientos!$K$2:$K$1013,0))) | P34: =O34/2 | Q34: =INDEX(Escala!$B$2:$B$6,MATCH(O34,Escala!$A$2:$A$6,0)) | R34: =IF(O34=2,"Sí","No") | S34: =IF(O34=0,"Sí","No") | T34: =IF(AND(ISNUMBER(K34),O34<2),IF(K34<INDEX('Por sistema'!$D$5:$D$9,MATCH(B34,'Por sistema'!$A$5:$A$9,0)),"Sí","No"),"No")
A35: sgc-2023-26 | B35: SGC | C35: Sistema de Gestión de Calidad | D35: 2023 | E35: 26 | F35: Actualizar la Resolución No. 096 de 2021 con el fin de actualizar los lineamientos (Política) y los objetivos del sistema de gestión de la Calidad, de acuerdo con el nuevo Plan Rectoral y Plan de Desarrollo. | G35: Oficina de Calidad - trámite ante los cuerpos colegiados | H35: Calidad, Cuerpos Colegiados y Comités | I35: Resolución No. 096 de 2021 actualizada, de acuerdo a los documentos maestros para la vigencia 2024. | J35: 45473 | K35: 45473 | L35: =COUNTIF(Seguimientos!$A$2:$A$1013,A35) | M35: =SUMPRODUCT(MAX((Seguimientos!$A$2:$A$1013=A35)*(Seguimientos!$H$2:$H$1013<>"")*Seguimientos!$B$2:$B$1013)) | N35: =IF(M35=0,"",INDEX(Seguimientos!$F$2:$F$1013,MATCH(A35&"|"&M35,Seguimientos!$K$2:$K$1013,0))) | O35: =IF(M35=0,0,INDEX(Seguimientos!$H$2:$H$1013,MATCH(A35&"|"&M35,Seguimientos!$K$2:$K$1013,0))) | P35: =O35/2 | Q35: =INDEX(Escala!$B$2:$B$6,MATCH(O35,Escala!$A$2:$A$6,0)) | R35: =IF(O35=2,"Sí","No") | S35: =IF(O35=0,"Sí","No") | T35: =IF(AND(ISNUMBER(K35),O35<2),IF(K35<INDEX('Por sistema'!$D$5:$D$9,MATCH(B35,'Por sistema'!$A$5:$A$9,0)),"Sí","No"),"No")
A36: sgc-2023-27 | B36: SGC | C36: Sistema de Gestión de Calidad | D36: 2023 | E36: 27 | F36: Actualizar el Modelo de Evaluación para los gestores del conocimiento en relación con el procedimiento, la estructura de la evaluación, la plataforma para el procesamiento de la información y la aprobación del Consejo Académico. | G36: Vicerrectoría Académica - Oficina de Desarrollo Académico - EFAD | H36: Vicerrectoría Académica, Apoyo y Desarrollo Académico, Educación Virtual y EFAD | I36: Nuevo Modelo de Evaluación para los gestores del conocimiento y procedimiento actualizado. | J36: 45473 | K36: 45473 | L36: =COUNTIF(Seguimientos!$A$2:$A$1013,A36) | M36: =SUMPRODUCT(MAX((Seguimientos!$A$2:$A$1013=A36)*(Seguimientos!$H$2:$H$1013<>"")*Seguimientos!$B$2:$B$1013)) | N36: =IF(M36=0,"",INDEX(Seguimientos!$F$2:$F$1013,MATCH(A36&"|"&M36,Seguimientos!$K$2:$K$1013,0))) | O36: =IF(M36=0,0,INDEX(Seguimientos!$H$2:$H$1013,MATCH(A36&"|"&M36,Seguimientos!$K$2:$K$1013,0))) | P36: =O36/2 | Q36: =INDEX(Escala!$B$2:$B$6,MATCH(O36,Escala!$A$2:$A$6,0)) | R36: =IF(O36=2,"Sí","No") | S36: =IF(O36=0,"Sí","No") | T36: =IF(AND(ISNUMBER(K36),O36<2),IF(K36<INDEX('Por sistema'!$D$5:$D$9,MATCH(B36,'Por sistema'!$A$5:$A$9,0)),"Sí","No"),"No")
A37: sgc-2023-28 | B37: SGC | C37: Sistema de Gestión de Calidad | D37: 2023 | E37: 28 | F37: En línea con la proposición establecida dentro de la sección de Objetivos de Calidad, si estos se actualizan, es necesario reevaluar toda la batería de indicadores en el año 2024, para ajustarlos o alinearlos en coherencia con las directrices que se definan en el Plan Rectoral y el Plan de Desarrollo. | G37: Oficina de Calidad - Comité SAC - Comisión de Gestión | H37: Calidad, Cuerpos Colegiados y Comités | I37: Batería de indicadores actualizada de acuerdo con los lineamientos de los documentos maestro(Plan rectoral y Plan de acción 2024) | J37: 45473 | K37: 45473 | L37: =COUNTIF(Seguimientos!$A$2:$A$1013,A37) | M37: =SUMPRODUCT(MAX((Seguimientos!$A$2:$A$1013=A37)*(Seguimientos!$H$2:$H$1013<>"")*Seguimientos!$B$2:$B$1013)) | N37: =IF(M37=0,"",INDEX(Seguimientos!$F$2:$F$1013,MATCH(A37&"|"&M37,Seguimientos!$K$2:$K$1013,0))) | O37: =IF(M37=0,0,INDEX(Seguimientos!$H$2:$H$1013,MATCH(A37&"|"&M37,Seguimientos!$K$2:$K$1013,0))) | P37: =O37/2 | Q37: =INDEX(Escala!$B$2:$B$6,MATCH(O37,Escala!$A$2:$A$6,0)) | R37: =IF(O37=2,"Sí","No") | S37: =IF(O37=0,"Sí","No") | T37: =IF(AND(ISNUMBER(K37),O37<2),IF(K37<INDEX('Por sistema'!$D$5:$D$9,MATCH(B37,'Por sistema'!$A$5:$A$9,0)),"Sí","No"),"No")
A38: sgc-2023-29 | B38: SGC | C38: Sistema de Gestión de Calidad | D38: 2023 | E38: 29 | F38: Realizar el seguimiento a la consolidación y avance del PETI. | G38: Comité de Sistemas | H38: Sistemas y Tecnología | I38: Informe de seguimiento a la consolidación y avance del PETI. | J38: junio 2024 | L38: =COUNTIF(Seguimientos!$A$2:$A$1013,A38) | M38: =SUMPRODUCT(MAX((Seguimientos!$A$2:$A$1013=A38)*(Seguimientos!$H$2:$H$1013<>"")*Seguimientos!$B$2:$B$1013)) | N38: =IF(M38=0,"",INDEX(Seguimientos!$F$2:$F$1013,MATCH(A38&"|"&M38,Seguimientos!$K$2:$K$1013,0))) | O38: =IF(M38=0,0,INDEX(Seguimientos!$H$2:$H$1013,MATCH(A38&"|"&M38,Seguimientos!$K$2:$K$1013,0))) | P38: =O38/2 | Q38: =INDEX(Escala!$B$2:$B$6,MATCH(O38,Escala!$A$2:$A$6,0)) | R38: =IF(O38=2,"Sí","No") | S38: =IF(O38=0,"Sí","No") | T38: =IF(AND(ISNUMBER(K38),O38<2),IF(K38<INDEX('Por sistema'!$D$5:$D$9,MATCH(B38,'Por sistema'!$A$5:$A$9,0)),"Sí","No"),"No")
A39: sgc-2023-30 | B39: SGC | C39: Sistema de Gestión de Calidad | D39: 2023 | E39: 30 | F39: Implementar la estrategia de cliente oculto para medir la efectividad de atención por medio telefónico. | G39: Oficina de Atención al Ciudadano | H39: Atención al Ciudadano | I39: Informe de implementación de la estrategia de cliente oculto para medir la efectividad de atención por medio telefónico. | J39: junio 2024 | L39: =COUNTIF(Seguimientos!$A$2:$A$1013,A39) | M39: =SUMPRODUCT(MAX((Seguimientos!$A$2:$A$1013=A39)*(Seguimientos!$H$2:$H$1013<>"")*Seguimientos!$B$2:$B$1013)) | N39: =IF(M39=0,"",INDEX(Seguimientos!$F$2:$F$1013,MATCH(A39&"|"&M39,Seguimientos!$K$2:$K$1013,0))) | O39: =IF(M39=0,0,INDEX(Seguimientos!$H$2:$H$1013,MATCH(A39&"|"&M39,Seguimientos!$K$2:$K$1013,0))) | P39: =O39/2 | Q39: =INDEX(Escala!$B$2:$B$6,MATCH(O39,Escala!$A$2:$A$6,0)) | R39: =IF(O39=2,"Sí","No") | S39: =IF(O39=0,"Sí","No") | T39: =IF(AND(ISNUMBER(K39),O39<2),IF(K39<INDEX('Por sistema'!$D$5:$D$9,MATCH(B39,'Por sistema'!$A$5:$A$9,0)),"Sí","No"),"No")
A40: sgc-2023-31 | B40: SGC | C40: Sistema de Gestión de Calidad | D40: 2023 | E40: 31 | F40: Crear un equipo interdisciplinario con las áreas de planeación, calidad, control interno y financiera, con el fin de dar lineamientos sobre los riesgos fiscales e incorporarlos a la metodología de riesgos, atendiendo la guía del DAFP de la vigencia 2022. | G40: Control Interno | H40: Control Interno | I40: Acta de conformación del equipo interdisciplinario y registros de asistencia de las sesiones de trabajo. | J40: 45504 | K40: 45504 | L40: =COUNTIF(Seguimientos!$A$2:$A$1013,A40) | M40: =SUMPRODUCT(MAX((Seguimientos!$A$2:$A$1013=A40)*(Seguimientos!$H$2:$H$1013<>"")*Seguimientos!$B$2:$B$1013)) | N40: =IF(M40=0,"",INDEX(Seguimientos!$F$2:$F$1013,MATCH(A40&"|"&M40,Seguimientos!$K$2:$K$1013,0))) | O40: =IF(M40=0,0,INDEX(Seguimientos!$H$2:$H$1013,MATCH(A40&"|"&M40,Seguimientos!$K$2:$K$1013,0))) | P40: =O40/2 | Q40: =INDEX(Escala!$B$2:$B$6,MATCH(O40,Escala!$A$2:$A$6,0)) | R40: =IF(O40=2,"Sí","No") | S40: =IF(O40=0,"Sí","No") | T40: =IF(AND(ISNUMBER(K40),O40<2),IF(K40<INDEX('Por sistema'!$D$5:$D$9,MATCH(B40,'Por sistema'!$A$5:$A$9,0)),"Sí","No"),"No")
A41: sgc-2023-32 | B41: SGC | C41: Sistema de Gestión de Calidad | D41: 2023 | E41: 32 | F41: Reinducción a los funcionarios en gestión documental física y digital. | G41: Archivo y Correspondencia | H41: Archivo y Correspondencia | I41: Registros de asistencia o grabaciones de las sesiones de reinducción. | J41: De conformidad al cronograma establecido por la Oficina de Archivo y Correspondencia para la vigencia 2024 | L41: =COUNTIF(Seguimientos!$A$2:$A$1013,A41) | M41: =SUMPRODUCT(MAX((Seguimientos!$A$2:$A$1013=A41)*(Seguimientos!$H$2:$H$1013<>"")*Seguimientos!$B$2:$B$1013)) | N41: =IF(M41=0,"",INDEX(Seguimientos!$F$2:$F$1013,MATCH(A41&"|"&M41,Seguimientos!$K$2:$K$1013,0))) | O41: =IF(M41=0,0,INDEX(Seguimientos!$H$2:$H$1013,MATCH(A41&"|"&M41,Seguimientos!$K$2:$K$1013,0))) | P41: =O41/2 | Q41: =INDEX(Escala!$B$2:$B$6,MATCH(O41,Escala!$A$2:$A$6,0)) | R41: =IF(O41=2,"Sí","No") | S41: =IF(O41=0,"Sí","No") | T41: =IF(AND(ISNUMBER(K41),O41<2),IF(K41<INDEX('Por sistema'!$D$5:$D$9,MATCH(B41,'Por sistema'!$A$5:$A$9,0)),"Sí","No"),"No")
A42: sgc-2023-33 | B42: SGC | C42: Sistema de Gestión de Calidad | D42: 2023 | E42: 33 | F42: Incluir dentro del programa de inducción y reinducción como anexos a los término fijo y planta, la realización de cursos virtuales en líneas de defensa y control de información documentada mínimo cada dos años. | G42: Dirección de Control Interno - Calidad - Talento Humano - Educación Virtual. | H42: Talento Humano, Control Interno, Calidad, Educación Virtual y EFAD | I42: Curso virtual activo y en funcionamiento en aulas virtuales, MOOCs. | J42: Prioridad Calidad IPA 2024 y posteriormente líneas de defensa IIPA 2024 | L42: =COUNTIF(Seguimientos!$A$2:$A$1013,A42) | M42: =SUMPRODUCT(MAX((Seguimientos!$A$2:$A$1013=A42)*(Seguimientos!$H$2:$H$1013<>"")*Seguimientos!$B$2:$B$1013)) | N42: =IF(M42=0,"",INDEX(Seguimientos!$F$2:$F$1013,MATCH(A42&"|"&M42,Seguimientos!$K$2:$K$1013,0))) | O42: =IF(M42=0,0,INDEX(Seguimientos!$H$2:$H$1013,MATCH(A42&"|"&M42,Seguimientos!$K$2:$K$1013,0))) | P42: =O42/2 | Q42: =INDEX(Escala!$B$2:$B$6,MATCH(O42,Escala!$A$2:$A$6,0)) | R42: =IF(O42=2,"Sí","No") | S42: =IF(O42=0,"Sí","No") | T42: =IF(AND(ISNUMBER(K42),O42<2),IF(K42<INDEX('Por sistema'!$D$5:$D$9,MATCH(B42,'Por sistema'!$A$5:$A$9,0)),"Sí","No"),"No")
A43: sgc-2023-34 | B43: SGC | C43: Sistema de Gestión de Calidad | D43: 2023 | E43: 34 | F43: Proponer la implementación de salario emocional a los líderes de proceso que gestionaron de manera efectiva planes de mejora, previa evaluación por parte del Comité de programas de incentivos y bienestar, y comités de capacitación. | G43: Talento Humano - cuerpos colegiados correspondientes | H43: Talento Humano, Cuerpos Colegiados y Comités | I43: Informe de propuesta para la implementación de salario emocional a los líderes de proceso que gestionaron de manera efectiva planes de mejora, previa evaluación por parte del Comité de programas de incentivos y bienestar, y comités de capacitación. | J43: vigencia 2024 (No pecuniarios) | L43: =COUNTIF(Seguimientos!$A$2:$A$1013,A43) | M43: =SUMPRODUCT(MAX((Seguimientos!$A$2:$A$1013=A43)*(Seguimientos!$H$2:$H$1013<>"")*Seguimientos!$B$2:$B$1013)) | N43: =IF(M43=0,"",INDEX(Seguimientos!$F$2:$F$1013,MATCH(A43&"|"&M43,Seguimientos!$K$2:$K$1013,0))) | O43: =IF(M43=0,0,INDEX(Seguimientos!$H$2:$H$1013,MATCH(A43&"|"&M43,Seguimientos!$K$2:$K$1013,0))) | P43: =O43/2 | Q43: =INDEX(Escala!$B$2:$B$6,MATCH(O43,Escala!$A$2:$A$6,0)) | R43: =IF(O43=2,"Sí","No") | S43: =IF(O43=0,"Sí","No") | T43: =IF(AND(ISNUMBER(K43),O43<2),IF(K43<INDEX('Por sistema'!$D$5:$D$9,MATCH(B43,'Por sistema'!$A$5:$A$9,0)),"Sí","No"),"No")
A44: sgc-2023-35 | B44: SGC | C44: Sistema de Gestión de Calidad | D44: 2023 | E44: 35 | F44: Trasladar el indicador de calibración de equipos y elementos educativos de investigación a la Dirección de Investigación. | G44: Oficina de Apoyo Académico - Oficina de Calidad, | H44: Calidad, Apoyo y Desarrollo Académico | I44: N/A, El presupuesto fue asignado nuevamente al proceso de apoyo académico y la supervisión del contrato del metrólogo esta a cargo de la jefatura de Apoyo académico. | J44: vigencia 2024 | L44: =COUNTIF(Seguimientos!$A$2:$A$1013,A44) | M44: =SUMPRODUCT(MAX((Seguimientos!$A$2:$A$1013=A44)*(Seguimientos!$H$2:$H$1013<>"")*Seguimientos!$B$2:$B$1013)) | N44: =IF(M44=0,"",INDEX(Seguimientos!$F$2:$F$1013,MATCH(A44&"|"&M44,Seguimientos!$K$2:$K$1013,0))) | O44: =IF(M44=0,0,INDEX(Seguimientos!$H$2:$H$1013,MATCH(A44&"|"&M44,Seguimientos!$K$2:$K$1013,0))) | P44: =O44/2 | Q44: =INDEX(Escala!$B$2:$B$6,MATCH(O44,Escala!$A$2:$A$6,0)) | R44: =IF(O44=2,"Sí","No") | S44: =IF(O44=0,"Sí","No") | T44: =IF(AND(ISNUMBER(K44),O44<2),IF(K44<INDEX('Por sistema'!$D$5:$D$9,MATCH(B44,'Por sistema'!$A$5:$A$9,0)),"Sí","No"),"No")
A45: sgc-2023-36 | B45: SGC | C45: Sistema de Gestión de Calidad | D45: 2023 | E45: 36 | F45: Hacer una revisión del procedimiento relacionado con el banco de programas y proyectos para el ajuste, incluyendo a las áreas correspondientes de acuerdo con la naturaleza de los proyectos, para que apoyen la formulación y la supervisión de los contratos que se deriven dentro del proyecto cuando se materialice. | G45: Apoyo Académico - Bienes y Servicios - Dirección de Planeación | H45: Planeación Institucional, Bienes, Servicios y Compras, Apoyo y Desarrollo Académico | I45: Informes con las áreas o procesos encargados con el fin de realizar ajuste al procedimiento relacionado con el banco de programas y proyectos. | J45: vigencia 2024 | L45: =COUNTIF(Seguimientos!$A$2:$A$1013,A45) | M45: =SUMPRODUCT(MAX((Seguimientos!$A$2:$A$1013=A45)*(Seguimientos!$H$2:$H$1013<>"")*Seguimientos!$B$2:$B$1013)) | N45: =IF(M45=0,"",INDEX(Seguimientos!$F$2:$F$1013,MATCH(A45&"|"&M45,Seguimientos!$K$2:$K$1013,0))) | O45: =IF(M45=0,0,INDEX(Seguimientos!$H$2:$H$1013,MATCH(A45&"|"&M45,Seguimientos!$K$2:$K$1013,0))) | P45: =O45/2 | Q45: =INDEX(Escala!$B$2:$B$6,MATCH(O45,Escala!$A$2:$A$6,0)) | R45: =IF(O45=2,"Sí","No") | S45: =IF(O45=0,"Sí","No") | T45: =IF(AND(ISNUMBER(K45),O45<2),IF(K45<INDEX('Por sistema'!$D$5:$D$9,MATCH(B45,'Por sistema'!$A$5:$A$9,0)),"Sí","No"),"No")
A46: sgc-2023-37 | B46: SGC | C46: Sistema de Gestión de Calidad | D46: 2023 | E46: 37 | F46: Socializar los datos generados en las encuestas de satisfacción a las áreas responsables, con el fin de tomar decisiones. | G46: Dirección de Planeación | H46: Planeación Institucional | I46: Registros de asistencia o grabaciones de las socializaciones de los datos de encuestas de satisfacción. | J46: vigencia 2024 | L46: =COUNTIF(Seguimientos!$A$2:$A$1013,A46) | M46: =SUMPRODUCT(MAX((Seguimientos!$A$2:$A$1013=A46)*(Seguimientos!$H$2:$H$1013<>"")*Seguimientos!$B$2:$B$1013)) | N46: =IF(M46=0,"",INDEX(Seguimientos!$F$2:$F$1013,MATCH(A46&"|"&M46,Seguimientos!$K$2:$K$1013,0))) | O46: =IF(M46=0,0,INDEX(Seguimientos!$H$2:$H$1013,MATCH(A46&"|"&M46,Seguimientos!$K$2:$K$1013,0))) | P46: =O46/2 | Q46: =INDEX(Escala!$B$2:$B$6,MATCH(O46,Escala!$A$2:$A$6,0)) | R46: =IF(O46=2,"Sí","No") | S46: =IF(O46=0,"Sí","No") | T46: =IF(AND(ISNUMBER(K46),O46<2),IF(K46<INDEX('Por sistema'!$D$5:$D$9,MATCH(B46,'Por sistema'!$A$5:$A$9,0)),"Sí","No"),"No")
A47: sgc-2023-38 | B47: SGC | C47: Sistema de Gestión de Calidad | D47: 2023 | E47: 38 | F47: Fortalecer los programas de capacitación de forma que el personal desarrolle nuevas competencias y habilidades para desempeñarse en diferentes dependencias al interior de la institución. | G47: Dirección de Talento Humano | H47: Talento Humano | I47: Análisis de tendencias para evidenciar el fortalecimiento en los programas de capacitación y desarrollo de nuevas competencias y habilidades en los funcionarios al interior de las dependencias. | J47: vigencia 2024 | L47: =COUNTIF(Seguimientos!$A$2:$A$1013,A47) | M47: =SUMPRODUCT(MAX((Seguimientos!$A$2:$A$1013=A47)*(Seguimientos!$H$2:$H$1013<>"")*Seguimientos!$B$2:$B$1013)) | N47: =IF(M47=0,"",INDEX(Seguimientos!$F$2:$F$1013,MATCH(A47&"|"&M47,Seguimientos!$K$2:$K$1013,0))) | O47: =IF(M47=0,0,INDEX(Seguimientos!$H$2:$H$1013,MATCH(A47&"|"&M47,Seguimientos!$K$2:$K$1013,0))) | P47: =O47/2 | Q47: =INDEX(Escala!$B$2:$B$6,MATCH(O47,Escala!$A$2:$A$6,0)) | R47: =IF(O47=2,"Sí","No") | S47: =IF(O47=0,"Sí","No") | T47: =IF(AND(ISNUMBER(K47),O47<2),IF(K47<INDEX('Por sistema'!$D$5:$D$9,MATCH(B47,'Por sistema'!$A$5:$A$9,0)),"Sí","No"),"No")
A48: sgc-2023-39 | B48: SGC | C48: Sistema de Gestión de Calidad | D48: 2023 | E48: 39 | F48: Generar estímulos para motivar el desempeño eficaz y el compromiso de los servidores considerando los de carácter deportivo, recreativo y vacacionales, artísticos y culturales, así como la prevención de la salud, y el desarrollo profesional, entre otros. | G48: Dirección de Talento Humano | H48: Talento Humano | I48: Documento de propuesta de generación de estímulos en la motivación del desempeño eficaz y el compromiso de los servidores. | J48: vigencia 2024 | L48: =COUNTIF(Seguimientos!$A$2:$A$1013,A48) | M48: =SUMPRODUCT(MAX((Seguimientos!$A$2:$A$1013=A48)*(Seguimientos!$H$2:$H$1013<>"")*Seguimientos!$B$2:$B$1013)) | N48: =IF(M48=0,"",INDEX(Seguimientos!$F$2:$F$1013,MATCH(A48&"|"&M48,Seguimientos!$K$2:$K$1013,0))) | O48: =IF(M48=0,0,INDEX(Seguimientos!$H$2:$H$1013,MATCH(A48&"|"&M48,Seguimientos!$K$2:$K$1013,0))) | P48: =O48/2 | Q48: =INDEX(Escala!$B$2:$B$6,MATCH(O48,Escala!$A$2:$A$6,0)) | R48: =IF(O48=2,"Sí","No") | S48: =IF(O48=0,"Sí","No") | T48: =IF(AND(ISNUMBER(K48),O48<2),IF(K48<INDEX('Por sistema'!$D$5:$D$9,MATCH(B48,'Por sistema'!$A$5:$A$9,0)),"Sí","No"),"No")
A49: sgc-2023-40 | B49: SGC | C49: Sistema de Gestión de Calidad | D49: 2023 | E49: 40 | F49: Fortalecer las competencias y habilidades de los funcionarios a través de los programas de capacitación y apoyo posgradual, teniendo en cuenta que estas deben estar relacionadas con las funciones o con el área en donde se encuentran los funcionarios prestando sus servicios. | G49: Dirección de Talento Humano | H49: Talento Humano | I49: Documento de propuesta de fortalecimiento de las competencias y habilidades de los funcionarios a través de los programas de capacitación y apoyo posgradual, específicos al área en que están prestando su servicio. | J49: vigencia 2024 | L49: =COUNTIF(Seguimientos!$A$2:$A$1013,A49) | M49: =SUMPRODUCT(MAX((Seguimientos!$A$2:$A$1013=A49)*(Seguimientos!$H$2:$H$1013<>"")*Seguimientos!$B$2:$B$1013)) | N49: =IF(M49=0,"",INDEX(Seguimientos!$F$2:$F$1013,MATCH(A49&"|"&M49,Seguimientos!$K$2:$K$1013,0))) | O49: =IF(M49=0,0,INDEX(Seguimientos!$H$2:$H$1013,MATCH(A49&"|"&M49,Seguimientos!$K$2:$K$1013,0))) | P49: =O49/2 | Q49: =INDEX(Escala!$B$2:$B$6,MATCH(O49,Escala!$A$2:$A$6,0)) | R49: =IF(O49=2,"Sí","No") | S49: =IF(O49=0,"Sí","No") | T49: =IF(AND(ISNUMBER(K49),O49<2),IF(K49<INDEX('Por sistema'!$D$5:$D$9,MATCH(B49,'Por sistema'!$A$5:$A$9,0)),"Sí","No"),"No")
A50: sgc-2023-41 | B50: SGC | C50: Sistema de Gestión de Calidad | D50: 2023 | E50: 41 | F50: Fomentar los índices de rotación interna del personal con el propósito de potenciar habilidades y destrezas para el correcto desempeño de los diferentes cargos en la institución previa convocatoria interna. | G50: Dirección de Talento Humano | H50: Talento Humano | I50: Documento de propuesta de fomento de índices de rotación interna del personal con el propósito de potenciar habilidades y destrezas para el correcto desempeño de los diferentes cargos en la institución previa convocatoria interna. | J50: vigencia 2024 | L50: =COUNTIF(Seguimientos!$A$2:$A$1013,A50) | M50: =SUMPRODUCT(MAX((Seguimientos!$A$2:$A$1013=A50)*(Seguimientos!$H$2:$H$1013<>"")*Seguimientos!$B$2:$B$1013)) | N50: =IF(M50=0,"",INDEX(Seguimientos!$F$2:$F$1013,MATCH(A50&"|"&M50,Seguimientos!$K$2:$K$1013,0))) | O50: =IF(M50=0,0,INDEX(Seguimientos!$H$2:$H$1013,MATCH(A50&"|"&M50,Seguimientos!$K$2:$K$1013,0))) | P50: =O50/2 | Q50: =INDEX(Escala!$B$2:$B$6,MATCH(O50,Escala!$A$2:$A$6,0)) | R50: =IF(O50=2,"Sí","No") | S50: =IF(O50=0,"Sí","No") | T50: =IF(AND(ISNUMBER(K50),O50<2),IF(K50<INDEX('Por sistema'!$D$5:$D$9,MATCH(B50,'Por sistema'!$A$5:$A$9,0)),"Sí","No"),"No")
A51: sgc-2023-42 | B51: SGC | C51: Sistema de Gestión de Calidad | D51: 2023 | E51: 42 | F51: Elevar la meta del indicador de eficacia en control del riesgo, considerando que la traza histórica de los tres períodos anteriores es de 81%. | G51: Comité SAC | H51: Cuerpos Colegiados y Comités | I51: Acta de aprobación de aumento en la meta por parte del Comité SAC o decisión que aplique. | J51: Vigencia 2024 | L51: =COUNTIF(Seguimientos!$A$2:$A$1013,A51) | M51: =SUMPRODUCT(MAX((Seguimientos!$A$2:$A$1013=A51)*(Seguimientos!$H$2:$H$1013<>"")*Seguimientos!$B$2:$B$1013)) | N51: =IF(M51=0,"",INDEX(Seguimientos!$F$2:$F$1013,MATCH(A51&"|"&M51,Seguimientos!$K$2:$K$1013,0))) | O51: =IF(M51=0,0,INDEX(Seguimientos!$H$2:$H$1013,MATCH(A51&"|"&M51,Seguimientos!$K$2:$K$1013,0))) | P51: =O51/2 | Q51: =INDEX(Escala!$B$2:$B$6,MATCH(O51,Escala!$A$2:$A$6,0)) | R51: =IF(O51=2,"Sí","No") | S51: =IF(O51=0,"Sí","No") | T51: =IF(AND(ISNUMBER(K51),O51<2),IF(K51<INDEX('Por sistema'!$D$5:$D$9,MATCH(B51,'Por sistema'!$A$5:$A$9,0)),"Sí","No"),"No")
A52: sgc-2023-43 | B52: SGC | C52: Sistema de Gestión de Calidad | D52: 2023 | E52: 43 | F52: El rol y las responsabilidades de líder de los sistemas integrados de gestión se le asigna a la coordinación de la Oficina de Calidad, la cual depende de la Dirección de Planeación Institucional. | G52: Dirección de Planeación | H52: Planeación Institucional | I52: Plan de trabajo del Coordinador de Calidad y apropiación de estas actividades. | J52: Vigencia 2024 | L52: =COUNTIF(Seguimientos!$A$2:$A$1013,A52) | M52: =SUMPRODUCT(MAX((Seguimientos!$A$2:$A$1013=A52)*(Seguimientos!$H$2:$H$1013<>"")*Seguimientos!$B$2:$B$1013)) | N52: =IF(M52=0,"",INDEX(Seguimientos!$F$2:$F$1013,MATCH(A52&"|"&M52,Seguimientos!$K$2:$K$1013,0))) | O52: =IF(M52=0,0,INDEX(Seguimientos!$H$2:$H$1013,MATCH(A52&"|"&M52,Seguimientos!$K$2:$K$1013,0))) | P52: =O52/2 | Q52: =INDEX(Escala!$B$2:$B$6,MATCH(O52,Escala!$A$2:$A$6,0)) | R52: =IF(O52=2,"Sí","No") | S52: =IF(O52=0,"Sí","No") | T52: =IF(AND(ISNUMBER(K52),O52<2),IF(K52<INDEX('Por sistema'!$D$5:$D$9,MATCH(B52,'Por sistema'!$A$5:$A$9,0)),"Sí","No"),"No")
... A54: sgc-2023-45 | B54: SGC | C54: Sistema de Gestión de Calidad | D54: 2023 | E54: 45 | F54: Implementar los cambios en los procedimientos según ruta crítica. | G54: Oficina de Calidad - Líder del Proceso | H54: Calidad | I54: Documentos actualizados en el MOD, de acuerdo a ruta crítica definida para la vigencia 2024. | J54: Vigencia 2024 | L54: =COUNTIF(Seguimientos!$A$2:$A$1013,A54) | M54: =SUMPRODUCT(MAX((Seguimientos!$A$2:$A$1013=A54)*(Seguimientos!$H$2:$H$1013<>"")*Seguimientos!$B$2:$B$1013)) | N54: =IF(M54=0,"",INDEX(Seguimientos!$F$2:$F$1013,MATCH(A54&"|"&M54,Seguimientos!$K$2:$K$1013,0))) | O54: =IF(M54=0,0,INDEX(Seguimientos!$H$2:$H$1013,MATCH(A54&"|"&M54,Seguimientos!$K$2:$K$1013,0))) | P54: =O54/2 | Q54: =INDEX(Escala!$B$2:$B$6,MATCH(O54,Escala!$A$2:$A$6,0)) | R54: =IF(O54=2,"Sí","No") | S54: =IF(O54=0,"Sí","No") | T54: =IF(AND(ISNUMBER(K54),O54<2),IF(K54<INDEX('Por sistema'!$D$5:$D$9,MATCH(B54,'Por sistema'!$A$5:$A$9,0)),"Sí","No"),"No")
A55: sgc-2024-1 | B55: SGC | C55: Sistema de Gestión de Calidad | D55: 2024 | E55: 1 | F55: Priorizar los desarrollos que agilicen y aseguren la eficiencia administrativa en beneficio de los procesos, asegurando la conectividad y cubrimiento a toda la comunidad universitaria. Priorizar el aplicativo de reporte de Salidas No Conformes con el fin de que se convierta en una herramienta de reporte, gestión y control. | G55: Dirección de Sistemas y Tecnología, Sistema de Gestión de Calidad | H55: Sistemas y Tecnología, Calidad | I55: Acta de entrega de desarrollos a producción. Evidencias de la divulgación de los desarrollos específicos. | J55: 45992 | K55: 45992 | L55: =COUNTIF(Seguimientos!$A$2:$A$1013,A55) | M55: =SUMPRODUCT(MAX((Seguimientos!$A$2:$A$1013=A55)*(Seguimientos!$H$2:$H$1013<>"")*Seguimientos!$B$2:$B$1013)) | N55: =IF(M55=0,"",INDEX(Seguimientos!$F$2:$F$1013,MATCH(A55&"|"&M55,Seguimientos!$K$2:$K$1013,0))) | O55: =IF(M55=0,0,INDEX(Seguimientos!$H$2:$H$1013,MATCH(A55&"|"&M55,Seguimientos!$K$2:$K$1013,0))) | P55: =O55/2 | Q55: =INDEX(Escala!$B$2:$B$6,MATCH(O55,Escala!$A$2:$A$6,0)) | R55: =IF(O55=2,"Sí","No") | S55: =IF(O55=0,"Sí","No") | T55: =IF(AND(ISNUMBER(K55),O55<2),IF(K55<INDEX('Por sistema'!$D$5:$D$9,MATCH(B55,'Por sistema'!$A$5:$A$9,0)),"Sí","No"),"No")
A56: sgc-2024-2 | B56: SGC | C56: Sistema de Gestión de Calidad | D56: 2024 | E56: 2 | F56: Gestionar la realización de capacitaciones a los funcionarios en cuanto a la resolución de conflictos, lenguaje claro, servicio de atención al ciudadano inclusivo y la importancia del proceso servicio de atención al ciudadano en cuanto a dar respuesta en los tiempos establecidos por la ley. | G56: Oficina de Talento Humano, Oficina de Atención al Ciudadano, Sistema de Gestión de Calidad | H56: Talento Humano, Calidad, Atención al Ciudadano | I56: Listas de asistencia. Material de las capacitaciones Grabación de las capacitaciones. | J56: 45992 | K56: 45992 | L56: =COUNTIF(Seguimientos!$A$2:$A$1013,A56) | M56: =SUMPRODUCT(MAX((Seguimientos!$A$2:$A$1013=A56)*(Seguimientos!$H$2:$H$1013<>"")*Seguimientos!$B$2:$B$1013)) | N56: =IF(M56=0,"",INDEX(Seguimientos!$F$2:$F$1013,MATCH(A56&"|"&M56,Seguimientos!$K$2:$K$1013,0))) | O56: =IF(M56=0,0,INDEX(Seguimientos!$H$2:$H$1013,MATCH(A56&"|"&M56,Seguimientos!$K$2:$K$1013,0))) | P56: =O56/2 | Q56: =INDEX(Escala!$B$2:$B$6,MATCH(O56,Escala!$A$2:$A$6,0)) | R56: =IF(O56=2,"Sí","No") | S56: =IF(O56=0,"Sí","No") | T56: =IF(AND(ISNUMBER(K56),O56<2),IF(K56<INDEX('Por sistema'!$D$5:$D$9,MATCH(B56,'Por sistema'!$A$5:$A$9,0)),"Sí","No"),"No")
A57: sgc-2024-3 | B57: SGC | C57: Sistema de Gestión de Calidad | D57: 2024 | E57: 3 | F57: Establecer un marco legal y administrativo que valide las posibles medidas correctivas por incumplimiento, en principios legales aplicables, garantizando la transparencia y la equidad a los proveedores que como resultado de los criterios de evaluación su calificación sea calificado como NO CONFORME y de los otros criterios de valoración. | G57: Dirección de Bienes y Servicios, Jefatura de Compras, Sistema de Gestión de Calidad | H57: Calidad, Bienes, Servicios y Compras | I57: Resolución emitida por Bienes y Servicios revisada por jurídica, actualización del manual de compras, actualización de los documentos que soporten la calificación de los proveedores y/o contratistas. | J57: 45839 | K57: 45839 | L57: =COUNTIF(Seguimientos!$A$2:$A$1013,A57) | M57: =SUMPRODUCT(MAX((Seguimientos!$A$2:$A$1013=A57)*(Seguimientos!$H$2:$H$1013<>"")*Seguimientos!$B$2:$B$1013)) | N57: =IF(M57=0,"",INDEX(Seguimientos!$F$2:$F$1013,MATCH(A57&"|"&M57,Seguimientos!$K$2:$K$1013,0))) | O57: =IF(M57=0,0,INDEX(Seguimientos!$H$2:$H$1013,MATCH(A57&"|"&M57,Seguimientos!$K$2:$K$1013,0))) | P57: =O57/2 | Q57: =INDEX(Escala!$B$2:$B$6,MATCH(O57,Escala!$A$2:$A$6,0)) | R57: =IF(O57=2,"Sí","No") | S57: =IF(O57=0,"Sí","No") | T57: =IF(AND(ISNUMBER(K57),O57<2),IF(K57<INDEX('Por sistema'!$D$5:$D$9,MATCH(B57,'Por sistema'!$A$5:$A$9,0)),"Sí","No"),"No")
A58: sgc-2024-4 | B58: SGC | C58: Sistema de Gestión de Calidad | D58: 2024 | E58: 4 | F58: Aprobar la constitución del área para proteger los activos tecnológicos y la información sensible de una organización (cubrir los riesgos relacionados con la seguridad cibernética, robo de datos, el malware y las brechas de seguridad). Para asegurar y garantizar la protección de la infraestructura tecnológica y los datos institucionales. | G58: Dirección de Sistemas y Tecnología | H58: Sistemas y Tecnología | I58: Proyección de presupuesto el área, los roles y responsabilidades del área, información documentada (procedimientos, manuales, formatos) de operación y administración. | J58: 45992 | K58: 45992 | L58: =COUNTIF(Seguimientos!$A$2:$A$1013,A58) | M58: =SUMPRODUCT(MAX((Seguimientos!$A$2:$A$1013=A58)*(Seguimientos!$H$2:$H$1013<>"")*Seguimientos!$B$2:$B$1013)) | N58: =IF(M58=0,"",INDEX(Seguimientos!$F$2:$F$1013,MATCH(A58&"|"&M58,Seguimientos!$K$2:$K$1013,0))) | O58: =IF(M58=0,0,INDEX(Seguimientos!$H$2:$H$1013,MATCH(A58&"|"&M58,Seguimientos!$K$2:$K$1013,0))) | P58: =O58/2 | Q58: =INDEX(Escala!$B$2:$B$6,MATCH(O58,Escala!$A$2:$A$6,0)) | R58: =IF(O58=2,"Sí","No") | S58: =IF(O58=0,"Sí","No") | T58: =IF(AND(ISNUMBER(K58),O58<2),IF(K58<INDEX('Por sistema'!$D$5:$D$9,MATCH(B58,'Por sistema'!$A$5:$A$9,0)),"Sí","No"),"No")
A59: sgc-2024-5 | B59: SGC | C59: Sistema de Gestión de Calidad | D59: 2024 | E59: 5 | F59: En materia de Sistemas y tecnología la aprobación en la constitución del área de Análisis de Datos (cumplir con las políticas para la transformación digital del país, y en el marco de la línea de acción 4.2 “Decisiones Basadas en Datos” del decreto 767 de 2022, el cual refiere al establecimiento de los lineamientos generales de la política de Gobierno Digital. | G59: Dirección de Sistemas y Tecnología | H59: Sistemas y Tecnología | I59: Proyección de presupuesto el área, los roles y responsabilidades del área, información documentada (procedimientos, manuales, formatos) de operación y administración. | J59: 45992 | K59: 45992 | L59: =COUNTIF(Seguimientos!$A$2:$A$1013,A59) | M59: =SUMPRODUCT(MAX((Seguimientos!$A$2:$A$1013=A59)*(Seguimientos!$H$2:$H$1013<>"")*Seguimientos!$B$2:$B$1013)) | N59: =IF(M59=0,"",INDEX(Seguimientos!$F$2:$F$1013,MATCH(A59&"|"&M59,Seguimientos!$K$2:$K$1013,0))) | O59: =IF(M59=0,0,INDEX(Seguimientos!$H$2:$H$1013,MATCH(A59&"|"&M59,Seguimientos!$K$2:$K$1013,0))) | P59: =O59/2 | Q59: =INDEX(Escala!$B$2:$B$6,MATCH(O59,Escala!$A$2:$A$6,0)) | R59: =IF(O59=2,"Sí","No") | S59: =IF(O59=0,"Sí","No") | T59: =IF(AND(ISNUMBER(K59),O59<2),IF(K59<INDEX('Por sistema'!$D$5:$D$9,MATCH(B59,'Por sistema'!$A$5:$A$9,0)),"Sí","No"),"No")
A60: sgc-2024-6 | B60: SGC | C60: Sistema de Gestión de Calidad | D60: 2024 | E60: 6 | F60: En materia de recursos físicos, Coordinar con la Dirección de Planeación, la Dirección de Bienes y Servicios, la Dirección Jurídica y expertos externos para diseñar una estrategia integral que permita resolver las situaciones urbanísticas que obstaculicen el crecimiento de la planta física incluyendo el Plan de Infraestructura Física, alineado con los lineamientos establecidos en la norma NTC 6714:2023. | G60: Dirección de Bienes y Servicios, Jefatura de Recursos Físicos y Servicios Generales Dirección Jurídica, Dirección de Planeación Institucional | H60: Planeación Institucional, Bienes, Servicios y Compras, Recursos Físicos, Dirección Jurídica | I60: Cronograma de actividades urbanísticas, asignación de recursos, plan de infraestructura física, soportes técnicos de la adecuación con el visto bueno de la Dirección Jurídica. | J60: 45992 | K60: 45992 | L60: =COUNTIF(Seguimientos!$A$2:$A$1013,A60) | M60: =SUMPRODUCT(MAX((Seguimientos!$A$2:$A$1013=A60)*(Seguimientos!$H$2:$H$1013<>"")*Seguimientos!$B$2:$B$1013)) | N60: =IF(M60=0,"",INDEX(Seguimientos!$F$2:$F$1013,MATCH(A60&"|"&M60,Seguimientos!$K$2:$K$1013,0))) | O60: =IF(M60=0,0,INDEX(Seguimientos!$H$2:$H$1013,MATCH(A60&"|"&M60,Seguimientos!$K$2:$K$1013,0))) | P60: =O60/2 | Q60: =INDEX(Escala!$B$2:$B$6,MATCH(O60,Escala!$A$2:$A$6,0)) | R60: =IF(O60=2,"Sí","No") | S60: =IF(O60=0,"Sí","No") | T60: =IF(AND(ISNUMBER(K60),O60<2),IF(K60<INDEX('Por sistema'!$D$5:$D$9,MATCH(B60,'Por sistema'!$A$5:$A$9,0)),"Sí","No"),"No")
A61: sgc-2024-7 | B61: SGC | C61: Sistema de Gestión de Calidad | D61: 2024 | E61: 7 | F61: Establecer mediante el desarrollo de actividades de formación continua específicas sobre la correcta ejecución de contratos y la gestión de novedades, adiciones, prórrogas o suspensiones, etc. (asegurar que los supervisores e interventores desempeñen de manera efectiva su rol, apoyados en la Resolución 206 de 2012 Art.33 “Responsabilidad de supervisores e interventores” y resolución 170 de 2017 la cual modifica dicho artículo, en la ejecución de los contratos). | G61: Dirección de Bienes y Servicios, Jefatura de Compras, Oficina de Calidad, Dirección de Talento Humano | H61: Talento Humano, Calidad, Bienes, Servicios y Compras | I61: Listas de asistencia, material de las capacitaciones, grabación de las capacitaciones. | J61: 45809 | K61: 45809 | L61: =COUNTIF(Seguimientos!$A$2:$A$1013,A61) | M61: =SUMPRODUCT(MAX((Seguimientos!$A$2:$A$1013=A61)*(Seguimientos!$H$2:$H$1013<>"")*Seguimientos!$B$2:$B$1013)) | N61: =IF(M61=0,"",INDEX(Seguimientos!$F$2:$F$1013,MATCH(A61&"|"&M61,Seguimientos!$K$2:$K$1013,0))) | O61: =IF(M61=0,0,INDEX(Seguimientos!$H$2:$H$1013,MATCH(A61&"|"&M61,Seguimientos!$K$2:$K$1013,0))) | P61: =O61/2 | Q61: =INDEX(Escala!$B$2:$B$6,MATCH(O61,Escala!$A$2:$A$6,0)) | R61: =IF(O61=2,"Sí","No") | S61: =IF(O61=0,"Sí","No") | T61: =IF(AND(ISNUMBER(K61),O61<2),IF(K61<INDEX('Por sistema'!$D$5:$D$9,MATCH(B61,'Por sistema'!$A$5:$A$9,0)),"Sí","No"),"No")
A62: sgc-2024-8 | B62: SGC | C62: Sistema de Gestión de Calidad | D62: 2024 | E62: 8 | F62: Realizar los análisis de Planes de mejoramiento para unificarlos, teniendo en cuenta el origen del hallazgo y la naturaleza de la misma. | G62: Dirección Control Interno, Sistema de Gestión de Calidad | H62: Control Interno, Calidad | I62: PM Plataforma de Control Interno - SEGUIMIENTO. | J62: 45992 | K62: 45992 | L62: =COUNTIF(Seguimientos!$A$2:$A$1013,A62) | M62: =SUMPRODUCT(MAX((Seguimientos!$A$2:$A$1013=A62)*(Seguimientos!$H$2:$H$1013<>"")*Seguimientos!$B$2:$B$1013)) | N62: =IF(M62=0,"",INDEX(Seguimientos!$F$2:$F$1013,MATCH(A62&"|"&M62,Seguimientos!$K$2:$K$1013,0))) | O62: =IF(M62=0,0,INDEX(Seguimientos!$H$2:$H$1013,MATCH(A62&"|"&M62,Seguimientos!$K$2:$K$1013,0))) | P62: =O62/2 | Q62: =INDEX(Escala!$B$2:$B$6,MATCH(O62,Escala!$A$2:$A$6,0)) | R62: =IF(O62=2,"Sí","No") | S62: =IF(O62=0,"Sí","No") | T62: =IF(AND(ISNUMBER(K62),O62<2),IF(K62<INDEX('Por sistema'!$D$5:$D$9,MATCH(B62,'Por sistema'!$A$5:$A$9,0)),"Sí","No"),"No")
A63: sgc-2024-9 | B63: SGC | C63: Sistema de Gestión de Calidad | D63: 2024 | E63: 9 | F63: Para gestionar y mantener la mejora continua del SIG, hacer uso del modelo pensamiento analítico de la universidad de Cundinamarca, para sacar diferencias y conclusiones, elementos importantes para que los procesos sean agiles, amigables, dinámicos y adecuados en los SIG. | G63: Sistema de Gestión de Calidad | H63: Calidad | I63: Informe y estadísticas del SAD | J63: 45992 | K63: 45992 | L63: =COUNTIF(Seguimientos!$A$2:$A$1013,A63) | M63: =SUMPRODUCT(MAX((Seguimientos!$A$2:$A$1013=A63)*(Seguimientos!$H$2:$H$1013<>"")*Seguimientos!$B$2:$B$1013)) | N63: =IF(M63=0,"",INDEX(Seguimientos!$F$2:$F$1013,MATCH(A63&"|"&M63,Seguimientos!$K$2:$K$1013,0))) | O63: =IF(M63=0,0,INDEX(Seguimientos!$H$2:$H$1013,MATCH(A63&"|"&M63,Seguimientos!$K$2:$K$1013,0))) | P63: =O63/2 | Q63: =INDEX(Escala!$B$2:$B$6,MATCH(O63,Escala!$A$2:$A$6,0)) | R63: =IF(O63=2,"Sí","No") | S63: =IF(O63=0,"Sí","No") | T63: =IF(AND(ISNUMBER(K63),O63<2),IF(K63<INDEX('Por sistema'!$D$5:$D$9,MATCH(B63,'Por sistema'!$A$5:$A$9,0)),"Sí","No"),"No")
A64: sgc-2024-10 | B64: SGC | C64: Sistema de Gestión de Calidad | D64: 2024 | E64: 10 | F64: Definir o fomentar las políticas de traslados a nivel administrativo y académico, para contrarrestar la fuga de conocimiento y mejorar resultados de permanencia (tipo salario emocional). | G64: Dirección de Talento Humano, Vicerrectoría Administrativa y Financiera, Sistema de Gestión de Calidad | H64: Talento Humano, Calidad, Vicerrectoría Administrativa y Financiera | I64: Cronograma de plan de trabajo Política de Gestión de Conocimiento Divulgación Medición y Resultados. | J64: 45992 | K64: 45992 | L64: =COUNTIF(Seguimientos!$A$2:$A$1013,A64) | M64: =SUMPRODUCT(MAX((Seguimientos!$A$2:$A$1013=A64)*(Seguimientos!$H$2:$H$1013<>"")*Seguimientos!$B$2:$B$1013)) | N64: =IF(M64=0,"",INDEX(Seguimientos!$F$2:$F$1013,MATCH(A64&"|"&M64,Seguimientos!$K$2:$K$1013,0))) | O64: =IF(M64=0,0,INDEX(Seguimientos!$H$2:$H$1013,MATCH(A64&"|"&M64,Seguimientos!$K$2:$K$1013,0))) | P64: =O64/2 | Q64: =INDEX(Escala!$B$2:$B$6,MATCH(O64,Escala!$A$2:$A$6,0)) | R64: =IF(O64=2,"Sí","No") | S64: =IF(O64=0,"Sí","No") | T64: =IF(AND(ISNUMBER(K64),O64<2),IF(K64<INDEX('Por sistema'!$D$5:$D$9,MATCH(B64,'Por sistema'!$A$5:$A$9,0)),"Sí","No"),"No")
A65: sgc-2024-11 | B65: SGC | C65: Sistema de Gestión de Calidad | D65: 2024 | E65: 11 | F65: Incluir en la evaluación de desempeño a nivel Administrativo y Académico, la toma de conciencia en los temas relacionados con las responsabilidades y autoridad frente a los diferentes Sistemas de Gestión de la Universidad. | G65: Dirección de Talento Humano, Sistema de Gestión de Calidad | H65: Talento Humano, Calidad | I65: Cronograma de plan de trabajo Resolución Evaluación Desempeño Divulgación Aplicación, Medición y Resultados Evaluación del Desempeño | J65: 45992 | K65: 45992 | L65: =COUNTIF(Seguimientos!$A$2:$A$1013,A65) | M65: =SUMPRODUCT(MAX((Seguimientos!$A$2:$A$1013=A65)*(Seguimientos!$H$2:$H$1013<>"")*Seguimientos!$B$2:$B$1013)) | N65: =IF(M65=0,"",INDEX(Seguimientos!$F$2:$F$1013,MATCH(A65&"|"&M65,Seguimientos!$K$2:$K$1013,0))) | O65: =IF(M65=0,0,INDEX(Seguimientos!$H$2:$H$1013,MATCH(A65&"|"&M65,Seguimientos!$K$2:$K$1013,0))) | P65: =O65/2 | Q65: =INDEX(Escala!$B$2:$B$6,MATCH(O65,Escala!$A$2:$A$6,0)) | R65: =IF(O65=2,"Sí","No") | S65: =IF(O65=0,"Sí","No") | T65: =IF(AND(ISNUMBER(K65),O65<2),IF(K65<INDEX('Por sistema'!$D$5:$D$9,MATCH(B65,'Por sistema'!$A$5:$A$9,0)),"Sí","No"),"No")
A66: sgc-2025-1 | B66: SGC | C66: Sistema de Gestión de Calidad | D66: 2025 | E66: 1 | F66: Revisar, ajustar y aprobar las tablas de retención documental de los procesos identificados en el modelo de operación digital aplicando los requisitos de las normas ISO implementadas por la Institución. | G66: Oficina de Archivo y Correspondencia | H66: Archivo y Correspondencia | I66: Actas de Comisión Desempeño Acto administrativo de adopción Tablas de valoración documental. Tablas de Retención documental vigentes | J66: 46142 | K66: 46142 | L66: =COUNTIF(Seguimientos!$A$2:$A$1013,A66) | M66: =SUMPRODUCT(MAX((Seguimientos!$A$2:$A$1013=A66)*(Seguimientos!$H$2:$H$1013<>"")*Seguimientos!$B$2:$B$1013)) | N66: =IF(M66=0,"",INDEX(Seguimientos!$F$2:$F$1013,MATCH(A66&"|"&M66,Seguimientos!$K$2:$K$1013,0))) | O66: =IF(M66=0,0,INDEX(Seguimientos!$H$2:$H$1013,MATCH(A66&"|"&M66,Seguimientos!$K$2:$K$1013,0))) | P66: =O66/2 | Q66: =INDEX(Escala!$B$2:$B$6,MATCH(O66,Escala!$A$2:$A$6,0)) | R66: =IF(O66=2,"Sí","No") | S66: =IF(O66=0,"Sí","No") | T66: =IF(AND(ISNUMBER(K66),O66<2),IF(K66<INDEX('Por sistema'!$D$5:$D$9,MATCH(B66,'Por sistema'!$A$5:$A$9,0)),"Sí","No"),"No")
A67: sgc-2025-2 | B67: SGC | C67: Sistema de Gestión de Calidad | D67: 2025 | E67: 2 | F67: Revisar el instrumento aplicado para medir la satisfacción de Clientes de los Sistemas de Gestión y de la Institución. | G67: Dirección Planeación Institucional | H67: Planeación Institucional | I67: Instrumento encuesta de satisfacción revisado. | J67: 46112 | K67: 46112 | L67: =COUNTIF(Seguimientos!$A$2:$A$1013,A67) | M67: =SUMPRODUCT(MAX((Seguimientos!$A$2:$A$1013=A67)*(Seguimientos!$H$2:$H$1013<>"")*Seguimientos!$B$2:$B$1013)) | N67: =IF(M67=0,"",INDEX(Seguimientos!$F$2:$F$1013,MATCH(A67&"|"&M67,Seguimientos!$K$2:$K$1013,0))) | O67: =IF(M67=0,0,INDEX(Seguimientos!$H$2:$H$1013,MATCH(A67&"|"&M67,Seguimientos!$K$2:$K$1013,0))) | P67: =O67/2 | Q67: =INDEX(Escala!$B$2:$B$6,MATCH(O67,Escala!$A$2:$A$6,0)) | R67: =IF(O67=2,"Sí","No") | S67: =IF(O67=0,"Sí","No") | T67: =IF(AND(ISNUMBER(K67),O67<2),IF(K67<INDEX('Por sistema'!$D$5:$D$9,MATCH(B67,'Por sistema'!$A$5:$A$9,0)),"Sí","No"),"No")
A68: sgc-2025-3 | B68: SGC | C68: Sistema de Gestión de Calidad | D68: 2025 | E68: 3 | F68: Elaboración y aprobación de los Riesgos Fiscales Institucionales iniciales con corte vigencia 2025 | G68: Oficina de Calidad | H68: Calidad | I68: Matriz de Riesgos Fiscales 2025 | J68: 31/06/2026 | L68: =COUNTIF(Seguimientos!$A$2:$A$1013,A68) | M68: =SUMPRODUCT(MAX((Seguimientos!$A$2:$A$1013=A68)*(Seguimientos!$H$2:$H$1013<>"")*Seguimientos!$B$2:$B$1013)) | N68: =IF(M68=0,"",INDEX(Seguimientos!$F$2:$F$1013,MATCH(A68&"|"&M68,Seguimientos!$K$2:$K$1013,0))) | O68: =IF(M68=0,0,INDEX(Seguimientos!$H$2:$H$1013,MATCH(A68&"|"&M68,Seguimientos!$K$2:$K$1013,0))) | P68: =O68/2 | Q68: =INDEX(Escala!$B$2:$B$6,MATCH(O68,Escala!$A$2:$A$6,0)) | R68: =IF(O68=2,"Sí","No") | S68: =IF(O68=0,"Sí","No") | T68: =IF(AND(ISNUMBER(K68),O68<2),IF(K68<INDEX('Por sistema'!$D$5:$D$9,MATCH(B68,'Por sistema'!$A$5:$A$9,0)),"Sí","No"),"No")
A69: sgc-2025-4 | B69: SGC | C69: Sistema de Gestión de Calidad | D69: 2025 | E69: 4 | F69: Implementar el Acuerdo CESU 01 de 2025 en Autoevaluación y Acreditación bajo el modelo institucional. | G69: Dirección de Autoevaluación y Acreditación | H69: Autoevaluación y Acreditación | I69: Actualización del Aplicativo de Aseguramiento de la Alta Calidad. Documentación institucional actualizada en el marco del Acuerdo CESU 01 de 2025. Acta de la comisión de Acreditación con el reporte de los procesos de Autoevaluación y Acreditación. | J69: 46371 | K69: 46371 | L69: =COUNTIF(Seguimientos!$A$2:$A$1013,A69) | M69: =SUMPRODUCT(MAX((Seguimientos!$A$2:$A$1013=A69)*(Seguimientos!$H$2:$H$1013<>"")*Seguimientos!$B$2:$B$1013)) | N69: =IF(M69=0,"",INDEX(Seguimientos!$F$2:$F$1013,MATCH(A69&"|"&M69,Seguimientos!$K$2:$K$1013,0))) | O69: =IF(M69=0,0,INDEX(Seguimientos!$H$2:$H$1013,MATCH(A69&"|"&M69,Seguimientos!$K$2:$K$1013,0))) | P69: =O69/2 | Q69: =INDEX(Escala!$B$2:$B$6,MATCH(O69,Escala!$A$2:$A$6,0)) | R69: =IF(O69=2,"Sí","No") | S69: =IF(O69=0,"Sí","No") | T69: =IF(AND(ISNUMBER(K69),O69<2),IF(K69<INDEX('Por sistema'!$D$5:$D$9,MATCH(B69,'Por sistema'!$A$5:$A$9,0)),"Sí","No"),"No")
A70: sgc-2025-5 | B70: SGC | C70: Sistema de Gestión de Calidad | D70: 2025 | E70: 5 | F70: Reforzar las campañas educativas dirigidos a la comunidad universitaria sobre derechos ciudadanos con el fin de incrementar el uso responsable y consciente de los mecanismos formales como denuncias y peticiones. | G70: Atención al Ciudadano | H70: Atención al Ciudadano | I70: Requerimeinto a la Oficina de Comunicaciones Campaña de socialización conocimiento para denuncias y peticiones Correo masivo con la información de la acampaña comunidad administrativa y academica | J70: 30/06/2026 | K70: 46203 | L70: =COUNTIF(Seguimientos!$A$2:$A$1013,A70) | M70: =SUMPRODUCT(MAX((Seguimientos!$A$2:$A$1013=A70)*(Seguimientos!$H$2:$H$1013<>"")*Seguimientos!$B$2:$B$1013)) | N70: =IF(M70=0,"",INDEX(Seguimientos!$F$2:$F$1013,MATCH(A70&"|"&M70,Seguimientos!$K$2:$K$1013,0))) | O70: =IF(M70=0,0,INDEX(Seguimientos!$H$2:$H$1013,MATCH(A70&"|"&M70,Seguimientos!$K$2:$K$1013,0))) | P70: =O70/2 | Q70: =INDEX(Escala!$B$2:$B$6,MATCH(O70,Escala!$A$2:$A$6,0)) | R70: =IF(O70=2,"Sí","No") | S70: =IF(O70=0,"Sí","No") | T70: =IF(AND(ISNUMBER(K70),O70<2),IF(K70<INDEX('Por sistema'!$D$5:$D$9,MATCH(B70,'Por sistema'!$A$5:$A$9,0)),"Sí","No"),"No")
A71: sgc-2025-6 | B71: SGC | C71: Sistema de Gestión de Calidad | D71: 2025 | E71: 6 | F71: Resignificar la Resolución No. 096 de 2021 con el fin de actualizar los lineamientos (Política) y los objetivos del Sistema de Gestión de la Calidad, alineado a la integración de los sistemas de gestión; asimismo, de acuerdo con el Plan Rectoral y Plan de Desarrollo. | G71: Sistemas Integrados de Gestión DIrección Planeación Institucional | H71: Planeación Institucional | I71: Resolución No. 096 de 2021 Actualizada | J71: 46371 | K71: 46371 | L71: =COUNTIF(Seguimientos!$A$2:$A$1013,A71) | M71: =SUMPRODUCT(MAX((Seguimientos!$A$2:$A$1013=A71)*(Seguimientos!$H$2:$H$1013<>"")*Seguimientos!$B$2:$B$1013)) | N71: =IF(M71=0,"",INDEX(Seguimientos!$F$2:$F$1013,MATCH(A71&"|"&M71,Seguimientos!$K$2:$K$1013,0))) | O71: =IF(M71=0,0,INDEX(Seguimientos!$H$2:$H$1013,MATCH(A71&"|"&M71,Seguimientos!$K$2:$K$1013,0))) | P71: =O71/2 | Q71: =INDEX(Escala!$B$2:$B$6,MATCH(O71,Escala!$A$2:$A$6,0)) | R71: =IF(O71=2,"Sí","No") | S71: =IF(O71=0,"Sí","No") | T71: =IF(AND(ISNUMBER(K71),O71<2),IF(K71<INDEX('Por sistema'!$D$5:$D$9,MATCH(B71,'Por sistema'!$A$5:$A$9,0)),"Sí","No"),"No")
A72: sgc-2025-7 | B72: SGC | C72: Sistema de Gestión de Calidad | D72: 2025 | E72: 7 | F72: Realizar el cierre y resignificar los objetivos establecidos en la Resolución 096 de 2021, con corte a diciembre 2025 y llevar el análisis de los resultados al comité SAC para la toma de decisiones que sea pertinente. | G72: Oficina de Calidad DIrección Planeación Institucional | H72: Planeación Institucional, Calidad | I72: Informe de cumplimiento de objetivos SGC 2025 | J72: 46371 | K72: 46371 | L72: =COUNTIF(Seguimientos!$A$2:$A$1013,A72) | M72: =SUMPRODUCT(MAX((Seguimientos!$A$2:$A$1013=A72)*(Seguimientos!$H$2:$H$1013<>"")*Seguimientos!$B$2:$B$1013)) | N72: =IF(M72=0,"",INDEX(Seguimientos!$F$2:$F$1013,MATCH(A72&"|"&M72,Seguimientos!$K$2:$K$1013,0))) | O72: =IF(M72=0,0,INDEX(Seguimientos!$H$2:$H$1013,MATCH(A72&"|"&M72,Seguimientos!$K$2:$K$1013,0))) | P72: =O72/2 | Q72: =INDEX(Escala!$B$2:$B$6,MATCH(O72,Escala!$A$2:$A$6,0)) | R72: =IF(O72=2,"Sí","No") | S72: =IF(O72=0,"Sí","No") | T72: =IF(AND(ISNUMBER(K72),O72<2),IF(K72<INDEX('Por sistema'!$D$5:$D$9,MATCH(B72,'Por sistema'!$A$5:$A$9,0)),"Sí","No"),"No")
A73: sgc-2025-8 | B73: SGC | C73: Sistema de Gestión de Calidad | D73: 2025 | E73: 8 | F73: Verificar y consolidar la batería de indicadores para identificar cuáles contribuyen efectivamente al cumplimiento de los objetivos de calidad, según su naturaleza, | G73: Oficina de Calidad Procesos identificados en el Modelo de Operación Digital | H73: Calidad | I73: Bateria Indicadores 2026 actualizado | J73: 46112 | K73: 46112 | L73: =COUNTIF(Seguimientos!$A$2:$A$1013,A73) | M73: =SUMPRODUCT(MAX((Seguimientos!$A$2:$A$1013=A73)*(Seguimientos!$H$2:$H$1013<>"")*Seguimientos!$B$2:$B$1013)) | N73: =IF(M73=0,"",INDEX(Seguimientos!$F$2:$F$1013,MATCH(A73&"|"&M73,Seguimientos!$K$2:$K$1013,0))) | O73: =IF(M73=0,0,INDEX(Seguimientos!$H$2:$H$1013,MATCH(A73&"|"&M73,Seguimientos!$K$2:$K$1013,0))) | P73: =O73/2 | Q73: =INDEX(Escala!$B$2:$B$6,MATCH(O73,Escala!$A$2:$A$6,0)) | R73: =IF(O73=2,"Sí","No") | S73: =IF(O73=0,"Sí","No") | T73: =IF(AND(ISNUMBER(K73),O73<2),IF(K73<INDEX('Por sistema'!$D$5:$D$9,MATCH(B73,'Por sistema'!$A$5:$A$9,0)),"Sí","No"),"No")
A74: sgc-2025-9 | B74: SGC | C74: Sistema de Gestión de Calidad | D74: 2025 | E74: 9 | F74: Solicitar la contratación del personal encargado del Repositorio Institucional de cada Unidad Regional en los teiempos oportunos para el cumplimiento de publicación de los documentos en el aplicativo Institucional | G74: Unidad Apoyo Academico | H74: Apoyo y Desarrollo Académico | I74: Lista de personal priorizado para iniciar labores en cada unidad regional Oficio de solicitud de contratación | J74: 46203 | K74: 46203 | L74: =COUNTIF(Seguimientos!$A$2:$A$1013,A74) | M74: =SUMPRODUCT(MAX((Seguimientos!$A$2:$A$1013=A74)*(Seguimientos!$H$2:$H$1013<>"")*Seguimientos!$B$2:$B$1013)) | N74: =IF(M74=0,"",INDEX(Seguimientos!$F$2:$F$1013,MATCH(A74&"|"&M74,Seguimientos!$K$2:$K$1013,0))) | O74: =IF(M74=0,0,INDEX(Seguimientos!$H$2:$H$1013,MATCH(A74&"|"&M74,Seguimientos!$K$2:$K$1013,0))) | P74: =O74/2 | Q74: =INDEX(Escala!$B$2:$B$6,MATCH(O74,Escala!$A$2:$A$6,0)) | R74: =IF(O74=2,"Sí","No") | S74: =IF(O74=0,"Sí","No") | T74: =IF(AND(ISNUMBER(K74),O74<2),IF(K74<INDEX('Por sistema'!$D$5:$D$9,MATCH(B74,'Por sistema'!$A$5:$A$9,0)),"Sí","No"),"No")
A75: sgc-2025-10 | B75: SGC | C75: Sistema de Gestión de Calidad | D75: 2025 | E75: 10 | F75: Verificar la proyección academica con el fin de dar cobertura en los espacios academicos en jurnadas diurnas y nocturnas, donde los directores administrativos junto con el Jefe de Apoyo Academico deberan realizar el estudio de este necesidad. | G75: Unidad Apoyo Academico | H75: Apoyo y Desarrollo Académico | I75: Acta de mesa de trabajo con los cada uno de los Directores Administrativos Aseguramiento de la contratación del personal adicional que se requiera | J75: 30/06/2026 | K75: 46203 | L75: =COUNTIF(Seguimientos!$A$2:$A$1013,A75) | M75: =SUMPRODUCT(MAX((Seguimientos!$A$2:$A$1013=A75)*(Seguimientos!$H$2:$H$1013<>"")*Seguimientos!$B$2:$B$1013)) | N75: =IF(M75=0,"",INDEX(Seguimientos!$F$2:$F$1013,MATCH(A75&"|"&M75,Seguimientos!$K$2:$K$1013,0))) | O75: =IF(M75=0,0,INDEX(Seguimientos!$H$2:$H$1013,MATCH(A75&"|"&M75,Seguimientos!$K$2:$K$1013,0))) | P75: =O75/2 | Q75: =INDEX(Escala!$B$2:$B$6,MATCH(O75,Escala!$A$2:$A$6,0)) | R75: =IF(O75=2,"Sí","No") | S75: =IF(O75=0,"Sí","No") | T75: =IF(AND(ISNUMBER(K75),O75<2),IF(K75<INDEX('Por sistema'!$D$5:$D$9,MATCH(B75,'Por sistema'!$A$5:$A$9,0)),"Sí","No"),"No")
A76: sgc-2025-11 | B76: SGC | C76: Sistema de Gestión de Calidad | D76: 2025 | E76: 11 | F76: Trasladar el indicador de Calibraciones "calibración de equipos y elementos educativos de Investigación" a la Dirección de Investigación para su reporte, control y medición, en razón que para el 2026 los recursos se encuentran asignados a la Dirección de Investigación. | G76: Unidad Apoyo Academico Dirección Investigación Universitaria | H76: Apoyo y Desarrollo Académico, Investigación Universitaria | I76: Acta de Comité Extraordinario SAC. - Traslado Indicador de Calibraciones "calibración de equipos y elementos educativos de Investigación Correo de notificación de traslado por apoyo tecnica del SAC Oficio a la Oficina de Calidad notificando el traslado del Indicador Ficha del indicador ajustado en la Dirección Investigación Universitaria | J76: 30/06/2026 | K76: 46203 | L76: =COUNTIF(Seguimientos!$A$2:$A$1013,A76) | M76: =SUMPRODUCT(MAX((Seguimientos!$A$2:$A$1013=A76)*(Seguimientos!$H$2:$H$1013<>"")*Seguimientos!$B$2:$B$1013)) | N76: =IF(M76=0,"",INDEX(Seguimientos!$F$2:$F$1013,MATCH(A76&"|"&M76,Seguimientos!$K$2:$K$1013,0))) | O76: =IF(M76=0,0,INDEX(Seguimientos!$H$2:$H$1013,MATCH(A76&"|"&M76,Seguimientos!$K$2:$K$1013,0))) | P76: =O76/2 | Q76: =INDEX(Escala!$B$2:$B$6,MATCH(O76,Escala!$A$2:$A$6,0)) | R76: =IF(O76=2,"Sí","No") | S76: =IF(O76=0,"Sí","No") | T76: =IF(AND(ISNUMBER(K76),O76<2),IF(K76<INDEX('Por sistema'!$D$5:$D$9,MATCH(B76,'Por sistema'!$A$5:$A$9,0)),"Sí","No"),"No")
A77: sgc-2025-12 | B77: SGC | C77: Sistema de Gestión de Calidad | D77: 2025 | E77: 12 | F77: Elaborar un tablero de control que permita comparar los datos de cada sistema de Gestión en las diferencias vigencias. | G77: Dirección Sistemas y Tecnología Grupo Gobierno de Datos | H77: Sistemas y Tecnología, Gobierno de Datos | I77: Tablero de Control | J77: 46203 | K77: 46203 | L77: =COUNTIF(Seguimientos!$A$2:$A$1013,A77) | M77: =SUMPRODUCT(MAX((Seguimientos!$A$2:$A$1013=A77)*(Seguimientos!$H$2:$H$1013<>"")*Seguimientos!$B$2:$B$1013)) | N77: =IF(M77=0,"",INDEX(Seguimientos!$F$2:$F$1013,MATCH(A77&"|"&M77,Seguimientos!$K$2:$K$1013,0))) | O77: =IF(M77=0,0,INDEX(Seguimientos!$H$2:$H$1013,MATCH(A77&"|"&M77,Seguimientos!$K$2:$K$1013,0))) | P77: =O77/2 | Q77: =INDEX(Escala!$B$2:$B$6,MATCH(O77,Escala!$A$2:$A$6,0)) | R77: =IF(O77=2,"Sí","No") | S77: =IF(O77=0,"Sí","No") | T77: =IF(AND(ISNUMBER(K77),O77<2),IF(K77<INDEX('Por sistema'!$D$5:$D$9,MATCH(B77,'Por sistema'!$A$5:$A$9,0)),"Sí","No"),"No")
A78: sgc-2025-13 | B78: SGC | C78: Sistema de Gestión de Calidad | D78: 2025 | E78: 13 | F78: Actualizar la Resolución No. 088 "POR LA CUAL SE ESTABLECE EL SISTEMA DE ASEGURAMIENTO DE LA CALIDAD DE LA UNIVERSIDAD DE CUNDINAMARCA¨ | G78: Oficina de Calidad Oficina de SST Oficina de SGSI Oficina Ambiental Sistema de Gestión Antisoborno | H78: Calidad, Gestión Ambiental, Seguridad de la Información, Seguridad y Salud en el Trabajo, Antisoborno | I78: Actualización Resolución No. 088 "POR LA CUAL SE ESTABLECE EL SISTEMA DE ASEGURAMIENTO DE LA CALIDAD DE LA UNIVERSIDAD DE CUNDINAMARCA¨ | J78: 46371 | K78: 46371 | L78: =COUNTIF(Seguimientos!$A$2:$A$1013,A78) | M78: =SUMPRODUCT(MAX((Seguimientos!$A$2:$A$1013=A78)*(Seguimientos!$H$2:$H$1013<>"")*Seguimientos!$B$2:$B$1013)) | N78: =IF(M78=0,"",INDEX(Seguimientos!$F$2:$F$1013,MATCH(A78&"|"&M78,Seguimientos!$K$2:$K$1013,0))) | O78: =IF(M78=0,0,INDEX(Seguimientos!$H$2:$H$1013,MATCH(A78&"|"&M78,Seguimientos!$K$2:$K$1013,0))) | P78: =O78/2 | Q78: =INDEX(Escala!$B$2:$B$6,MATCH(O78,Escala!$A$2:$A$6,0)) | R78: =IF(O78=2,"Sí","No") | S78: =IF(O78=0,"Sí","No") | T78: =IF(AND(ISNUMBER(K78),O78<2),IF(K78<INDEX('Por sistema'!$D$5:$D$9,MATCH(B78,'Por sistema'!$A$5:$A$9,0)),"Sí","No"),"No")
A79: sga-2022-1 | B79: SGA | C79: Sistema de Gestión Ambiental | D79: 2022 | E79: 1 | F79: Priorizar inversiones asociadas con Planes de Mejoramiento de auditorías internas o de certificación SST y SGA para vigencia 2023. | G79: Sistema de Gestión Ambiental - Directora de Planeación Institucional | H79: Planeación Institucional, Gestión Ambiental | I79: Solicitud priorización de recursos para el cumplimiento de Planes de Mejoramiento que requieren inversión. | J79: 15-12-2023 | K79: 45275 | L79: =COUNTIF(Seguimientos!$A$2:$A$1013,A79) | M79: =SUMPRODUCT(MAX((Seguimientos!$A$2:$A$1013=A79)*(Seguimientos!$H$2:$H$1013<>"")*Seguimientos!$B$2:$B$1013)) | N79: =IF(M79=0,"",INDEX(Seguimientos!$F$2:$F$1013,MATCH(A79&"|"&M79,Seguimientos!$K$2:$K$1013,0))) | O79: =IF(M79=0,0,INDEX(Seguimientos!$H$2:$H$1013,MATCH(A79&"|"&M79,Seguimientos!$K$2:$K$1013,0))) | P79: =O79/2 | Q79: =INDEX(Escala!$B$2:$B$6,MATCH(O79,Escala!$A$2:$A$6,0)) | R79: =IF(O79=2,"Sí","No") | S79: =IF(O79=0,"Sí","No") | T79: =IF(AND(ISNUMBER(K79),O79<2),IF(K79<INDEX('Por sistema'!$D$5:$D$9,MATCH(B79,'Por sistema'!$A$5:$A$9,0)),"Sí","No"),"No")
A80: sga-2022-2 | B80: SGA | C80: Sistema de Gestión Ambiental | D80: 2022 | E80: 2 | F80: Respecto a la conformación del equipo del SGA, evaluar la viabilidad de cambiar la modalidad de contratación de las gestoras ambientales de Ubaté y Fusagasugá, de OPS a término fijo, y en lo casos en los que no sea viable para el resto del equipo, asegurar la continuidad del contrato sin interrupción a mitad de año, con el fin de asegurar la continuidad del apoyo y disponibilidad en el cumplimiento de requisitos legales y otros ambientales. Evaluar la aprobación de contratación de un apoyo con un profesional más para la Sede de Fusagasugá, dado el alcance que se debe cubrir en las instalaciones que incluye el CAD y la Unidad Agroambiental La Esperanza, para lo cual ya se cuenta con recursos aprobados en el presupuesto SGA 2023. | G80: Sistema de Gestión Ambiental - Directora de Planeación Institucional | H80: Planeación Institucional, Gestión Ambiental | I80: 2.1 Contratos de OPS de equipo de SGA por 11 meses para vigencia 2022. 2.2 Contrato de un segundo profesional como Gestor ambiental para la Sede de Fusagasugá. 2.3 Soportes de solicitud de evaluación de las Hojas de Vida de las profesionales del equipo. | J80: 15-12-2023 | K80: 45275 | L80: =COUNTIF(Seguimientos!$A$2:$A$1013,A80) | M80: =SUMPRODUCT(MAX((Seguimientos!$A$2:$A$1013=A80)*(Seguimientos!$H$2:$H$1013<>"")*Seguimientos!$B$2:$B$1013)) | N80: =IF(M80=0,"",INDEX(Seguimientos!$F$2:$F$1013,MATCH(A80&"|"&M80,Seguimientos!$K$2:$K$1013,0))) | O80: =IF(M80=0,0,INDEX(Seguimientos!$H$2:$H$1013,MATCH(A80&"|"&M80,Seguimientos!$K$2:$K$1013,0))) | P80: =O80/2 | Q80: =INDEX(Escala!$B$2:$B$6,MATCH(O80,Escala!$A$2:$A$6,0)) | R80: =IF(O80=2,"Sí","No") | S80: =IF(O80=0,"Sí","No") | T80: =IF(AND(ISNUMBER(K80),O80<2),IF(K80<INDEX('Por sistema'!$D$5:$D$9,MATCH(B80,'Por sistema'!$A$5:$A$9,0)),"Sí","No"),"No")
... A85: sga-2022-7 | B85: SGA | C85: Sistema de Gestión Ambiental | D85: 2022 | E85: 7 | F85: Evaluar la viabilidad de realizar las reuniones de Comisión de Gestión con frecuencia bimensual​ para fortalecer los procesos de planeación, implementación y seguimiento de los Sistemas Integrados de Gestión con la oportuna toma de decisiones según la dinámica institucional. | G85: Sistema de Gestión Ambiental - Directora de Planeación Institucional | H85: Planeación Institucional, Gestión Ambiental | I85: 7.1 Acta de Comisión de Gestión con aprobación de la propuesta de realizar las sesiones cada dos meses para fortalecer los procesos de planeación, implementación y seguimiento de los Sistemas Integrados de Gestión . | J85: 15-12-2023 | K85: 45275 | L85: =COUNTIF(Seguimientos!$A$2:$A$1013,A85) | M85: =SUMPRODUCT(MAX((Seguimientos!$A$2:$A$1013=A85)*(Seguimientos!$H$2:$H$1013<>"")*Seguimientos!$B$2:$B$1013)) | N85: =IF(M85=0,"",INDEX(Seguimientos!$F$2:$F$1013,MATCH(A85&"|"&M85,Seguimientos!$K$2:$K$1013,0))) | O85: =IF(M85=0,0,INDEX(Seguimientos!$H$2:$H$1013,MATCH(A85&"|"&M85,Seguimientos!$K$2:$K$1013,0))) | P85: =O85/2 | Q85: =INDEX(Escala!$B$2:$B$6,MATCH(O85,Escala!$A$2:$A$6,0)) | R85: =IF(O85=2,"Sí","No") | S85: =IF(O85=0,"Sí","No") | T85: =IF(AND(ISNUMBER(K85),O85<2),IF(K85<INDEX('Por sistema'!$D$5:$D$9,MATCH(B85,'Por sistema'!$A$5:$A$9,0)),"Sí","No"),"No")
A86: sga-2023-1 | B86: SGA | C86: Sistema de Gestión Ambiental | D86: 2023 | E86: 1 | F86: Priorizar inversiones asociadas con Planes de Mejoramiento de auditorías SGA y SST para vigencia 2024 | G86: Directora de Planeación Institucional. Coordinadora SGA. | H86: Planeación Institucional, Gestión Ambiental | I86: 1.1. Planes de mejoramiento aprobados, implementados, y verificados | J86: 2024 - I | L86: =COUNTIF(Seguimientos!$A$2:$A$1013,A86) | M86: =SUMPRODUCT(MAX((Seguimientos!$A$2:$A$1013=A86)*(Seguimientos!$H$2:$H$1013<>"")*Seguimientos!$B$2:$B$1013)) | N86: =IF(M86=0,"",INDEX(Seguimientos!$F$2:$F$1013,MATCH(A86&"|"&M86,Seguimientos!$K$2:$K$1013,0))) | O86: =IF(M86=0,0,INDEX(Seguimientos!$H$2:$H$1013,MATCH(A86&"|"&M86,Seguimientos!$K$2:$K$1013,0))) | P86: =O86/2 | Q86: =INDEX(Escala!$B$2:$B$6,MATCH(O86,Escala!$A$2:$A$6,0)) | R86: =IF(O86=2,"Sí","No") | S86: =IF(O86=0,"Sí","No") | T86: =IF(AND(ISNUMBER(K86),O86<2),IF(K86<INDEX('Por sistema'!$D$5:$D$9,MATCH(B86,'Por sistema'!$A$5:$A$9,0)),"Sí","No"),"No")
A87: sga-2023-sn3csidz | B87: SGA | C87: Sistema de Gestión Ambiental | D87: 2023 | F87: Realizar auditoría interna a la totalidad de las sedes y de seguimiento a la certificación ISO 14001 SGA en las sedes aún no verificadas: Extensión Chía, Extensión Zipaquirá, Extensión Soacha, Unidad Agroambiental la Esperanza de Fusagasugá, Centro Académico Deportivo CAD y Oficinas Bogotá | G87: Directora de Planeación Institucional. Coordinadora SGA. | H87: Planeación Institucional, Gestión Ambiental | I87: 2.1. Plan de auditoria 2.2. Contrato de auditoría interna combinada. 2.3. Contrato de Auditoría de tercera parte. 2.4 Informes de auditorías SGA. | J87: 2024 - II | L87: =COUNTIF(Seguimientos!$A$2:$A$1013,A87) | M87: =SUMPRODUCT(MAX((Seguimientos!$A$2:$A$1013=A87)*(Seguimientos!$H$2:$H$1013<>"")*Seguimientos!$B$2:$B$1013)) | N87: =IF(M87=0,"",INDEX(Seguimientos!$F$2:$F$1013,MATCH(A87&"|"&M87,Seguimientos!$K$2:$K$1013,0))) | O87: =IF(M87=0,0,INDEX(Seguimientos!$H$2:$H$1013,MATCH(A87&"|"&M87,Seguimientos!$K$2:$K$1013,0))) | P87: =O87/2 | Q87: =INDEX(Escala!$B$2:$B$6,MATCH(O87,Escala!$A$2:$A$6,0)) | R87: =IF(O87=2,"Sí","No") | S87: =IF(O87=0,"Sí","No") | T87: =IF(AND(ISNUMBER(K87),O87<2),IF(K87<INDEX('Por sistema'!$D$5:$D$9,MATCH(B87,'Por sistema'!$A$5:$A$9,0)),"Sí","No"),"No")
A88: sga-2023-3 | B88: SGA | C88: Sistema de Gestión Ambiental | D88: 2023 | E88: 3 | F88: Revisar y evaluar la propuesta de la actualización de la Política de Gestión Ambiental como Lineamiento institucional de Gestión Ambiental, presentado a la Comisión de Gestión en 2023. | G88: Directora de Planeación Institucional. Coordinadora SGA. | H88: Planeación Institucional, Gestión Ambiental | I88: 3.1. Política de Gestión Ambiental aprobada, divulgada y publicada. | J88: 2024 - I | L88: =COUNTIF(Seguimientos!$A$2:$A$1013,A88) | M88: =SUMPRODUCT(MAX((Seguimientos!$A$2:$A$1013=A88)*(Seguimientos!$H$2:$H$1013<>"")*Seguimientos!$B$2:$B$1013)) | N88: =IF(M88=0,"",INDEX(Seguimientos!$F$2:$F$1013,MATCH(A88&"|"&M88,Seguimientos!$K$2:$K$1013,0))) | O88: =IF(M88=0,0,INDEX(Seguimientos!$H$2:$H$1013,MATCH(A88&"|"&M88,Seguimientos!$K$2:$K$1013,0))) | P88: =O88/2 | Q88: =INDEX(Escala!$B$2:$B$6,MATCH(O88,Escala!$A$2:$A$6,0)) | R88: =IF(O88=2,"Sí","No") | S88: =IF(O88=0,"Sí","No") | T88: =IF(AND(ISNUMBER(K88),O88<2),IF(K88<INDEX('Por sistema'!$D$5:$D$9,MATCH(B88,'Por sistema'!$A$5:$A$9,0)),"Sí","No"),"No")
A89: sga-2024-1 | B89: SGA | C89: Sistema de Gestión Ambiental | D89: 2024 | E89: 1 | F89: Desarrollar un marco de acción climática que alinee las metas institucionales con las políticas nacionales e internacionales sobre cambio. | G89: SGA | H89: Gestión Ambiental | I89: Diagnóstico de las políticas nacionales e internacionales actuales sobre cambio climático y sostenibilidad. | J89: 31/06/2025 | L89: =COUNTIF(Seguimientos!$A$2:$A$1013,A89) | M89: =SUMPRODUCT(MAX((Seguimientos!$A$2:$A$1013=A89)*(Seguimientos!$H$2:$H$1013<>"")*Seguimientos!$B$2:$B$1013)) | N89: =IF(M89=0,"",INDEX(Seguimientos!$F$2:$F$1013,MATCH(A89&"|"&M89,Seguimientos!$K$2:$K$1013,0))) | O89: =IF(M89=0,0,INDEX(Seguimientos!$H$2:$H$1013,MATCH(A89&"|"&M89,Seguimientos!$K$2:$K$1013,0))) | P89: =O89/2 | Q89: =INDEX(Escala!$B$2:$B$6,MATCH(O89,Escala!$A$2:$A$6,0)) | R89: =IF(O89=2,"Sí","No") | S89: =IF(O89=0,"Sí","No") | T89: =IF(AND(ISNUMBER(K89),O89<2),IF(K89<INDEX('Por sistema'!$D$5:$D$9,MATCH(B89,'Por sistema'!$A$5:$A$9,0)),"Sí","No"),"No")
A90: sga-2024-2 | B90: SGA | C90: Sistema de Gestión Ambiental | D90: 2024 | E90: 2 | F90: Revisar y actualizar los lineamientos internos para incluir consideraciones de sostenibilidad y resiliencia. | G90: SGA | H90: Gestión Ambiental | I90: Informe Evaluación institucional. Identificar áreas clave para la integración de acciones climáticas. | J90: 46021 | K90: 46021 | L90: =COUNTIF(Seguimientos!$A$2:$A$1013,A90) | M90: =SUMPRODUCT(MAX((Seguimientos!$A$2:$A$1013=A90)*(Seguimientos!$H$2:$H$1013<>"")*Seguimientos!$B$2:$B$1013)) | N90: =IF(M90=0,"",INDEX(Seguimientos!$F$2:$F$1013,MATCH(A90&"|"&M90,Seguimientos!$K$2:$K$1013,0))) | O90: =IF(M90=0,0,INDEX(Seguimientos!$H$2:$H$1013,MATCH(A90&"|"&M90,Seguimientos!$K$2:$K$1013,0))) | P90: =O90/2 | Q90: =INDEX(Escala!$B$2:$B$6,MATCH(O90,Escala!$A$2:$A$6,0)) | R90: =IF(O90=2,"Sí","No") | S90: =IF(O90=0,"Sí","No") | T90: =IF(AND(ISNUMBER(K90),O90<2),IF(K90<INDEX('Por sistema'!$D$5:$D$9,MATCH(B90,'Por sistema'!$A$5:$A$9,0)),"Sí","No"),"No")
A91: sga-2024-3 | B91: SGA | C91: Sistema de Gestión Ambiental | D91: 2024 | E91: 3 | F91: Establecer acuerdos de colaboración con partes interesadas especializados en cambio climático. | G91: SGA | H91: Gestión Ambiental | I91: Actas/ evidencias de reunión. | J91: 46021 | K91: 46021 | L91: =COUNTIF(Seguimientos!$A$2:$A$1013,A91) | M91: =SUMPRODUCT(MAX((Seguimientos!$A$2:$A$1013=A91)*(Seguimientos!$H$2:$H$1013<>"")*Seguimientos!$B$2:$B$1013)) | N91: =IF(M91=0,"",INDEX(Seguimientos!$F$2:$F$1013,MATCH(A91&"|"&M91,Seguimientos!$K$2:$K$1013,0))) | O91: =IF(M91=0,0,INDEX(Seguimientos!$H$2:$H$1013,MATCH(A91&"|"&M91,Seguimientos!$K$2:$K$1013,0))) | P91: =O91/2 | Q91: =INDEX(Escala!$B$2:$B$6,MATCH(O91,Escala!$A$2:$A$6,0)) | R91: =IF(O91=2,"Sí","No") | S91: =IF(O91=0,"Sí","No") | T91: =IF(AND(ISNUMBER(K91),O91<2),IF(K91<INDEX('Por sistema'!$D$5:$D$9,MATCH(B91,'Por sistema'!$A$5:$A$9,0)),"Sí","No"),"No")
A92: sga-2024-3-sn2y0blt | B92: SGA | C92: Sistema de Gestión Ambiental | D92: 2024 | E92: 3 | F92: Establecer acuerdos de colaboración con partes interesadas especializados en cambio climático. | G92: SGA | H92: Gestión Ambiental | I92: Acuerdos interinstitucionales. | J92: 46021 | K92: 46021 | L92: =COUNTIF(Seguimientos!$A$2:$A$1013,A92) | M92: =SUMPRODUCT(MAX((Seguimientos!$A$2:$A$1013=A92)*(Seguimientos!$H$2:$H$1013<>"")*Seguimientos!$B$2:$B$1013)) | N92: =IF(M92=0,"",INDEX(Seguimientos!$F$2:$F$1013,MATCH(A92&"|"&M92,Seguimientos!$K$2:$K$1013,0))) | O92: =IF(M92=0,0,INDEX(Seguimientos!$H$2:$H$1013,MATCH(A92&"|"&M92,Seguimientos!$K$2:$K$1013,0))) | P92: =O92/2 | Q92: =INDEX(Escala!$B$2:$B$6,MATCH(O92,Escala!$A$2:$A$6,0)) | R92: =IF(O92=2,"Sí","No") | S92: =IF(O92=0,"Sí","No") | T92: =IF(AND(ISNUMBER(K92),O92<2),IF(K92<INDEX('Por sistema'!$D$5:$D$9,MATCH(B92,'Por sistema'!$A$5:$A$9,0)),"Sí","No"),"No")
A93: sga-2024-4 | B93: SGA | C93: Sistema de Gestión Ambiental | D93: 2024 | E93: 4 | F93: Establecer indicadores específicos para medir el progreso en la integración climática. | G93: SGA | H93: Gestión Ambiental | I93: Matriz de indicadores. | J93: 30/062025 | K93: 45838 | L93: =COUNTIF(Seguimientos!$A$2:$A$1013,A93) | M93: =SUMPRODUCT(MAX((Seguimientos!$A$2:$A$1013=A93)*(Seguimientos!$H$2:$H$1013<>"")*Seguimientos!$B$2:$B$1013)) | N93: =IF(M93=0,"",INDEX(Seguimientos!$F$2:$F$1013,MATCH(A93&"|"&M93,Seguimientos!$K$2:$K$1013,0))) | O93: =IF(M93=0,0,INDEX(Seguimientos!$H$2:$H$1013,MATCH(A93&"|"&M93,Seguimientos!$K$2:$K$1013,0))) | P93: =O93/2 | Q93: =INDEX(Escala!$B$2:$B$6,MATCH(O93,Escala!$A$2:$A$6,0)) | R93: =IF(O93=2,"Sí","No") | S93: =IF(O93=0,"Sí","No") | T93: =IF(AND(ISNUMBER(K93),O93<2),IF(K93<INDEX('Por sistema'!$D$5:$D$9,MATCH(B93,'Por sistema'!$A$5:$A$9,0)),"Sí","No"),"No")
A94: sga-2024-5 | B94: SGA | C94: Sistema de Gestión Ambiental | D94: 2024 | E94: 5 | F94: Direccionar la medición de huella de carbono y su verificación al SGA. | G94: SGA | H94: Gestión Ambiental | I94: Inventario de emisiones 2024. | J94: 45838 | K94: 45838 | L94: =COUNTIF(Seguimientos!$A$2:$A$1013,A94) | M94: =SUMPRODUCT(MAX((Seguimientos!$A$2:$A$1013=A94)*(Seguimientos!$H$2:$H$1013<>"")*Seguimientos!$B$2:$B$1013)) | N94: =IF(M94=0,"",INDEX(Seguimientos!$F$2:$F$1013,MATCH(A94&"|"&M94,Seguimientos!$K$2:$K$1013,0))) | O94: =IF(M94=0,0,INDEX(Seguimientos!$H$2:$H$1013,MATCH(A94&"|"&M94,Seguimientos!$K$2:$K$1013,0))) | P94: =O94/2 | Q94: =INDEX(Escala!$B$2:$B$6,MATCH(O94,Escala!$A$2:$A$6,0)) | R94: =IF(O94=2,"Sí","No") | S94: =IF(O94=0,"Sí","No") | T94: =IF(AND(ISNUMBER(K94),O94<2),IF(K94<INDEX('Por sistema'!$D$5:$D$9,MATCH(B94,'Por sistema'!$A$5:$A$9,0)),"Sí","No"),"No")
A95: sga-2024-5-sn1ip8sv | B95: SGA | C95: Sistema de Gestión Ambiental | D95: 2024 | E95: 5 | F95: Direccionar la medición de huella de carbono y su verificación al SGA. | G95: SGA Proveedor externo | H95: Gestión Ambiental | I95: Calculo de huella de CO2 2024. | J95: 45838 | K95: 45838 | L95: =COUNTIF(Seguimientos!$A$2:$A$1013,A95) | M95: =SUMPRODUCT(MAX((Seguimientos!$A$2:$A$1013=A95)*(Seguimientos!$H$2:$H$1013<>"")*Seguimientos!$B$2:$B$1013)) | N95: =IF(M95=0,"",INDEX(Seguimientos!$F$2:$F$1013,MATCH(A95&"|"&M95,Seguimientos!$K$2:$K$1013,0))) | O95: =IF(M95=0,0,INDEX(Seguimientos!$H$2:$H$1013,MATCH(A95&"|"&M95,Seguimientos!$K$2:$K$1013,0))) | P95: =O95/2 | Q95: =INDEX(Escala!$B$2:$B$6,MATCH(O95,Escala!$A$2:$A$6,0)) | R95: =IF(O95=2,"Sí","No") | S95: =IF(O95=0,"Sí","No") | T95: =IF(AND(ISNUMBER(K95),O95<2),IF(K95<INDEX('Por sistema'!$D$5:$D$9,MATCH(B95,'Por sistema'!$A$5:$A$9,0)),"Sí","No"),"No")
A96: sga-2024-5-sn164bwd | B96: SGA | C96: Sistema de Gestión Ambiental | D96: 2024 | E96: 5 | F96: Direccionar la medición de huella de carbono y su verificación al SGA. | G96: SGA Proveedor externo | H96: Gestión Ambiental | I96: Resultados de verificación de la huella. | J96: 46021 | K96: 46021 | L96: =COUNTIF(Seguimientos!$A$2:$A$1013,A96) | M96: =SUMPRODUCT(MAX((Seguimientos!$A$2:$A$1013=A96)*(Seguimientos!$H$2:$H$1013<>"")*Seguimientos!$B$2:$B$1013)) | N96: =IF(M96=0,"",INDEX(Seguimientos!$F$2:$F$1013,MATCH(A96&"|"&M96,Seguimientos!$K$2:$K$1013,0))) | O96: =IF(M96=0,0,INDEX(Seguimientos!$H$2:$H$1013,MATCH(A96&"|"&M96,Seguimientos!$K$2:$K$1013,0))) | P96: =O96/2 | Q96: =INDEX(Escala!$B$2:$B$6,MATCH(O96,Escala!$A$2:$A$6,0)) | R96: =IF(O96=2,"Sí","No") | S96: =IF(O96=0,"Sí","No") | T96: =IF(AND(ISNUMBER(K96),O96<2),IF(K96<INDEX('Por sistema'!$D$5:$D$9,MATCH(B96,'Por sistema'!$A$5:$A$9,0)),"Sí","No"),"No")
A97: sga-2024-6 | B97: SGA | C97: Sistema de Gestión Ambiental | D97: 2024 | E97: 6 | F97: Actualizar equipos existentes para mejorar la precisión y confiabilidad de las mediciones. (eficiencia de paneles solares, medición de aguas lluvias, medición de aguas de punto de captación). | G97: SGA | H97: Gestión Ambiental | I97: Evaluación de los equipos actuales y su rendimiento. | J97: 45747 | K97: 45747 | L97: =COUNTIF(Seguimientos!$A$2:$A$1013,A97) | M97: =SUMPRODUCT(MAX((Seguimientos!$A$2:$A$1013=A97)*(Seguimientos!$H$2:$H$1013<>"")*Seguimientos!$B$2:$B$1013)) | N97: =IF(M97=0,"",INDEX(Seguimientos!$F$2:$F$1013,MATCH(A97&"|"&M97,Seguimientos!$K$2:$K$1013,0))) | O97: =IF(M97=0,0,INDEX(Seguimientos!$H$2:$H$1013,MATCH(A97&"|"&M97,Seguimientos!$K$2:$K$1013,0))) | P97: =O97/2 | Q97: =INDEX(Escala!$B$2:$B$6,MATCH(O97,Escala!$A$2:$A$6,0)) | R97: =IF(O97=2,"Sí","No") | S97: =IF(O97=0,"Sí","No") | T97: =IF(AND(ISNUMBER(K97),O97<2),IF(K97<INDEX('Por sistema'!$D$5:$D$9,MATCH(B97,'Por sistema'!$A$5:$A$9,0)),"Sí","No"),"No")
A98: sga-2024-6-snvuu6j0 | B98: SGA | C98: Sistema de Gestión Ambiental | D98: 2024 | E98: 6 | F98: Actualizar equipos existentes para mejorar la precisión y confiabilidad de las mediciones. (eficiencia de paneles solares, medición de aguas lluvias, medición de aguas de punto de captación). | G98: SGA | H98: Gestión Ambiental | I98: Identificación de mejoras tecnológicas y nuevas herramientas de medición. | J98: 45748 | K98: 45748 | L98: =COUNTIF(Seguimientos!$A$2:$A$1013,A98) | M98: =SUMPRODUCT(MAX((Seguimientos!$A$2:$A$1013=A98)*(Seguimientos!$H$2:$H$1013<>"")*Seguimientos!$B$2:$B$1013)) | N98: =IF(M98=0,"",INDEX(Seguimientos!$F$2:$F$1013,MATCH(A98&"|"&M98,Seguimientos!$K$2:$K$1013,0))) | O98: =IF(M98=0,0,INDEX(Seguimientos!$H$2:$H$1013,MATCH(A98&"|"&M98,Seguimientos!$K$2:$K$1013,0))) | P98: =O98/2 | Q98: =INDEX(Escala!$B$2:$B$6,MATCH(O98,Escala!$A$2:$A$6,0)) | R98: =IF(O98=2,"Sí","No") | S98: =IF(O98=0,"Sí","No") | T98: =IF(AND(ISNUMBER(K98),O98<2),IF(K98<INDEX('Por sistema'!$D$5:$D$9,MATCH(B98,'Por sistema'!$A$5:$A$9,0)),"Sí","No"),"No")
A99: sga-2024-7 | B99: SGA | C99: Sistema de Gestión Ambiental | D99: 2024 | E99: 7 | F99: Fortalecimiento con el Proceso de Bienestar Universitario para abarcar la población estudiantil. | G99: SGA Bienestar institucional | H99: Gestión Ambiental, Interacción Social y Bienestar | I99: Informe/matriz Revisión de los programas y actividades de bienestar existentes. | J99: 45747 | K99: 45747 | L99: =COUNTIF(Seguimientos!$A$2:$A$1013,A99) | M99: =SUMPRODUCT(MAX((Seguimientos!$A$2:$A$1013=A99)*(Seguimientos!$H$2:$H$1013<>"")*Seguimientos!$B$2:$B$1013)) | N99: =IF(M99=0,"",INDEX(Seguimientos!$F$2:$F$1013,MATCH(A99&"|"&M99,Seguimientos!$K$2:$K$1013,0))) | O99: =IF(M99=0,0,INDEX(Seguimientos!$H$2:$H$1013,MATCH(A99&"|"&M99,Seguimientos!$K$2:$K$1013,0))) | P99: =O99/2 | Q99: =INDEX(Escala!$B$2:$B$6,MATCH(O99,Escala!$A$2:$A$6,0)) | R99: =IF(O99=2,"Sí","No") | S99: =IF(O99=0,"Sí","No") | T99: =IF(AND(ISNUMBER(K99),O99<2),IF(K99<INDEX('Por sistema'!$D$5:$D$9,MATCH(B99,'Por sistema'!$A$5:$A$9,0)),"Sí","No"),"No")
A100: sga-2024-7-sna17bss | B100: SGA | C100: Sistema de Gestión Ambiental | D100: 2024 | E100: 7 | F100: Fortalecimiento con el Proceso de Bienestar Universitario para abarcar la población estudiantil. | G100: SGA Bienestar institucional | H100: Gestión Ambiental, Interacción Social y Bienestar | I100: Cronograma de articulación con Bienestar. | J100: 45838 | K100: 45838 | L100: =COUNTIF(Seguimientos!$A$2:$A$1013,A100) | M100: =SUMPRODUCT(MAX((Seguimientos!$A$2:$A$1013=A100)*(Seguimientos!$H$2:$H$1013<>"")*Seguimientos!$B$2:$B$1013)) | N100: =IF(M100=0,"",INDEX(Seguimientos!$F$2:$F$1013,MATCH(A100&"|"&M100,Seguimientos!$K$2:$K$1013,0))) | O100: =IF(M100=0,0,INDEX(Seguimientos!$H$2:$H$1013,MATCH(A100&"|"&M100,Seguimientos!$K$2:$K$1013,0))) | P100: =O100/2 | Q100: =INDEX(Escala!$B$2:$B$6,MATCH(O100,Escala!$A$2:$A$6,0)) | R100: =IF(O100=2,"Sí","No") | S100: =IF(O100=0,"Sí","No") | T100: =IF(AND(ISNUMBER(K100),O100<2),IF(K100<INDEX('Por sistema'!$D$5:$D$9,MATCH(B100,'Por sistema'!$A$5:$A$9,0)),"Sí","No"),"No")
A101: sga-2024-7-sn18hcag | B101: SGA | C101: Sistema de Gestión Ambiental | D101: 2024 | E101: 7 | F101: Fortalecimiento con el Proceso de Bienestar Universitario para abarcar la población estudiantil. | G101: SGA Bienestar institucional | H101: Gestión Ambiental, Interacción Social y Bienestar | I101: Listas de asistencia, registro fotográfico. | J101: 45930 | K101: 45930 | L101: =COUNTIF(Seguimientos!$A$2:$A$1013,A101) | M101: =SUMPRODUCT(MAX((Seguimientos!$A$2:$A$1013=A101)*(Seguimientos!$H$2:$H$1013<>"")*Seguimientos!$B$2:$B$1013)) | N101: =IF(M101=0,"",INDEX(Seguimientos!$F$2:$F$1013,MATCH(A101&"|"&M101,Seguimientos!$K$2:$K$1013,0))) | O101: =IF(M101=0,0,INDEX(Seguimientos!$H$2:$H$1013,MATCH(A101&"|"&M101,Seguimientos!$K$2:$K$1013,0))) | P101: =O101/2 | Q101: =INDEX(Escala!$B$2:$B$6,MATCH(O101,Escala!$A$2:$A$6,0)) | R101: =IF(O101=2,"Sí","No") | S101: =IF(O101=0,"Sí","No") | T101: =IF(AND(ISNUMBER(K101),O101<2),IF(K101<INDEX('Por sistema'!$D$5:$D$9,MATCH(B101,'Por sistema'!$A$5:$A$9,0)),"Sí","No"),"No")
... A116: sga-2025-5 | B116: SGA | C116: Sistema de Gestión Ambiental | D116: 2025 | E116: 5 | F116: Fortalecer el recurso humano especializado en gestión ambiental | G116: Equipo SGA. Talento Humano. | H116: Talento Humano, Gestión Ambiental | I116: Programa de formación continua y fortalecimiento de competencias del SGA | J116: 30/11/2026 | K116: 46356 | L116: =COUNTIF(Seguimientos!$A$2:$A$1013,A116) | M116: =SUMPRODUCT(MAX((Seguimientos!$A$2:$A$1013=A116)*(Seguimientos!$H$2:$H$1013<>"")*Seguimientos!$B$2:$B$1013)) | N116: =IF(M116=0,"",INDEX(Seguimientos!$F$2:$F$1013,MATCH(A116&"|"&M116,Seguimientos!$K$2:$K$1013,0))) | O116: =IF(M116=0,0,INDEX(Seguimientos!$H$2:$H$1013,MATCH(A116&"|"&M116,Seguimientos!$K$2:$K$1013,0))) | P116: =O116/2 | Q116: =INDEX(Escala!$B$2:$B$6,MATCH(O116,Escala!$A$2:$A$6,0)) | R116: =IF(O116=2,"Sí","No") | S116: =IF(O116=0,"Sí","No") | T116: =IF(AND(ISNUMBER(K116),O116<2),IF(K116<INDEX('Por sistema'!$D$5:$D$9,MATCH(B116,'Por sistema'!$A$5:$A$9,0)),"Sí","No"),"No")
A117: sgsst-2023-1 | B117: SG-SST | C117: Seguridad y Salud en el Trabajo | D117: 2023 | E117: 1 | F117: Aprobación de la actualización de los Lineamientos del SG-SST (política). | G117: SG-SST/ALTA DIRECCION | H117: Alta Dirección, Seguridad y Salud en el Trabajo | I117: Política firmada | J117: ABRIL | L117: =COUNTIF(Seguimientos!$A$2:$A$1013,A117) | M117: =SUMPRODUCT(MAX((Seguimientos!$A$2:$A$1013=A117)*(Seguimientos!$H$2:$H$1013<>"")*Seguimientos!$B$2:$B$1013)) | N117: =IF(M117=0,"",INDEX(Seguimientos!$F$2:$F$1013,MATCH(A117&"|"&M117,Seguimientos!$K$2:$K$1013,0))) | O117: =IF(M117=0,0,INDEX(Seguimientos!$H$2:$H$1013,MATCH(A117&"|"&M117,Seguimientos!$K$2:$K$1013,0))) | P117: =O117/2 | Q117: =INDEX(Escala!$B$2:$B$6,MATCH(O117,Escala!$A$2:$A$6,0)) | R117: =IF(O117=2,"Sí","No") | S117: =IF(O117=0,"Sí","No") | T117: =IF(AND(ISNUMBER(K117),O117<2),IF(K117<INDEX('Por sistema'!$D$5:$D$9,MATCH(B117,'Por sistema'!$A$5:$A$9,0)),"Sí","No"),"No")
A118: sgsst-2023-2 | B118: SG-SST | C118: Seguridad y Salud en el Trabajo | D118: 2023 | E118: 2 | F118: Priorización de recursos para proyectos de inversión que tengan relación con el SG-SST. | G118: ALTA DIRECCIÓN | H118: Alta Dirección | I118: Viabilidad de proyecto y asignación de recursos | J118: Julio | L118: =COUNTIF(Seguimientos!$A$2:$A$1013,A118) | M118: =SUMPRODUCT(MAX((Seguimientos!$A$2:$A$1013=A118)*(Seguimientos!$H$2:$H$1013<>"")*Seguimientos!$B$2:$B$1013)) | N118: =IF(M118=0,"",INDEX(Seguimientos!$F$2:$F$1013,MATCH(A118&"|"&M118,Seguimientos!$K$2:$K$1013,0))) | O118: =IF(M118=0,0,INDEX(Seguimientos!$H$2:$H$1013,MATCH(A118&"|"&M118,Seguimientos!$K$2:$K$1013,0))) | P118: =O118/2 | Q118: =INDEX(Escala!$B$2:$B$6,MATCH(O118,Escala!$A$2:$A$6,0)) | R118: =IF(O118=2,"Sí","No") | S118: =IF(O118=0,"Sí","No") | T118: =IF(AND(ISNUMBER(K118),O118<2),IF(K118<INDEX('Por sistema'!$D$5:$D$9,MATCH(B118,'Por sistema'!$A$5:$A$9,0)),"Sí","No"),"No")
A119: sgsst-2023-3 | B119: SG-SST | C119: Seguridad y Salud en el Trabajo | D119: 2023 | E119: 3 | F119: Continuidad del personal de Laboratorios- control riesgo químico | G119: SG-SST/APOYO ACADEMICO/VICERRECTORIA ADMINISTRATIVA | H119: Seguridad y Salud en el Trabajo, Vicerrectoría Administrativa y Financiera, Apoyo y Desarrollo Académico | I119: Continuidad de funcionarios de Laboratorios | J119: Julio | L119: =COUNTIF(Seguimientos!$A$2:$A$1013,A119) | M119: =SUMPRODUCT(MAX((Seguimientos!$A$2:$A$1013=A119)*(Seguimientos!$H$2:$H$1013<>"")*Seguimientos!$B$2:$B$1013)) | N119: =IF(M119=0,"",INDEX(Seguimientos!$F$2:$F$1013,MATCH(A119&"|"&M119,Seguimientos!$K$2:$K$1013,0))) | O119: =IF(M119=0,0,INDEX(Seguimientos!$H$2:$H$1013,MATCH(A119&"|"&M119,Seguimientos!$K$2:$K$1013,0))) | P119: =O119/2 | Q119: =INDEX(Escala!$B$2:$B$6,MATCH(O119,Escala!$A$2:$A$6,0)) | R119: =IF(O119=2,"Sí","No") | S119: =IF(O119=0,"Sí","No") | T119: =IF(AND(ISNUMBER(K119),O119<2),IF(K119<INDEX('Por sistema'!$D$5:$D$9,MATCH(B119,'Por sistema'!$A$5:$A$9,0)),"Sí","No"),"No")
...

Sheet Seguimientos
A1: ID OM | B1: N.º | C1: Sistema | D1: Vigencia | E1: PM N° | F1: Fecha de corte | G1: Funcionario | H1: Calificación | I1: Avance | J1: Cuenta en el corte | K1: Clave | L1: Observación
A2: sgc-2022-1 | B2: 1 | C2: SGC | D2: 2022 | E2: 1 | F2: 45133 | G2: DANIEL EDUARDO SOTO BERNAL | H2: 1 | I2: =IF(H2="","",H2/2) | J2: =IF(H2="",0,IF(SUMPRODUCT((Seguimientos!$A$2:$A$1013=A2)*(Seguimientos!$F$2:$F$1013=F2)*(Seguimientos!$B$2:$B$1013>B2)*(Seguimientos!$H$2:$H$1013<>""))=0,1,0)) | K2: =A2&"|"&B2 | L2: A la fecha se han actualizado los siguientes documentos de salidas no conformes: 2 Instructivos (MCTI001-MBUI014) 1 procedimiento (MFAP11) Se evidencia que aun falta SNC en los procesos Misionales
A3: sgc-2022-1 | B3: 2 | C3: SGC | D3: 2022 | E3: 1 | F3: 45245 | G3: DANIEL EDUARDO SOTO BERNAL | H3: 1 | I3: =IF(H3="","",H3/2) | J3: =IF(H3="",0,IF(SUMPRODUCT((Seguimientos!$A$2:$A$1013=A3)*(Seguimientos!$F$2:$F$1013=F3)*(Seguimientos!$B$2:$B$1013>B3)*(Seguimientos!$H$2:$H$1013<>""))=0,1,0)) | K3: =A3&"|"&B3 | L3: Se esta ala espera de actualización de las salidas no conformes en los procesos Misiones razón por la que no se ha podido dar avance a esta actividad propuesta
A4: sgc-2022-1 | B4: 3 | C4: SGC | D4: 2022 | E4: 1 | F4: 45405 | G4: DANIEL EDUARDO SOTO BERNAL | H4: 1 | I4: =IF(H4="","",H4/2) | J4: =IF(H4="",0,IF(SUMPRODUCT((Seguimientos!$A$2:$A$1013=A4)*(Seguimientos!$F$2:$F$1013=F4)*(Seguimientos!$B$2:$B$1013>B4)*(Seguimientos!$H$2:$H$1013<>""))=0,1,0)) | K4: =A4&"|"&B4 | L4: A la fecha se han actualizado los siguientes documentos de salidas no conformes: 3 Instructivos (MCTI001-MBUI014-AAAI017) 1 procedimiento (MFAP11)
A5: sgc-2022-1 | B5: 4 | C5: SGC | D5: 2022 | E5: 1 | F5: 45497 | G5: DANIEL EDUARDO SOTO BERNAL | H5: 1 | I5: =IF(H5="","",H5/2) | J5: =IF(H5="",0,IF(SUMPRODUCT((Seguimientos!$A$2:$A$1013=A5)*(Seguimientos!$F$2:$F$1013=F5)*(Seguimientos!$B$2:$B$1013>B5)*(Seguimientos!$H$2:$H$1013<>""))=0,1,0)) | K5: =A5&"|"&B5 | L5: Por decisión de Comisión de Gestión de 5 de junio de 2024 se estableció inactivar la totalidad de procedimientos de Salidas No Conformes que se encontraban replicados en los procesos que reportan salidas no conformes, generando un único procedimiento desde el Sistema de Gestión de la Calidad, actualmente el Sistema de Gestión se encuentra realizando los ajustes documentales pertinentes.
A6: sgc-2022-1 | B6: 5 | C6: SGC | D6: 2022 | E6: 1 | F6: 45583 | G6: DANIEL EDUARDO SOTO BERNAL | H6: 2 | I6: =IF(H6="","",H6/2) | J6: =IF(H6="",0,IF(SUMPRODUCT((Seguimientos!$A$2:$A$1013=A6)*(Seguimientos!$F$2:$F$1013=F6)*(Seguimientos!$B$2:$B$1013>B6)*(Seguimientos!$H$2:$H$1013<>""))=0,1,0)) | K6: =A6&"|"&B6 | L6: El 23 de Agosto de 2024 se inactivaron la totalidad de procedimientos de Salidas No Conformes y se creó un único procedimiento desde el Sistema de Gestión de la Calidad.
A7: sgc-2022-1 | B7: 6 | C7: SGC | D7: 2022 | E7: 1 | F7: 45777 | G7: DANIEL EDUARDO SOTO BERNAL | H7: 2 | I7: =IF(H7="","",H7/2) | J7: =IF(H7="",0,IF(SUMPRODUCT((Seguimientos!$A$2:$A$1013=A7)*(Seguimientos!$F$2:$F$1013=F7)*(Seguimientos!$B$2:$B$1013>B7)*(Seguimientos!$H$2:$H$1013<>""))=0,1,0)) | K7: =A7&"|"&B7 | L7: ACTIVIDAD COMPLETADA
A8: sgc-2022-1 | B8: 7 | C8: SGC | D8: 2022 | E8: 1 | F8: 45838 | G8: DANIEL EDUARDO SOTO BERNAL | H8: 2 | I8: =IF(H8="","",H8/2) | J8: =IF(H8="",0,IF(SUMPRODUCT((Seguimientos!$A$2:$A$1013=A8)*(Seguimientos!$F$2:$F$1013=F8)*(Seguimientos!$B$2:$B$1013>B8)*(Seguimientos!$H$2:$H$1013<>""))=0,1,0)) | K8: =A8&"|"&B8 | L8: ACTIVIDAD COMPLETADA
A9: sgc-2022-1 | B9: 8 | C9: SGC | D9: 2022 | E9: 1 | F9: 45930 | G9: Sin registrar | H9: 2 | I9: =IF(H9="","",H9/2) | J9: =IF(H9="",0,IF(SUMPRODUCT((Seguimientos!$A$2:$A$1013=A9)*(Seguimientos!$F$2:$F$1013=F9)*(Seguimientos!$B$2:$B$1013>B9)*(Seguimientos!$H$2:$H$1013<>""))=0,1,0)) | K9: =A9&"|"&B9 | L9: ACTIVIDAD COMPLETADA
A10: sgc-2022-2 | B10: 1 | C10: SGC | D10: 2022 | E10: 2 | F10: 45133 | G10: DANIEL EDUARDO SOTO BERNAL | H10: 1 | I10: =IF(H10="","",H10/2) | J10: =IF(H10="",0,IF(SUMPRODUCT((Seguimientos!$A$2:$A$1013=A10)*(Seguimientos!$F$2:$F$1013=F10)*(Seguimientos!$B$2:$B$1013>B10)*(Seguimientos!$H$2:$H$1013<>""))=0,1,0)) | K10: =A10&"|"&B10 | L10: Se tiene el contrato F-OCS- 103, contrato se realizó para el segundo periodo académico de la vigencia en curso 2023.
A11: sgc-2022-2 | B11: 2 | C11: SGC | D11: 2022 | E11: 2 | F11: 45245 | G11: DANIEL EDUARDO SOTO BERNAL | H11: 2 | I11: =IF(H11="","",H11/2) | J11: =IF(H11="",0,IF(SUMPRODUCT((Seguimientos!$A$2:$A$1013=A11)*(Seguimientos!$F$2:$F$1013=F11)*(Seguimientos!$B$2:$B$1013>B11)*(Seguimientos!$H$2:$H$1013<>""))=0,1,0)) | K11: =A11&"|"&B11 | L11: Se tiene el contrato F-OCS- 103, contrato se realizó para el segundo periodo académico de la vigencia en curso 2023. Ejecutado a corte de revisión con la AIAP CONSULTORES SAS.
A12: sgc-2022-2 | B12: 3 | C12: SGC | D12: 2022 | E12: 2 | F12: 45405 | G12: DANIEL EDUARDO SOTO BERNAL | H12: 2 | I12: =IF(H12="","",H12/2) | J12: =IF(H12="",0,IF(SUMPRODUCT((Seguimientos!$A$2:$A$1013=A12)*(Seguimientos!$F$2:$F$1013=F12)*(Seguimientos!$B$2:$B$1013>B12)*(Seguimientos!$H$2:$H$1013<>""))=0,1,0)) | K12: =A12&"|"&B12
A13: sgc-2022-2 | B13: 4 | C13: SGC | D13: 2022 | E13: 2 | F13: 45497 | G13: DANIEL EDUARDO SOTO BERNAL | H13: 2 | I13: =IF(H13="","",H13/2) | J13: =IF(H13="",0,IF(SUMPRODUCT((Seguimientos!$A$2:$A$1013=A13)*(Seguimientos!$F$2:$F$1013=F13)*(Seguimientos!$B$2:$B$1013>B13)*(Seguimientos!$H$2:$H$1013<>""))=0,1,0)) | K13: =A13&"|"&B13
A14: sgc-2022-2 | B14: 5 | C14: SGC | D14: 2022 | E14: 2 | F14: 45583 | G14: DANIEL EDUARDO SOTO BERNAL | H14: 2 | I14: =IF(H14="","",H14/2) | J14: =IF(H14="",0,IF(SUMPRODUCT((Seguimientos!$A$2:$A$1013=A14)*(Seguimientos!$F$2:$F$1013=F14)*(Seguimientos!$B$2:$B$1013>B14)*(Seguimientos!$H$2:$H$1013<>""))=0,1,0)) | K14: =A14&"|"&B14 | L14: ACTIVIDAD COMPLETADA
A15: sgc-2022-2 | B15: 6 | C15: SGC | D15: 2022 | E15: 2 | F15: 45777 | G15: DANIEL EDUARDO SOTO BERNAL | H15: 2 | I15: =IF(H15="","",H15/2) | J15: =IF(H15="",0,IF(SUMPRODUCT((Seguimientos!$A$2:$A$1013=A15)*(Seguimientos!$F$2:$F$1013=F15)*(Seguimientos!$B$2:$B$1013>B15)*(Seguimientos!$H$2:$H$1013<>""))=0,1,0)) | K15: =A15&"|"&B15 | L15: ACTIVIDAD COMPLETADA
A16: sgc-2022-2 | B16: 7 | C16: SGC | D16: 2022 | E16: 2 | F16: 45838 | G16: DANIEL EDUARDO SOTO BERNAL | H16: 2 | I16: =IF(H16="","",H16/2) | J16: =IF(H16="",0,IF(SUMPRODUCT((Seguimientos!$A$2:$A$1013=A16)*(Seguimientos!$F$2:$F$1013=F16)*(Seguimientos!$B$2:$B$1013>B16)*(Seguimientos!$H$2:$H$1013<>""))=0,1,0)) | K16: =A16&"|"&B16 | L16: ACTIVIDAD COMPLETADA
A17: sgc-2022-2 | B17: 8 | C17: SGC | D17: 2022 | E17: 2 | F17: 45930 | G17: Sin registrar | H17: 2 | I17: =IF(H17="","",H17/2) | J17: =IF(H17="",0,IF(SUMPRODUCT((Seguimientos!$A$2:$A$1013=A17)*(Seguimientos!$F$2:$F$1013=F17)*(Seguimientos!$B$2:$B$1013>B17)*(Seguimientos!$H$2:$H$1013<>""))=0,1,0)) | K17: =A17&"|"&B17 | L17: ACTIVIDAD COMPLETADA
A18: sgc-2022-3 | B18: 1 | C18: SGC | D18: 2022 | E18: 3 | F18: 45133 | G18: DANIEL EDUARDO SOTO BERNAL | H18: 0 | I18: =IF(H18="","",H18/2) | J18: =IF(H18="",0,IF(SUMPRODUCT((Seguimientos!$A$2:$A$1013=A18)*(Seguimientos!$F$2:$F$1013=F18)*(Seguimientos!$B$2:$B$1013>B18)*(Seguimientos!$H$2:$H$1013<>""))=0,1,0)) | K18: =A18&"|"&B18 | L18: Se encuentra pendiente la Sistematización de los formatos: ABSF049 - Reevaluación de Proveedores de Bienes. ABSF084 - Reevaluación de Proveedores de Servicios. Se ha hecho la entrega de las respectivas propuestas desde el Sistema de Gestión de Calidad el pasado
A19: sgc-2022-3 | B19: 2 | C19: SGC | D19: 2022 | E19: 3 | F19: 45245 | G19: DANIEL EDUARDO SOTO BERNAL | H19: 1 | I19: =IF(H19="","",H19/2) | J19: =IF(H19="",0,IF(SUMPRODUCT((Seguimientos!$A$2:$A$1013=A19)*(Seguimientos!$F$2:$F$1013=F19)*(Seguimientos!$B$2:$B$1013>B19)*(Seguimientos!$H$2:$H$1013<>""))=0,1,0)) | K19: =A19&"|"&B19 | L19: El proceso indica en toda la trazabilidad la gestión de los formatos antes mencionados estando en borrador para actualización y posterior publicación de sus versiones actualizadas 10/03/2023. En Reingeniería se trabajará con la Oficina de Compras para avanzar con la sistematización de los formatos en Integradoc.
A20: sgc-2022-3 | B20: 3 | C20: SGC | D20: 2022 | E20: 3 | F20: 45405 | G20: DANIEL EDUARDO SOTO BERNAL | H20: 1 | I20: =IF(H20="","",H20/2) | J20: =IF(H20="",0,IF(SUMPRODUCT((Seguimientos!$A$2:$A$1013=A20)*(Seguimientos!$F$2:$F$1013=F20)*(Seguimientos!$B$2:$B$1013>B20)*(Seguimientos!$H$2:$H$1013<>""))=0,1,0)) | K20: =A20&"|"&B20 | L20: Por la magnitud de los formatos ABSF049 - ABSF084 en su momento el proceso decide que los documentos sean cargados a Integradoc como soporte pero no digitalizados, sin embargo el Sistema de Gestión de Calidad se encuentra a la espera de la revisión de los formatos por parte del proceso.
A21: sgc-2022-3 | B21: 4 | C21: SGC | D21: 2022 | E21: 3 | F21: 45497 | G21: DANIEL EDUARDO SOTO BERNAL | H21: 1.5 | I21: =IF(H21="","",H21/2) | J21: =IF(H21="",0,IF(SUMPRODUCT((Seguimientos!$A$2:$A$1013=A21)*(Seguimientos!$F$2:$F$1013=F21)*(Seguimientos!$B$2:$B$1013>B21)*(Seguimientos!$H$2:$H$1013<>""))=0,1,0)) | K21: =A21&"|"&B21 | L21: REEVALUACIÓN DE PROVEEDORES DE BIENES (ABSF049) - Se inactivo el documento en abril de 2024 y se unifico con el formato ABSF145, unificando los criterios y facilitando la identificación del formato y el diligenciamiento del mismo. El formato es cargado a Integradoc como soporte pero no digitalizado.
A22: sgc-2022-3 | B22: 5 | C22: SGC | D22: 2022 | E22: 3 | F22: 45583 | G22: DANIEL EDUARDO SOTO BERNAL | H22: 2 | I22: =IF(H22="","",H22/2) | J22: =IF(H22="",0,IF(SUMPRODUCT((Seguimientos!$A$2:$A$1013=A22)*(Seguimientos!$F$2:$F$1013=F22)*(Seguimientos!$B$2:$B$1013>B22)*(Seguimientos!$H$2:$H$1013<>""))=0,1,0)) | K22: =A22&"|"&B22 | L22: En reingenieria se incluye notificacion al proveedor para v.b de la reevaluacion 1.supervisor carga la reevaluación del proveedor 2.compras valida que se encuentre correcta 3.Notificación al Proveedor 4. cinco días hábiles espera respuesta por el Proveedor respecto a su calificación 5. Si observaciones, se remiten al supervisor del contrato para verificación y efectuar ajustes, devolución a la tarea de cargar la Reevaluación versión 2.
A23: sgc-2022-3 | B23: 6 | C23: SGC | D23: 2022 | E23: 3 | F23: 45777 | G23: DANIEL EDUARDO SOTO BERNAL | H23: 2 | I23: =IF(H23="","",H23/2) | J23: =IF(H23="",0,IF(SUMPRODUCT((Seguimientos!$A$2:$A$1013=A23)*(Seguimientos!$F$2:$F$1013=F23)*(Seguimientos!$B$2:$B$1013>B23)*(Seguimientos!$H$2:$H$1013<>""))=0,1,0)) | K23: =A23&"|"&B23 | L23: ACTIVIDAD COMPLETADA
A24: sgc-2022-3 | B24: 7 | C24: SGC | D24: 2022 | E24: 3 | F24: 45838 | G24: DANIEL EDUARDO SOTO BERNAL | H24: 2 | I24: =IF(H24="","",H24/2) | J24: =IF(H24="",0,IF(SUMPRODUCT((Seguimientos!$A$2:$A$1013=A24)*(Seguimientos!$F$2:$F$1013=F24)*(Seguimientos!$B$2:$B$1013>B24)*(Seguimientos!$H$2:$H$1013<>""))=0,1,0)) | K24: =A24&"|"&B24 | L24: ACTIVIDAD COMPLETADA
A25: sgc-2022-3 | B25: 8 | C25: SGC | D25: 2022 | E25: 3 | F25: 45930 | G25: Sin registrar | H25: 2 | I25: =IF(H25="","",H25/2) | J25: =IF(H25="",0,IF(SUMPRODUCT((Seguimientos!$A$2:$A$1013=A25)*(Seguimientos!$F$2:$F$1013=F25)*(Seguimientos!$B$2:$B$1013>B25)*(Seguimientos!$H$2:$H$1013<>""))=0,1,0)) | K25: =A25&"|"&B25 | L25: ACTIVIDAD COMPLETADA
... A43: sgc-2022-5 | B43: 2 | C43: SGC | D43: 2022 | E43: 5 | F43: 45245 | G43: DANIEL EDUARDO SOTO BERNAL | H43: 2 | I43: =IF(H43="","",H43/2) | J43: =IF(H43="",0,IF(SUMPRODUCT((Seguimientos!$A$2:$A$1013=A43)*(Seguimientos!$F$2:$F$1013=F43)*(Seguimientos!$B$2:$B$1013>B43)*(Seguimientos!$H$2:$H$1013<>""))=0,1,0)) | K43: =A43&"|"&B43 | L43: En su versión 21 se cambio la metodología aumentando la rigurosidad de calificación del riesgo. Se incluye nota en el numeral 5 de requisitos y condiciones generales; adicional, se incorpora un control en la actividad 5. VIGENCIA: 2023-07-06 GESTIÓN DEL RIESGO Y LAS OPORTUNIDADES
A44: sgc-2022-5 | B44: 3 | C44: SGC | D44: 2022 | E44: 5 | F44: 45405 | G44: DANIEL EDUARDO SOTO BERNAL | H44: 2 | I44: =IF(H44="","",H44/2) | J44: =IF(H44="",0,IF(SUMPRODUCT((Seguimientos!$A$2:$A$1013=A44)*(Seguimientos!$F$2:$F$1013=F44)*(Seguimientos!$B$2:$B$1013>B44)*(Seguimientos!$H$2:$H$1013<>""))=0,1,0)) | K44: =A44&"|"&B44
A45: sgc-2022-5 | B45: 4 | C45: SGC | D45: 2022 | E45: 5 | F45: 45497 | G45: DANIEL EDUARDO SOTO BERNAL | H45: 2 | I45: =IF(H45="","",H45/2) | J45: =IF(H45="",0,IF(SUMPRODUCT((Seguimientos!$A$2:$A$1013=A45)*(Seguimientos!$F$2:$F$1013=F45)*(Seguimientos!$B$2:$B$1013>B45)*(Seguimientos!$H$2:$H$1013<>""))=0,1,0)) | K45: =A45&"|"&B45
A46: sgc-2022-5 | B46: 5 | C46: SGC | D46: 2022 | E46: 5 | F46: 45583 | G46: DANIEL EDUARDO SOTO BERNAL | H46: 2 | I46: =IF(H46="","",H46/2) | J46: =IF(H46="",0,IF(SUMPRODUCT((Seguimientos!$A$2:$A$1013=A46)*(Seguimientos!$F$2:$F$1013=F46)*(Seguimientos!$B$2:$B$1013>B46)*(Seguimientos!$H$2:$H$1013<>""))=0,1,0)) | K46: =A46&"|"&B46 | L46: ACTIVIDAD COMPLETADA
A47: sgc-2022-5 | B47: 6 | C47: SGC | D47: 2022 | E47: 5 | F47: 45777 | G47: DANIEL EDUARDO SOTO BERNAL | H47: 2 | I47: =IF(H47="","",H47/2) | J47: =IF(H47="",0,IF(SUMPRODUCT((Seguimientos!$A$2:$A$1013=A47)*(Seguimientos!$F$2:$F$1013=F47)*(Seguimientos!$B$2:$B$1013>B47)*(Seguimientos!$H$2:$H$1013<>""))=0,1,0)) | K47: =A47&"|"&B47 | L47: ACTIVIDAD COMPLETADA
A48: sgc-2022-5 | B48: 7 | C48: SGC | D48: 2022 | E48: 5 | F48: 45838 | G48: DANIEL EDUARDO SOTO BERNAL | H48: 2 | I48: =IF(H48="","",H48/2) | J48: =IF(H48="",0,IF(SUMPRODUCT((Seguimientos!$A$2:$A$1013=A48)*(Seguimientos!$F$2:$F$1013=F48)*(Seguimientos!$B$2:$B$1013>B48)*(Seguimientos!$H$2:$H$1013<>""))=0,1,0)) | K48: =A48&"|"&B48 | L48: ACTIVIDAD COMPLETADA
A49: sgc-2022-5 | B49: 8 | C49: SGC | D49: 2022 | E49: 5 | F49: 45930 | G49: Sin registrar | H49: 2 | I49: =IF(H49="","",H49/2) | J49: =IF(H49="",0,IF(SUMPRODUCT((Seguimientos!$A$2:$A$1013=A49)*(Seguimientos!$F$2:$F$1013=F49)*(Seguimientos!$B$2:$B$1013>B49)*(Seguimientos!$H$2:$H$1013<>""))=0,1,0)) | K49: =A49&"|"&B49 | L49: ACTIVIDAD COMPLETADA
A50: sgc-2022-6 | B50: 1 | C50: SGC | D50: 2022 | E50: 6 | F50: 45133 | G50: DANIEL EDUARDO SOTO BERNAL | H50: 1 | I50: =IF(H50="","",H50/2) | J50: =IF(H50="",0,IF(SUMPRODUCT((Seguimientos!$A$2:$A$1013=A50)*(Seguimientos!$F$2:$F$1013=F50)*(Seguimientos!$B$2:$B$1013>B50)*(Seguimientos!$H$2:$H$1013<>""))=0,1,0)) | K50: =A50&"|"&B50 | L50: La Dirección de Control Interno remitió la relación de los temas críticos identificados como hallazgos recurrentes, desde el Sistema de Gestión de la Calidad se realizo la distribución de los temas a tratar al respecto; actualmente la oficina se encuentra en proceso de actualización de los criterios para dar respuesta a su solicitud.
A51: sgc-2022-6 | B51: 2 | C51: SGC | D51: 2022 | E51: 6 | F51: 45245 | G51: DANIEL EDUARDO SOTO BERNAL | H51: 2 | I51: =IF(H51="","",H51/2) | J51: =IF(H51="",0,IF(SUMPRODUCT((Seguimientos!$A$2:$A$1013=A51)*(Seguimientos!$F$2:$F$1013=F51)*(Seguimientos!$B$2:$B$1013>B51)*(Seguimientos!$H$2:$H$1013<>""))=0,1,0)) | K51: =A51&"|"&B51 | L51: La oficina de Sistema de Gestión de Calidad SGC mediante su gestora Alejandra Panqueva recopila y analiza la información suministrada por la Dirección de Control Interno determinado los controles a las acciones reiterativas en los procesos, si ya se actualizaron, si se deben actualizar y que controles se den aplicar para mitigar estos impactos reiterativos. Se adjunta archivo de Excel.
A52: sgc-2022-6 | B52: 3 | C52: SGC | D52: 2022 | E52: 6 | F52: 45405 | G52: DANIEL EDUARDO SOTO BERNAL | H52: 2 | I52: =IF(H52="","",H52/2) | J52: =IF(H52="",0,IF(SUMPRODUCT((Seguimientos!$A$2:$A$1013=A52)*(Seguimientos!$F$2:$F$1013=F52)*(Seguimientos!$B$2:$B$1013>B52)*(Seguimientos!$H$2:$H$1013<>""))=0,1,0)) | K52: =A52&"|"&B52
A53: sgc-2022-6 | B53: 4 | C53: SGC | D53: 2022 | E53: 6 | F53: 45497 | G53: DANIEL EDUARDO SOTO BERNAL | H53: 2 | I53: =IF(H53="","",H53/2) | J53: =IF(H53="",0,IF(SUMPRODUCT((Seguimientos!$A$2:$A$1013=A53)*(Seguimientos!$F$2:$F$1013=F53)*(Seguimientos!$B$2:$B$1013>B53)*(Seguimientos!$H$2:$H$1013<>""))=0,1,0)) | K53: =A53&"|"&B53
A54: sgc-2022-6 | B54: 5 | C54: SGC | D54: 2022 | E54: 6 | F54: 45583 | G54: DANIEL EDUARDO SOTO BERNAL | H54: 2 | I54: =IF(H54="","",H54/2) | J54: =IF(H54="",0,IF(SUMPRODUCT((Seguimientos!$A$2:$A$1013=A54)*(Seguimientos!$F$2:$F$1013=F54)*(Seguimientos!$B$2:$B$1013>B54)*(Seguimientos!$H$2:$H$1013<>""))=0,1,0)) | K54: =A54&"|"&B54 | L54: ACTIVIDAD COMPLETADA
A55: sgc-2022-6 | B55: 6 | C55: SGC | D55: 2022 | E55: 6 | F55: 45777 | G55: DANIEL EDUARDO SOTO BERNAL | H55: 2 | I55: =IF(H55="","",H55/2) | J55: =IF(H55="",0,IF(SUMPRODUCT((Seguimientos!$A$2:$A$1013=A55)*(Seguimientos!$F$2:$F$1013=F55)*(Seguimientos!$B$2:$B$1013>B55)*(Seguimientos!$H$2:$H$1013<>""))=0,1,0)) | K55: =A55&"|"&B55 | L55: ACTIVIDAD COMPLETADA
A56: sgc-2022-6 | B56: 7 | C56: SGC | D56: 2022 | E56: 6 | F56: 45838 | G56: DANIEL EDUARDO SOTO BERNAL | H56: 2 | I56: =IF(H56="","",H56/2) | J56: =IF(H56="",0,IF(SUMPRODUCT((Seguimientos!$A$2:$A$1013=A56)*(Seguimientos!$F$2:$F$1013=F56)*(Seguimientos!$B$2:$B$1013>B56)*(Seguimientos!$H$2:$H$1013<>""))=0,1,0)) | K56: =A56&"|"&B56 | L56: ACTIVIDAD COMPLETADA
A57: sgc-2022-6 | B57: 8 | C57: SGC | D57: 2022 | E57: 6 | F57: 45930 | G57: Sin registrar | H57: 2 | I57: =IF(H57="","",H57/2) | J57: =IF(H57="",0,IF(SUMPRODUCT((Seguimientos!$A$2:$A$1013=A57)*(Seguimientos!$F$2:$F$1013=F57)*(Seguimientos!$B$2:$B$1013>B57)*(Seguimientos!$H$2:$H$1013<>""))=0,1,0)) | K57: =A57&"|"&B57 | L57: ACTIVIDAD COMPLETADA
A58: sgc-2022-7 | B58: 1 | C58: SGC | D58: 2022 | E58: 7 | F58: 45133 | G58: DANIEL EDUARDO SOTO BERNAL | H58: 0 | I58: =IF(H58="","",H58/2) | J58: =IF(H58="",0,IF(SUMPRODUCT((Seguimientos!$A$2:$A$1013=A58)*(Seguimientos!$F$2:$F$1013=F58)*(Seguimientos!$B$2:$B$1013>B58)*(Seguimientos!$H$2:$H$1013<>""))=0,1,0)) | K58: =A58&"|"&B58 | L58: La Dirección de Control Interno remitió la relación de los temas críticos identificados como hallazgos recurrentes, desde el Sistema de Gestión de la Calidad se realizo la distribución de los temas a tratar al respecto; actualmente la oficina se encuentra en proceso de actualización de los criterios para dar respuesta a su solicitud.
A59: sgc-2022-7 | B59: 2 | C59: SGC | D59: 2022 | E59: 7 | F59: 45245 | G59: DANIEL EDUARDO SOTO BERNAL | H59: 1 | I59: =IF(H59="","",H59/2) | J59: =IF(H59="",0,IF(SUMPRODUCT((Seguimientos!$A$2:$A$1013=A59)*(Seguimientos!$F$2:$F$1013=F59)*(Seguimientos!$B$2:$B$1013>B59)*(Seguimientos!$H$2:$H$1013<>""))=0,1,0)) | K59: =A59&"|"&B59 | L59: Conforme a la actividad anterior N° 6, se ajustaran los controles en los procedimientos donde se encuentran sitiados estos hallazgos de No Conformidades de forma recurrente, trabajados desde el archivo producido por la Dirección de Control Interno y analizados por el Sistema de Gestión de la Calidad SGC.
A60: sgc-2022-7 | B60: 3 | C60: SGC | D60: 2022 | E60: 7 | F60: 45405 | G60: DANIEL EDUARDO SOTO BERNAL | H60: 2 | I60: =IF(H60="","",H60/2) | J60: =IF(H60="",0,IF(SUMPRODUCT((Seguimientos!$A$2:$A$1013=A60)*(Seguimientos!$F$2:$F$1013=F60)*(Seguimientos!$B$2:$B$1013>B60)*(Seguimientos!$H$2:$H$1013<>""))=0,1,0)) | K60: =A60&"|"&B60 | L60: Se adjunta evidencia "CRONOGRAMA RUTA CRITICA DE ACTUALIZACIÓN DOCUMENTAL" para los procesos: Formación y Aprendizaje Admisiones y Registro Dirección Financiera
A61: sgc-2022-7 | B61: 4 | C61: SGC | D61: 2022 | E61: 7 | F61: 45497 | G61: DANIEL EDUARDO SOTO BERNAL | H61: 2 | I61: =IF(H61="","",H61/2) | J61: =IF(H61="",0,IF(SUMPRODUCT((Seguimientos!$A$2:$A$1013=A61)*(Seguimientos!$F$2:$F$1013=F61)*(Seguimientos!$B$2:$B$1013>B61)*(Seguimientos!$H$2:$H$1013<>""))=0,1,0)) | K61: =A61&"|"&B61
A62: sgc-2022-7 | B62: 5 | C62: SGC | D62: 2022 | E62: 7 | F62: 45583 | G62: DANIEL EDUARDO SOTO BERNAL | H62: 2 | I62: =IF(H62="","",H62/2) | J62: =IF(H62="",0,IF(SUMPRODUCT((Seguimientos!$A$2:$A$1013=A62)*(Seguimientos!$F$2:$F$1013=F62)*(Seguimientos!$B$2:$B$1013>B62)*(Seguimientos!$H$2:$H$1013<>""))=0,1,0)) | K62: =A62&"|"&B62 | L62: ACTIVIDAD COMPLETADA
A63: sgc-2022-7 | B63: 6 | C63: SGC | D63: 2022 | E63: 7 | F63: 45777 | G63: DANIEL EDUARDO SOTO BERNAL | H63: 2 | I63: =IF(H63="","",H63/2) | J63: =IF(H63="",0,IF(SUMPRODUCT((Seguimientos!$A$2:$A$1013=A63)*(Seguimientos!$F$2:$F$1013=F63)*(Seguimientos!$B$2:$B$1013>B63)*(Seguimientos!$H$2:$H$1013<>""))=0,1,0)) | K63: =A63&"|"&B63 | L63: ACTIVIDAD COMPLETADA
A64: sgc-2022-7 | B64: 7 | C64: SGC | D64: 2022 | E64: 7 | F64: 45838 | G64: DANIEL EDUARDO SOTO BERNAL | H64: 2 | I64: =IF(H64="","",H64/2) | J64: =IF(H64="",0,IF(SUMPRODUCT((Seguimientos!$A$2:$A$1013=A64)*(Seguimientos!$F$2:$F$1013=F64)*(Seguimientos!$B$2:$B$1013>B64)*(Seguimientos!$H$2:$H$1013<>""))=0,1,0)) | K64: =A64&"|"&B64 | L64: ACTIVIDAD COMPLETADA
A65: sgc-2022-7 | B65: 8 | C65: SGC | D65: 2022 | E65: 7 | F65: 45930 | G65: Sin registrar | H65: 2 | I65: =IF(H65="","",H65/2) | J65: =IF(H65="",0,IF(SUMPRODUCT((Seguimientos!$A$2:$A$1013=A65)*(Seguimientos!$F$2:$F$1013=F65)*(Seguimientos!$B$2:$B$1013>B65)*(Seguimientos!$H$2:$H$1013<>""))=0,1,0)) | K65: =A65&"|"&B65 | L65: ACTIVIDAD COMPLETADA
A66: sgc-2023-1 | B66: 1 | C66: SGC | D66: 2023 | E66: 1 | F66: 45405 | G66: DANIEL EDUARDO SOTO BERNAL | H66: 2 | I66: =IF(H66="","",H66/2) | J66: =IF(H66="",0,IF(SUMPRODUCT((Seguimientos!$A$2:$A$1013=A66)*(Seguimientos!$F$2:$F$1013=F66)*(Seguimientos!$B$2:$B$1013>B66)*(Seguimientos!$H$2:$H$1013<>""))=0,1,0)) | K66: =A66&"|"&B66 | L66: Se realiza seguimiento a las tareas pendientes de Oportunidad de Mejora de Revisión por la Dirección dentro de la actividad Tablero de Control. Actividad finalizada.
A67: sgc-2023-1 | B67: 2 | C67: SGC | D67: 2023 | E67: 1 | F67: 45497 | G67: DANIEL EDUARDO SOTO BERNAL | H67: 2 | I67: =IF(H67="","",H67/2) | J67: =IF(H67="",0,IF(SUMPRODUCT((Seguimientos!$A$2:$A$1013=A67)*(Seguimientos!$F$2:$F$1013=F67)*(Seguimientos!$B$2:$B$1013>B67)*(Seguimientos!$H$2:$H$1013<>""))=0,1,0)) | K67: =A67&"|"&B67 | L67: ACTIVIDAD COMPLETADA
A68: sgc-2023-1 | B68: 3 | C68: SGC | D68: 2023 | E68: 1 | F68: 45583 | G68: DANIEL EDUARDO SOTO BERNAL | H68: 2 | I68: =IF(H68="","",H68/2) | J68: =IF(H68="",0,IF(SUMPRODUCT((Seguimientos!$A$2:$A$1013=A68)*(Seguimientos!$F$2:$F$1013=F68)*(Seguimientos!$B$2:$B$1013>B68)*(Seguimientos!$H$2:$H$1013<>""))=0,1,0)) | K68: =A68&"|"&B68 | L68: ACTIVIDAD COMPLETADA
A69: sgc-2023-1 | B69: 4 | C69: SGC | D69: 2023 | E69: 1 | F69: 45777 | G69: DANIEL EDUARDO SOTO BERNAL | H69: 2 | I69: =IF(H69="","",H69/2) | J69: =IF(H69="",0,IF(SUMPRODUCT((Seguimientos!$A$2:$A$1013=A69)*(Seguimientos!$F$2:$F$1013=F69)*(Seguimientos!$B$2:$B$1013>B69)*(Seguimientos!$H$2:$H$1013<>""))=0,1,0)) | K69: =A69&"|"&B69 | L69: ACTIVIDAD COMPLETADA
A70: sgc-2023-1 | B70: 5 | C70: SGC | D70: 2023 | E70: 1 | F70: 45838 | G70: DANIEL EDUARDO SOTO BERNAL | H70: 2 | I70: =IF(H70="","",H70/2) | J70: =IF(H70="",0,IF(SUMPRODUCT((Seguimientos!$A$2:$A$1013=A70)*(Seguimientos!$F$2:$F$1013=F70)*(Seguimientos!$B$2:$B$1013>B70)*(Seguimientos!$H$2:$H$1013<>""))=0,1,0)) | K70: =A70&"|"&B70 | L70: ACTIVIDAD COMPLETADA
A71: sgc-2023-1 | B71: 6 | C71: SGC | D71: 2023 | E71: 1 | F71: 45930 | G71: JOAN IMAYINNE GALVIS MORENO | H71: 2 | I71: =IF(H71="","",H71/2) | J71: =IF(H71="",0,IF(SUMPRODUCT((Seguimientos!$A$2:$A$1013=A71)*(Seguimientos!$F$2:$F$1013=F71)*(Seguimientos!$B$2:$B$1013>B71)*(Seguimientos!$H$2:$H$1013<>""))=0,1,0)) | K71: =A71&"|"&B71 | L71: ACTIVIDAD COMPLETADA
A72: sgc-2023-1 | B72: 7 | C72: SGC | D72: 2023 | E72: 1 | F72: 46021 | G72: JOAN IMAYINNE GALVIS MORENO | H72: 2 | I72: =IF(H72="","",H72/2) | J72: =IF(H72="",0,IF(SUMPRODUCT((Seguimientos!$A$2:$A$1013=A72)*(Seguimientos!$F$2:$F$1013=F72)*(Seguimientos!$B$2:$B$1013>B72)*(Seguimientos!$H$2:$H$1013<>""))=0,1,0)) | K72: =A72&"|"&B72 | L72: ACTIVIDAD COMPLETADA
A73: sgc-2023-1 | B73: 8 | C73: SGC | D73: 2023 | E73: 1 | F73: 46142 | G73: JOAN IMAYINNE GALVIS MORENO | H73: 2 | I73: =IF(H73="","",H73/2) | J73: =IF(H73="",0,IF(SUMPRODUCT((Seguimientos!$A$2:$A$1013=A73)*(Seguimientos!$F$2:$F$1013=F73)*(Seguimientos!$B$2:$B$1013>B73)*(Seguimientos!$H$2:$H$1013<>""))=0,1,0)) | K73: =A73&"|"&B73 | L73: ACTIVIDAD COMPLETADA
... A145: sgc-2023-9 | B145: 8 | C145: SGC | D145: 2023 | E145: 9 | F145: 46142 | G145: JOAN IMAYINNE GALVIS MORENO | H145: 1.5 | I145: =IF(H145="","",H145/2) | J145: =IF(H145="",0,IF(SUMPRODUCT((Seguimientos!$A$2:$A$1013=A145)*(Seguimientos!$F$2:$F$1013=F145)*(Seguimientos!$B$2:$B$1013>B145)*(Seguimientos!$H$2:$H$1013<>""))=0,1,0)) | K145: =A145&"|"&B145 | L145: De acuerdo con la información suministrada por la Jefatura de Recursos Físicos, se identifica que se ha adelantado la elaboración del proyecto de resolución, en el cual ya se contemplan los vistos buenos por parte del área jurídica del acto administrativo. Sin embargo, falta la realización de una mesa de trabajo con la alta dirección, la cual es necesaria para culminar el trámite de aprobación y publicación.
A146: sgc-2023-9 | B146: 9 | C146: SGC | D146: 2023 | E146: 9 | F146: 46203 | G146: JOAN IMAYINNE GALVIS MORENO | H146: 1.5 | I146: =IF(H146="","",H146/2) | J146: =IF(H146="",0,IF(SUMPRODUCT((Seguimientos!$A$2:$A$1013=A146)*(Seguimientos!$F$2:$F$1013=F146)*(Seguimientos!$B$2:$B$1013>B146)*(Seguimientos!$H$2:$H$1013<>""))=0,1,0)) | K146: =A146&"|"&B146
A147: sgc-2023-10 | B147: 1 | C147: SGC | D147: 2023 | E147: 10 | F147: 45405 | G147: DANIEL EDUARDO SOTO BERNAL | H147: 2 | I147: =IF(H147="","",H147/2) | J147: =IF(H147="",0,IF(SUMPRODUCT((Seguimientos!$A$2:$A$1013=A147)*(Seguimientos!$F$2:$F$1013=F147)*(Seguimientos!$B$2:$B$1013>B147)*(Seguimientos!$H$2:$H$1013<>""))=0,1,0)) | K147: =A147&"|"&B147 | L147: Se carga informe sobre las condiciones de los teléfonos de la UCundinamarca realizado por el área de Servicios Tecnológicos.
A148: sgc-2023-10 | B148: 2 | C148: SGC | D148: 2023 | E148: 10 | F148: 45497 | G148: DANIEL EDUARDO SOTO BERNAL | H148: 2 | I148: =IF(H148="","",H148/2) | J148: =IF(H148="",0,IF(SUMPRODUCT((Seguimientos!$A$2:$A$1013=A148)*(Seguimientos!$F$2:$F$1013=F148)*(Seguimientos!$B$2:$B$1013>B148)*(Seguimientos!$H$2:$H$1013<>""))=0,1,0)) | K148: =A148&"|"&B148 | L148: ACTIVIDAD COMPLETADA
A149: sgc-2023-10 | B149: 3 | C149: SGC | D149: 2023 | E149: 10 | F149: 45583 | G149: DANIEL EDUARDO SOTO BERNAL | H149: 2 | I149: =IF(H149="","",H149/2) | J149: =IF(H149="",0,IF(SUMPRODUCT((Seguimientos!$A$2:$A$1013=A149)*(Seguimientos!$F$2:$F$1013=F149)*(Seguimientos!$B$2:$B$1013>B149)*(Seguimientos!$H$2:$H$1013<>""))=0,1,0)) | K149: =A149&"|"&B149 | L149: ACTIVIDAD COMPLETADA
A150: sgc-2023-10 | B150: 4 | C150: SGC | D150: 2023 | E150: 10 | F150: 45777 | G150: DANIEL EDUARDO SOTO BERNAL | H150: 2 | I150: =IF(H150="","",H150/2) | J150: =IF(H150="",0,IF(SUMPRODUCT((Seguimientos!$A$2:$A$1013=A150)*(Seguimientos!$F$2:$F$1013=F150)*(Seguimientos!$B$2:$B$1013>B150)*(Seguimientos!$H$2:$H$1013<>""))=0,1,0)) | K150: =A150&"|"&B150 | L150: ACTIVIDAD COMPLETADA
A151: sgc-2023-10 | B151: 5 | C151: SGC | D151: 2023 | E151: 10 | F151: 45838 | G151: DANIEL EDUARDO SOTO BERNAL | H151: 2 | I151: =IF(H151="","",H151/2) | J151: =IF(H151="",0,IF(SUMPRODUCT((Seguimientos!$A$2:$A$1013=A151)*(Seguimientos!$F$2:$F$1013=F151)*(Seguimientos!$B$2:$B$1013>B151)*(Seguimientos!$H$2:$H$1013<>""))=0,1,0)) | K151: =A151&"|"&B151 | L151: ACTIVIDAD COMPLETADA
A152: sgc-2023-10 | B152: 6 | C152: SGC | D152: 2023 | E152: 10 | F152: 45930 | G152: JOAN IMAYINNE GALVIS MORENO | H152: 2 | I152: =IF(H152="","",H152/2) | J152: =IF(H152="",0,IF(SUMPRODUCT((Seguimientos!$A$2:$A$1013=A152)*(Seguimientos!$F$2:$F$1013=F152)*(Seguimientos!$B$2:$B$1013>B152)*(Seguimientos!$H$2:$H$1013<>""))=0,1,0)) | K152: =A152&"|"&B152 | L152: ACTIVIDAD COMPLETADA
A153: sgc-2023-10 | B153: 7 | C153: SGC | D153: 2023 | E153: 10 | F153: 46021 | G153: JOAN IMAYINNE GALVIS MORENO | H153: 2 | I153: =IF(H153="","",H153/2) | J153: =IF(H153="",0,IF(SUMPRODUCT((Seguimientos!$A$2:$A$1013=A153)*(Seguimientos!$F$2:$F$1013=F153)*(Seguimientos!$B$2:$B$1013>B153)*(Seguimientos!$H$2:$H$1013<>""))=0,1,0)) | K153: =A153&"|"&B153 | L153: ACTIVIDAD COMPLETADA
A154: sgc-2023-10 | B154: 8 | C154: SGC | D154: 2023 | E154: 10 | F154: 46142 | G154: JOAN IMAYINNE GALVIS MORENO | H154: 2 | I154: =IF(H154="","",H154/2) | J154: =IF(H154="",0,IF(SUMPRODUCT((Seguimientos!$A$2:$A$1013=A154)*(Seguimientos!$F$2:$F$1013=F154)*(Seguimientos!$B$2:$B$1013>B154)*(Seguimientos!$H$2:$H$1013<>""))=0,1,0)) | K154: =A154&"|"&B154 | L154: ACTIVIDAD COMPLETADA
A155: sgc-2023-10 | B155: 9 | C155: SGC | D155: 2023 | E155: 10 | F155: 46203 | G155: JOAN IMAYINNE GALVIS MORENO | H155: 2 | I155: =IF(H155="","",H155/2) | J155: =IF(H155="",0,IF(SUMPRODUCT((Seguimientos!$A$2:$A$1013=A155)*(Seguimientos!$F$2:$F$1013=F155)*(Seguimientos!$B$2:$B$1013>B155)*(Seguimientos!$H$2:$H$1013<>""))=0,1,0)) | K155: =A155&"|"&B155 | L155: ACTIVIDAD COMPLETADA
A156: sgc-2023-11 | B156: 1 | C156: SGC | D156: 2023 | E156: 11 | F156: 45405 | G156: DANIEL EDUARDO SOTO BERNAL | H156: 2 | I156: =IF(H156="","",H156/2) | J156: =IF(H156="",0,IF(SUMPRODUCT((Seguimientos!$A$2:$A$1013=A156)*(Seguimientos!$F$2:$F$1013=F156)*(Seguimientos!$B$2:$B$1013>B156)*(Seguimientos!$H$2:$H$1013<>""))=0,1,0)) | K156: =A156&"|"&B156 | L156: En la sesión del Comité de Prácticas Académicas y/o Experiencias Formativas del 08/02/2024, se llevó a cabo la presentación, estudio y discusión de los lineamientos proporcionados por el Comité. Estos lineamientos abordan diversas directrices relacionadas con el funcionamiento del comité, el proceso para realizar modificaciones, entre otros aspectos. En la sesión subsiguiente del Comité, realizada el 06/03/2024, se procedió a la socialización de dichos lineamientos para su posterior aprobación.
A157: sgc-2023-11 | B157: 2 | C157: SGC | D157: 2023 | E157: 11 | F157: 45497 | G157: DANIEL EDUARDO SOTO BERNAL | H157: 2 | I157: =IF(H157="","",H157/2) | J157: =IF(H157="",0,IF(SUMPRODUCT((Seguimientos!$A$2:$A$1013=A157)*(Seguimientos!$F$2:$F$1013=F157)*(Seguimientos!$B$2:$B$1013>B157)*(Seguimientos!$H$2:$H$1013<>""))=0,1,0)) | K157: =A157&"|"&B157 | L157: ACTIVIDAD COMPLETADA
A158: sgc-2023-11 | B158: 3 | C158: SGC | D158: 2023 | E158: 11 | F158: 45583 | G158: DANIEL EDUARDO SOTO BERNAL | H158: 2 | I158: =IF(H158="","",H158/2) | J158: =IF(H158="",0,IF(SUMPRODUCT((Seguimientos!$A$2:$A$1013=A158)*(Seguimientos!$F$2:$F$1013=F158)*(Seguimientos!$B$2:$B$1013>B158)*(Seguimientos!$H$2:$H$1013<>""))=0,1,0)) | K158: =A158&"|"&B158 | L158: ACTIVIDAD COMPLETADA
... A225: sgc-2023-18 | B225: 7 | C225: SGC | D225: 2023 | E225: 18 | F225: 46021 | G225: JOAN IMAYINNE GALVIS MORENO | H225: 1.5 | I225: =IF(H225="","",H225/2) | J225: =IF(H225="",0,IF(SUMPRODUCT((Seguimientos!$A$2:$A$1013=A225)*(Seguimientos!$F$2:$F$1013=F225)*(Seguimientos!$B$2:$B$1013>B225)*(Seguimientos!$H$2:$H$1013<>""))=0,1,0)) | K225: =A225&"|"&B225 | L225: Actividad pendiente por cumplir, No soportan evidencia.
A226: sgc-2023-18 | B226: 8 | C226: SGC | D226: 2023 | E226: 18 | F226: 46142 | G226: JOAN IMAYINNE GALVIS MORENO | H226: 1.5 | I226: =IF(H226="","",H226/2) | J226: =IF(H226="",0,IF(SUMPRODUCT((Seguimientos!$A$2:$A$1013=A226)*(Seguimientos!$F$2:$F$1013=F226)*(Seguimientos!$B$2:$B$1013>B226)*(Seguimientos!$H$2:$H$1013<>""))=0,1,0)) | K226: =A226&"|"&B226
A227: sgc-2023-18 | B227: 9 | C227: SGC | D227: 2023 | E227: 18 | F227: 46203 | G227: JOAN IMAYINNE GALVIS MORENO | H227: 1.5 | I227: =IF(H227="","",H227/2) | J227: =IF(H227="",0,IF(SUMPRODUCT((Seguimientos!$A$2:$A$1013=A227)*(Seguimientos!$F$2:$F$1013=F227)*(Seguimientos!$B$2:$B$1013>B227)*(Seguimientos!$H$2:$H$1013<>""))=0,1,0)) | K227: =A227&"|"&B227 | L227: Se remite por parte de la oficina de Dialogando con el Mundo informe sobre el seguimiento de las actividades que realiza, sin embargo no se evidencia si estos cumplimientos son efectivos para la academia o como estan siento valorados.
A228: sgc-2023-19 | B228: 1 | C228: SGC | D228: 2023 | E228: 19 | F228: 45405 | G228: DANIEL EDUARDO SOTO BERNAL | H228: 0 | I228: =IF(H228="","",H228/2) | J228: =IF(H228="",0,IF(SUMPRODUCT((Seguimientos!$A$2:$A$1013=A228)*(Seguimientos!$F$2:$F$1013=F228)*(Seguimientos!$B$2:$B$1013>B228)*(Seguimientos!$H$2:$H$1013<>""))=0,1,0)) | K228: =A228&"|"&B228 | L228: Actividad pendiente por cumplir, No soportan evidencia.
A229: sgc-2023-19 | B229: 2 | C229: SGC | D229: 2023 | E229: 19 | F229: 45497 | G229: DANIEL EDUARDO SOTO BERNAL | H229: 0 | I229: =IF(H229="","",H229/2) | J229: =IF(H229="",0,IF(SUMPRODUCT((Seguimientos!$A$2:$A$1013=A229)*(Seguimientos!$F$2:$F$1013=F229)*(Seguimientos!$B$2:$B$1013>B229)*(Seguimientos!$H$2:$H$1013<>""))=0,1,0)) | K229: =A229&"|"&B229 | L229: Actualmente esta actividad se encuentra en pausa, una vez, se surta el proceso para la emisión de los lineamientos y el manual, se reactivaran las mesas de trabajo con el área de equidad y diversidad y con el sistema de seguridad en el trabajo.
A230: sgc-2023-19 | B230: 3 | C230: SGC | D230: 2023 | E230: 19 | F230: 45583 | G230: DANIEL EDUARDO SOTO BERNAL | H230: 1 | I230: =IF(H230="","",H230/2) | J230: =IF(H230="",0,IF(SUMPRODUCT((Seguimientos!$A$2:$A$1013=A230)*(Seguimientos!$F$2:$F$1013=F230)*(Seguimientos!$B$2:$B$1013>B230)*(Seguimientos!$H$2:$H$1013<>""))=0,1,0)) | K230: =A230&"|"&B230 | L230: Conforme a la necesidad evidenciada y con la finalidad de dar cumplimiento a los criterios de accesibilidad a la planta física de la institución, la Jefatura de Recursos Físicos y Servicios Generales en articulación con la Dirección de Bienes y Servicios, Planeación Institucional y Equidad y Diversidad, ha avanzado en la adecuación de algunos escenarios de la planta física tendientes a garantizar el acceso a todos los miembros de la comunidad universitaria, entre los avances se cuentan los siguientes: 1. Señalización y adecuación de zonas de estacionamiento temporal para personas con movilidad reducida en la sede Fusagasugá, Centro Académico y Deportivo, Extensión Facatativá, Seccional Girardot, Extensión Soacha. 2. Elaboración y mantenimiento de rampas de acceso en la seccional Girardot y Fusagasugá. 3. Mantenimiento recurrente a ascensores con el objetivo de garantizar la continuidad de este servicio.
A231: sgc-2023-19 | B231: 4 | C231: SGC | D231: 2023 | E231: 19 | F231: 45777 | G231: DANIEL EDUARDO SOTO BERNAL | H231: 1 | I231: =IF(H231="","",H231/2) | J231: =IF(H231="",0,IF(SUMPRODUCT((Seguimientos!$A$2:$A$1013=A231)*(Seguimientos!$F$2:$F$1013=F231)*(Seguimientos!$B$2:$B$1013>B231)*(Seguimientos!$H$2:$H$1013<>""))=0,1,0)) | K231: =A231&"|"&B231 | L231: Actividad pendiente por cumplir, No soportan evidencia.
A232: sgc-2023-19 | B232: 5 | C232: SGC | D232: 2023 | E232: 19 | F232: 45838 | G232: DANIEL EDUARDO SOTO BERNAL | H232: 1 | I232: =IF(H232="","",H232/2) | J232: =IF(H232="",0,IF(SUMPRODUCT((Seguimientos!$A$2:$A$1013=A232)*(Seguimientos!$F$2:$F$1013=F232)*(Seguimientos!$B$2:$B$1013>B232)*(Seguimientos!$H$2:$H$1013<>""))=0,1,0)) | K232: =A232&"|"&B232 | L232: Actividad pendiente por cumplir, No soportan evidencia.
A233: sgc-2023-19 | B233: 6 | C233: SGC | D233: 2023 | E233: 19 | F233: 45930 | G233: JOAN IMAYINNE GALVIS MORENO | H233: 1 | I233: =IF(H233="","",H233/2) | J233: =IF(H233="",0,IF(SUMPRODUCT((Seguimientos!$A$2:$A$1013=A233)*(Seguimientos!$F$2:$F$1013=F233)*(Seguimientos!$B$2:$B$1013>B233)*(Seguimientos!$H$2:$H$1013<>""))=0,1,0)) | K233: =A233&"|"&B233 | L233: Actividad pendiente por cumplir, No soportan evidencia.
A234: sgc-2023-19 | B234: 7 | C234: SGC | D234: 2023 | E234: 19 | F234: 46021 | G234: JOAN IMAYINNE GALVIS MORENO | H234: 1 | I234: =IF(H234="","",H234/2) | J234: =IF(H234="",0,IF(SUMPRODUCT((Seguimientos!$A$2:$A$1013=A234)*(Seguimientos!$F$2:$F$1013=F234)*(Seguimientos!$B$2:$B$1013>B234)*(Seguimientos!$H$2:$H$1013<>""))=0,1,0)) | K234: =A234&"|"&B234 | L234: Actividad pendiente por cumplir, No soportan evidencia.
A235: sgc-2023-19 | B235: 8 | C235: SGC | D235: 2023 | E235: 19 | F235: 46142 | G235: JOAN IMAYINNE GALVIS MORENO | H235: 1 | I235: =IF(H235="","",H235/2) | J235: =IF(H235="",0,IF(SUMPRODUCT((Seguimientos!$A$2:$A$1013=A235)*(Seguimientos!$F$2:$F$1013=F235)*(Seguimientos!$B$2:$B$1013>B235)*(Seguimientos!$H$2:$H$1013<>""))=0,1,0)) | K235: =A235&"|"&B235
A236: sgc-2023-19 | B236: 9 | C236: SGC | D236: 2023 | E236: 19 | F236: 46203 | G236: JOAN IMAYINNE GALVIS MORENO | H236: 1 | I236: =IF(H236="","",H236/2) | J236: =IF(H236="",0,IF(SUMPRODUCT((Seguimientos!$A$2:$A$1013=A236)*(Seguimientos!$F$2:$F$1013=F236)*(Seguimientos!$B$2:$B$1013>B236)*(Seguimientos!$H$2:$H$1013<>""))=0,1,0)) | K236: =A236&"|"&B236
A237: sgc-2023-20 | B237: 1 | C237: SGC | D237: 2023 | E237: 20 | F237: 45405 | G237: DANIEL EDUARDO SOTO BERNAL | H237: 1 | I237: =IF(H237="","",H237/2) | J237: =IF(H237="",0,IF(SUMPRODUCT((Seguimientos!$A$2:$A$1013=A237)*(Seguimientos!$F$2:$F$1013=F237)*(Seguimientos!$B$2:$B$1013>B237)*(Seguimientos!$H$2:$H$1013<>""))=0,1,0)) | K237: =A237&"|"&B237 | L237: Se hace requerimiento al área de educación virtual y a distancia. En seguimiento,
A238: sgc-2023-20 | B238: 2 | C238: SGC | D238: 2023 | E238: 20 | F238: 45497 | G238: DANIEL EDUARDO SOTO BERNAL | H238: 1.5 | I238: =IF(H238="","",H238/2) | J238: =IF(H238="",0,IF(SUMPRODUCT((Seguimientos!$A$2:$A$1013=A238)*(Seguimientos!$F$2:$F$1013=F238)*(Seguimientos!$B$2:$B$1013>B238)*(Seguimientos!$H$2:$H$1013<>""))=0,1,0)) | K238: =A238&"|"&B238 | L238: En lo concerniente al Recuso Educativo Digital Las 4 Líneas de Defensa, Solicitado por la oficina de Control Interno de la Universidad de Cundinamarca, nos permitimos informar que el trabajo se inició la última semana del mes de mayo, la solicitante conoce y aprobó el contenido del RED diseñado. Se acordó fecha de entrega final para el 14 de agosto y hoy en día el estado de RED en mención.
A239: sgc-2023-20 | B239: 3 | C239: SGC | D239: 2023 | E239: 20 | F239: 45583 | G239: DANIEL EDUARDO SOTO BERNAL | H239: 1.5 | I239: =IF(H239="","",H239/2) | J239: =IF(H239="",0,IF(SUMPRODUCT((Seguimientos!$A$2:$A$1013=A239)*(Seguimientos!$F$2:$F$1013=F239)*(Seguimientos!$B$2:$B$1013>B239)*(Seguimientos!$H$2:$H$1013<>""))=0,1,0)) | K239: =A239&"|"&B239 | L239: El curso virtual, en el cual se profundice sobre las líneas de defensa en apoyo con la oficina de Educación Virtual y a Distancia, se entregó a la Oficina de Control Interno en la segunda semana del mes de noviembre de 2024, se hará la prueba piloto en funcionarios de la Dirección de Control Interno y posteriormente será aplicado en el modelo de contratación de los funcionarios, aplicado docente y estudiantes de carreras afines para su conocimiento y aprobación en MOOCs.
A240: sgc-2023-20 | B240: 4 | C240: SGC | D240: 2023 | E240: 20 | F240: 45777 | G240: DANIEL EDUARDO SOTO BERNAL | H240: 1.5 | I240: =IF(H240="","",H240/2) | J240: =IF(H240="",0,IF(SUMPRODUCT((Seguimientos!$A$2:$A$1013=A240)*(Seguimientos!$F$2:$F$1013=F240)*(Seguimientos!$B$2:$B$1013>B240)*(Seguimientos!$H$2:$H$1013<>""))=0,1,0)) | K240: =A240&"|"&B240 | L240: El curso virtual de lineas de defensa ya paso las pruebas pilotos por parte de control interno. Pendiente respuesta de Educacion Virtual y a distancia para las correcciones y entrega final,
A241: sgc-2023-20 | B241: 5 | C241: SGC | D241: 2023 | E241: 20 | F241: 45838 | G241: DANIEL EDUARDO SOTO BERNAL | H241: 1.5 | I241: =IF(H241="","",H241/2) | J241: =IF(H241="",0,IF(SUMPRODUCT((Seguimientos!$A$2:$A$1013=A241)*(Seguimientos!$F$2:$F$1013=F241)*(Seguimientos!$B$2:$B$1013>B241)*(Seguimientos!$H$2:$H$1013<>""))=0,1,0)) | K241: =A241&"|"&B241 | L241: Desde la Oficina de Educación Virtual y a Distancia se hace la entrega oficial del curso de líneas de defensa a la Dirección de Control Interno la cual espera lanzar en las aulas virtuales requisito de inducción y reinducción para personal administrativo y así tener este curso aprobado para la contratación.
A242: sgc-2023-20 | B242: 6 | C242: SGC | D242: 2023 | E242: 20 | F242: 45930 | G242: JOAN IMAYINNE GALVIS MORENO | H242: 1.5 | I242: =IF(H242="","",H242/2) | J242: =IF(H242="",0,IF(SUMPRODUCT((Seguimientos!$A$2:$A$1013=A242)*(Seguimientos!$F$2:$F$1013=F242)*(Seguimientos!$B$2:$B$1013>B242)*(Seguimientos!$H$2:$H$1013<>""))=0,1,0)) | K242: =A242&"|"&B242 | L242: Actividad pendiente por cumplir, No soportan evidencia.
A243: sgc-2023-20 | B243: 7 | C243: SGC | D243: 2023 | E243: 20 | F243: 46021 | G243: JOAN IMAYINNE GALVIS MORENO | H243: 1.5 | I243: =IF(H243="","",H243/2) | J243: =IF(H243="",0,IF(SUMPRODUCT((Seguimientos!$A$2:$A$1013=A243)*(Seguimientos!$F$2:$F$1013=F243)*(Seguimientos!$B$2:$B$1013>B243)*(Seguimientos!$H$2:$H$1013<>""))=0,1,0)) | K243: =A243&"|"&B243 | L243: Actividad pendiente por cumplir, No soportan evidencia.
A244: sgc-2023-20 | B244: 8 | C244: SGC | D244: 2023 | E244: 20 | F244: 46142 | G244: JOAN IMAYINNE GALVIS MORENO | H244: 1.5 | I244: =IF(H244="","",H244/2) | J244: =IF(H244="",0,IF(SUMPRODUCT((Seguimientos!$A$2:$A$1013=A244)*(Seguimientos!$F$2:$F$1013=F244)*(Seguimientos!$B$2:$B$1013>B244)*(Seguimientos!$H$2:$H$1013<>""))=0,1,0)) | K244: =A244&"|"&B244 | L244: Se encuentra en proceso de validación, con el fin de realizar su lanzamiento y puesta en funcionamiento.
A245: sgc-2023-20 | B245: 9 | C245: SGC | D245: 2023 | E245: 20 | F245: 46203 | G245: JOAN IMAYINNE GALVIS MORENO | H245: 1.5 | I245: =IF(H245="","",H245/2) | J245: =IF(H245="",0,IF(SUMPRODUCT((Seguimientos!$A$2:$A$1013=A245)*(Seguimientos!$F$2:$F$1013=F245)*(Seguimientos!$B$2:$B$1013>B245)*(Seguimientos!$H$2:$H$1013<>""))=0,1,0)) | K245: =A245&"|"&B245
A246: sgc-2023-21 | B246: 1 | C246: SGC | D246: 2023 | E246: 21 | F246: 45405 | G246: DANIEL EDUARDO SOTO BERNAL | H246: 2 | I246: =IF(H246="","",H246/2) | J246: =IF(H246="",0,IF(SUMPRODUCT((Seguimientos!$A$2:$A$1013=A246)*(Seguimientos!$F$2:$F$1013=F246)*(Seguimientos!$B$2:$B$1013>B246)*(Seguimientos!$H$2:$H$1013<>""))=0,1,0)) | K246: =A246&"|"&B246 | L246: Se aprueba Plan anual de auditoria 2024 basado en la metodología Universo de Auditoria basada en riesgos que establece el DAFP
A247: sgc-2023-21 | B247: 2 | C247: SGC | D247: 2023 | E247: 21 | F247: 45497 | G247: DANIEL EDUARDO SOTO BERNAL | H247: 2 | I247: =IF(H247="","",H247/2) | J247: =IF(H247="",0,IF(SUMPRODUCT((Seguimientos!$A$2:$A$1013=A247)*(Seguimientos!$F$2:$F$1013=F247)*(Seguimientos!$B$2:$B$1013>B247)*(Seguimientos!$H$2:$H$1013<>""))=0,1,0)) | K247: =A247&"|"&B247 | L247: ACTIVIDAD COMPLETADA
A248: sgc-2023-21 | B248: 3 | C248: SGC | D248: 2023 | E248: 21 | F248: 45583 | G248: DANIEL EDUARDO SOTO BERNAL | H248: 2 | I248: =IF(H248="","",H248/2) | J248: =IF(H248="",0,IF(SUMPRODUCT((Seguimientos!$A$2:$A$1013=A248)*(Seguimientos!$F$2:$F$1013=F248)*(Seguimientos!$B$2:$B$1013>B248)*(Seguimientos!$H$2:$H$1013<>""))=0,1,0)) | K248: =A248&"|"&B248 | L248: ACTIVIDAD COMPLETADA
A249: sgc-2023-21 | B249: 4 | C249: SGC | D249: 2023 | E249: 21 | F249: 45777 | G249: DANIEL EDUARDO SOTO BERNAL | H249: 2 | I249: =IF(H249="","",H249/2) | J249: =IF(H249="",0,IF(SUMPRODUCT((Seguimientos!$A$2:$A$1013=A249)*(Seguimientos!$F$2:$F$1013=F249)*(Seguimientos!$B$2:$B$1013>B249)*(Seguimientos!$H$2:$H$1013<>""))=0,1,0)) | K249: =A249&"|"&B249 | L249: ACTIVIDAD COMPLETADA
A250: sgc-2023-21 | B250: 5 | C250: SGC | D250: 2023 | E250: 21 | F250: 45838 | G250: DANIEL EDUARDO SOTO BERNAL | H250: 2 | I250: =IF(H250="","",H250/2) | J250: =IF(H250="",0,IF(SUMPRODUCT((Seguimientos!$A$2:$A$1013=A250)*(Seguimientos!$F$2:$F$1013=F250)*(Seguimientos!$B$2:$B$1013>B250)*(Seguimientos!$H$2:$H$1013<>""))=0,1,0)) | K250: =A250&"|"&B250 | L250: ACTIVIDAD COMPLETADA
A251: sgc-2023-21 | B251: 6 | C251: SGC | D251: 2023 | E251: 21 | F251: 45930 | G251: JOAN IMAYINNE GALVIS MORENO | H251: 2 | I251: =IF(H251="","",H251/2) | J251: =IF(H251="",0,IF(SUMPRODUCT((Seguimientos!$A$2:$A$1013=A251)*(Seguimientos!$F$2:$F$1013=F251)*(Seguimientos!$B$2:$B$1013>B251)*(Seguimientos!$H$2:$H$1013<>""))=0,1,0)) | K251: =A251&"|"&B251 | L251: ACTIVIDAD COMPLETADA
A252: sgc-2023-21 | B252: 7 | C252: SGC | D252: 2023 | E252: 21 | F252: 46021 | G252: JOAN IMAYINNE GALVIS MORENO | H252: 2 | I252: =IF(H252="","",H252/2) | J252: =IF(H252="",0,IF(SUMPRODUCT((Seguimientos!$A$2:$A$1013=A252)*(Seguimientos!$F$2:$F$1013=F252)*(Seguimientos!$B$2:$B$1013>B252)*(Seguimientos!$H$2:$H$1013<>""))=0,1,0)) | K252: =A252&"|"&B252 | L252: ACTIVIDAD COMPLETADA
A253: sgc-2023-21 | B253: 8 | C253: SGC | D253: 2023 | E253: 21 | F253: 46142 | G253: JOAN IMAYINNE GALVIS MORENO | H253: 2 | I253: =IF(H253="","",H253/2) | J253: =IF(H253="",0,IF(SUMPRODUCT((Seguimientos!$A$2:$A$1013=A253)*(Seguimientos!$F$2:$F$1013=F253)*(Seguimientos!$B$2:$B$1013>B253)*(Seguimientos!$H$2:$H$1013<>""))=0,1,0)) | K253: =A253&"|"&B253 | L253: ACTIVIDAD COMPLETADA
A254: sgc-2023-21 | B254: 9 | C254: SGC | D254: 2023 | E254: 21 | F254: 46203 | G254: JOAN IMAYINNE GALVIS MORENO | H254: 2 | I254: =IF(H254="","",H254/2) | J254: =IF(H254="",0,IF(SUMPRODUCT((Seguimientos!$A$2:$A$1013=A254)*(Seguimientos!$F$2:$F$1013=F254)*(Seguimientos!$B$2:$B$1013>B254)*(Seguimientos!$H$2:$H$1013<>""))=0,1,0)) | K254: =A254&"|"&B254 | L254: ACTIVIDAD COMPLETADA
...

Sheet Escala
A1: Calificación | B1: Estado | C1: Avance
A2: 0 | B2: Sin avance | C2: =A2/2
A3: 0.5 | B3: Avance mínimo | C3: =A3/2
A4: 1 | B4: Avance parcial | C4: =A4/2
A5: 1.5 | B5: Avance significativo | C5: =A5/2
A6: 2 | B6: Cumplida | C6: =A6/2
A8: Escala institucional de la RXD: 2 = 100 % (cumplida). Avance = calificación ÷ 2.
